Workbook

Sheet dataset
A1: Department | B1: Employee ID | C1: Position | D1: Job Function | E1: № | F1: Monthly Salary | G1: Base Salary (Monthly) | H1: Security Clearance Allowance | I1: Performance Bonus | J1: Salary Indexation (8%) | K1: Annual Salary | L1: KPI Bonus (%) | M1: Annual KPI Bonus Reserve | N1: Payroll Taxes (KPI Bonus) | O1: Annual Salary + KPI Bonus | P1: Vacation Reserve | Q1: Payroll Taxes (Vacation) | R1: 11-Month Salary | S1: Payroll Taxes (Salary) | T1: Health Insurance | U1: Total Payroll | V1: Total Payroll Taxes | W1: Total Compensation Cost
A2: Administration | B2: Emp_001 | C2: Chief Executive Officer | D2: =VLOOKUP(Payroll_Data_Analysis[[#This Row],[Position]],Position_Map!$A$2:$B$58,2,FALSE) -> Executive | E2: 1 | F2: 600000 | G2: 265000 | H2: =dataset!$G2*0.1 -> 26500 | I2: =dataset!$F2-dataset!$J2-dataset!$G2-dataset!$H2 -> 287300 | J2: =dataset!$G2*0.08 -> 21200 | K2: =dataset!$F2*12 -> 7200000 | L2: =IF(dataset!$G2>=200000,38%,IF(dataset!$G2<=145000,12.3%,)) -> 0.38 | M2: =dataset!$G2*L3*12 -> 391140 | N2: =IF(Payroll_Data_Analysis[[#This Row],[Annual KPI Bonus Reserve]]<=2979000,Payroll_Data_Analysis[[#This Row],[Annual KPI Bonus Reserve]]*0.302,2979000*0.302+(Payroll_Data_Analysis[[#This Row],[Annual KPI Bonus Reserve]]-2979000)*0.151) -> 118124.28 | O2: =dataset!$K2+dataset!$M2 -> 7591140 | P2: =Payroll_Data_Analysis[[#This Row],[Annual Salary + KPI Bonus]]/12/29.3*31 -> 669298.46 | Q2: =IF(Payroll_Data_Analysis[[#This Row],[Vacation Reserve]]<=2979000,Payroll_Data_Analysis[[#This Row],[Vacation Reserve]]*0.302,2979000*0.302+(Payroll_Data_Analysis[[#This Row],[Vacation Reserve]]-2979000)*0.151) -> 202128.14 | R2: =Payroll_Data_Analysis[[#This Row],[Monthly Salary]]*11 -> 6600000 | S2: =IF(Payroll_Data_Analysis[[#This Row],[11-Month Salary]]<=2979000,Payroll_Data_Analysis[[#This Row],[11-Month Salary]]*0.302,2979000*0.302+(Payroll_Data_Analysis[[#This Row],[11-Month Salary]]-2979000)*0.151) -> 1446429 | T2: =IF(Payroll_Data_Analysis[[#This Row],[Base Salary (Monthly)]]>=200000,69507,IF(Payroll_Data_Analysis[[#This Row],[Base Salary (Monthly)]]>=145000,52684,35103)) -> 69507 | U2: =Payroll_Data_Analysis[[#This Row],[Annual KPI Bonus Reserve]]+Payroll_Data_Analysis[[#This Row],[Vacation Reserve]]+Payroll_Data_Analysis[[#This Row],[11-Month Salary]] -> 7660438.5 | V2: =Payroll_Data_Analysis[[#This Row],[Payroll Taxes (KPI Bonus)]]+Payroll_Data_Analysis[[#This Row],[Payroll Taxes (Vacation)]]+Payroll_Data_Analysis[[#This Row],[Payroll Taxes (Salary)]] -> 1766681.4 | W2: =Payroll_Data_Analysis[[#This Row],[Total Payroll]]+Payroll_Data_Analysis[[#This Row],[Total Payroll Taxes]] -> 9427119.9
A3: Administration | B3: Emp_002 | C3: Assistant | D3: =VLOOKUP(Payroll_Data_Analysis[[#This Row],[Position]],Position_Map!$A$2:$B$58,2,FALSE) -> Administration | E3: 1 | F3: 231600 | G3: 145000 | I3: =dataset!$F3-dataset!$J3-dataset!$G3-dataset!$H3 -> 75000 | J3: =dataset!$G3*0.08 -> 11600 | K3: =dataset!$F3*12 -> 2779200 | L3: =IF(dataset!$G3>=200000,38%,IF(dataset!$G3<=145000,12.3%,)) -> 0.123 | M3: =dataset!$G3*L4*12 -> 214020 | N3: =IF(Payroll_Data_Analysis[[#This Row],[Annual KPI Bonus Reserve]]<=2979000,Payroll_Data_Analysis[[#This Row],[Annual KPI Bonus Reserve]]*0.302,2979000*0.302+(Payroll_Data_Analysis[[#This Row],[Annual KPI Bonus Reserve]]-2979000)*0.151) -> 64634.04 | O3: =dataset!$K3+dataset!$M3 -> 2993220 | P3: =Payroll_Data_Analysis[[#This Row],[Annual Salary + KPI Bonus]]/12/29.3*31 -> 263907.34 | Q3: =IF(Payroll_Data_Analysis[[#This Row],[Vacation Reserve]]<=2979000,Payroll_Data_Analysis[[#This Row],[Vacation Reserve]]*0.302,2979000*0.302+(Payroll_Data_Analysis[[#This Row],[Vacation Reserve]]-2979000)*0.151) -> 79700.016 | R3: =Payroll_Data_Analysis[[#This Row],[Monthly Salary]]*11 -> 2547600 | S3: =IF(Payroll_Data_Analysis[[#This Row],[11-Month Salary]]<=2979000,Payroll_Data_Analysis[[#This Row],[11-Month Salary]]*0.302,2979000*0.302+(Payroll_Data_Analysis[[#This Row],[11-Month Salary]]-2979000)*0.151) -> 769375.2 | T3: =IF(Payroll_Data_Analysis[[#This Row],[Base Salary (Monthly)]]>=200000,69507,IF(Payroll_Data_Analysis[[#This Row],[Base Salary (Monthly)]]>=145000,52684,35103)) -> 52684 | U3: =Payroll_Data_Analysis[[#This Row],[Annual KPI Bonus Reserve]]+Payroll_Data_Analysis[[#This Row],[Vacation Reserve]]+Payroll_Data_Analysis[[#This Row],[11-Month Salary]] -> 3025527.3 | V3: =Payroll_Data_Analysis[[#This Row],[Payroll Taxes (KPI Bonus)]]+Payroll_Data_Analysis[[#This Row],[Payroll Taxes (Vacation)]]+Payroll_Data_Analysis[[#This Row],[Payroll Taxes (Salary)]] -> 913709.26 | W3: =Payroll_Data_Analysis[[#This Row],[Total Payroll]]+Payroll_Data_Analysis[[#This Row],[Total Payroll Taxes]] -> 3939236.6
A4: Administration | B4: Emp_003 | C4: Advisor | D4: =VLOOKUP(Payroll_Data_Analysis[[#This Row],[Position]],Position_Map!$A$2:$B$58,2,FALSE) -> Professional | E4: 1 | F4: 288000 | G4: 145000 | I4: =dataset!$F4-dataset!$J4-dataset!$G4-dataset!$H4 -> 131400 | J4: =dataset!$G4*0.08 -> 11600 | K4: =dataset!$F4*12 -> 3456000 | L4: =IF(dataset!$G4>=200000,38%,IF(dataset!$G4<=145000,12.3%,)) -> 0.123 | M4: =dataset!$G4*L5*12 -> 214020 | N4: =IF(Payroll_Data_Analysis[[#This Row],[Annual KPI Bonus Reserve]]<=2979000,Payroll_Data_Analysis[[#This Row],[Annual KPI Bonus Reserve]]*0.302,2979000*0.302+(Payroll_Data_Analysis[[#This Row],[Annual KPI Bonus Reserve]]-2979000)*0.151) -> 64634.04 | O4: =dataset!$K4+dataset!$M4 -> 3670020 | P4: =Payroll_Data_Analysis[[#This Row],[Annual Salary + KPI Bonus]]/12/29.3*31 -> 323579.69 | Q4: =IF(Payroll_Data_Analysis[[#This Row],[Vacation Reserve]]<=2979000,Payroll_Data_Analysis[[#This Row],[Vacation Reserve]]*0.302,2979000*0.302+(Payroll_Data_Analysis[[#This Row],[Vacation Reserve]]-2979000)*0.151) -> 97721.067 | R4: =Payroll_Data_Analysis[[#This Row],[Monthly Salary]]*11 -> 3168000 | S4: =IF(Payroll_Data_Analysis[[#This Row],[11-Month Salary]]<=2979000,Payroll_Data_Analysis[[#This Row],[11-Month Salary]]*0.302,2979000*0.302+(Payroll_Data_Analysis[[#This Row],[11-Month Salary]]-2979000)*0.151) -> 928197 | T4: =IF(Payroll_Data_Analysis[[#This Row],[Base Salary (Monthly)]]>=200000,69507,IF(Payroll_Data_Analysis[[#This Row],[Base Salary (Monthly)]]>=145000,52684,35103)) -> 52684 | U4: =Payroll_Data_Analysis[[#This Row],[Annual KPI Bonus Reserve]]+Payroll_Data_Analysis[[#This Row],[Vacation Reserve]]+Payroll_Data_Analysis[[#This Row],[11-Month Salary]] -> 3705599.7 | V4: =Payroll_Data_Analysis[[#This Row],[Payroll Taxes (KPI Bonus)]]+Payroll_Data_Analysis[[#This Row],[Payroll Taxes (Vacation)]]+Payroll_Data_Analysis[[#This Row],[Payroll Taxes (Salary)]] -> 1090552.1 | W4: =Payroll_Data_Analysis[[#This Row],[Total Payroll]]+Payroll_Data_Analysis[[#This Row],[Total Payroll Taxes]] -> 4796151.8
A5: Administration | B5: Emp_004 | C5: Advisor | D5: =VLOOKUP(Payroll_Data_Analysis[[#This Row],[Position]],Position_Map!$A$2:$B$58,2,FALSE) -> Professional | E5: 1 | F5: 120000 | G5: 100000 | I5: =dataset!$F5-dataset!$J5-dataset!$G5-dataset!$H5 -> 12000 | J5: =dataset!$G5*0.08 -> 8000 | K5: =dataset!$F5*12 -> 1440000 | L5: =IF(dataset!$G5>=200000,38%,IF(dataset!$G5<=145000,12.3%,)) -> 0.123 | M5: =dataset!$G5*L6*12 -> 456000 | N5: =IF(Payroll_Data_Analysis[[#This Row],[Annual KPI Bonus Reserve]]<=2979000,Payroll_Data_Analysis[[#This Row],[Annual KPI Bonus Reserve]]*0.302,2979000*0.302+(Payroll_Data_Analysis[[#This Row],[Annual KPI Bonus Reserve]]-2979000)*0.151) -> 137712 | O5: =dataset!$K5+dataset!$M5 -> 1896000 | P5: =Payroll_Data_Analysis[[#This Row],[Annual Salary + KPI Bonus]]/12/29.3*31 -> 167167.24 | Q5: =IF(Payroll_Data_Analysis[[#This Row],[Vacation Reserve]]<=2979000,Payroll_Data_Analysis[[#This Row],[Vacation Reserve]]*0.302,2979000*0.302+(Payroll_Data_Analysis[[#This Row],[Vacation Reserve]]-2979000)*0.151) -> 50484.505 | R5: =Payroll_Data_Analysis[[#This Row],[Monthly Salary]]*11 -> 1320000 | S5: =IF(Payroll_Data_Analysis[[#This Row],[11-Month Salary]]<=2979000,Payroll_Data_Analysis[[#This Row],[11-Month Salary]]*0.302,2979000*0.302+(Payroll_Data_Analysis[[#This Row],[11-Month Salary]]-2979000)*0.151) -> 398640 | T5: =IF(Payroll_Data_Analysis[[#This Row],[Base Salary (Monthly)]]>=200000,69507,IF(Payroll_Data_Analysis[[#This Row],[Base Salary (Monthly)]]>=145000,52684,35103)) -> 35103 | U5: =Payroll_Data_Analysis[[#This Row],[Annual KPI Bonus Reserve]]+Payroll_Data_Analysis[[#This Row],[Vacation Reserve]]+Payroll_Data_Analysis[[#This Row],[11-Month Salary]] -> 1943167.2 | V5: =Payroll_Data_Analysis[[#This Row],[Payroll Taxes (KPI Bonus)]]+Payroll_Data_Analysis[[#This Row],[Payroll Taxes (Vacation)]]+Payroll_Data_Analysis[[#This Row],[Payroll Taxes (Salary)]] -> 586836.51 | W5: =Payroll_Data_Analysis[[#This Row],[Total Payroll]]+Payroll_Data_Analysis[[#This Row],[Total Payroll Taxes]] -> 2530003.7
A6: Administration | B6: Emp_005 | C6: First Deputy CEO – Department Director | D6: =VLOOKUP(Payroll_Data_Analysis[[#This Row],[Position]],Position_Map!$A$2:$B$58,2,FALSE) -> Executive | E6: 1 | F6: 396000 | G6: 200000 | I6: =dataset!$F6-dataset!$J6-dataset!$G6-dataset!$H6 -> 180000 | J6: =dataset!$G6*0.08 -> 16000 | K6: =dataset!$F6*12 -> 4752000 | L6: =IF(dataset!$G6>=200000,38%,IF(dataset!$G6<=145000,12.3%,)) -> 0.38 | M6: =dataset!$G6*L7*12 -> 912000 | N6: =IF(Payroll_Data_Analysis[[#This Row],[Annual KPI Bonus Reserve]]<=2979000,Payroll_Data_Analysis[[#This Row],[Annual KPI Bonus Reserve]]*0.302,2979000*0.302+(Payroll_Data_Analysis[[#This Row],[Annual KPI Bonus Reserve]]-2979000)*0.151) -> 275424 | O6: =dataset!$K6+dataset!$M6 -> 5664000 | P6: =Payroll_Data_Analysis[[#This Row],[Annual Salary + KPI Bonus]]/12/29.3*31 -> 499385.67 | Q6: =IF(Payroll_Data_Analysis[[#This Row],[Vacation Reserve]]<=2979000,Payroll_Data_Analysis[[#This Row],[Vacation Reserve]]*0.302,2979000*0.302+(Payroll_Data_Analysis[[#This Row],[Vacation Reserve]]-2979000)*0.151) -> 150814.47 | R6: =Payroll_Data_Analysis[[#This Row],[Monthly Salary]]*11 -> 4356000 | S6: =IF(Payroll_Data_Analysis[[#This Row],[11-Month Salary]]<=2979000,Payroll_Data_Analysis[[#This Row],[11-Month Salary]]*0.302,2979000*0.302+(Payroll_Data_Analysis[[#This Row],[11-Month Salary]]-2979000)*0.151) -> 1107585 | T6: =IF(Payroll_Data_Analysis[[#This Row],[Base Salary (Monthly)]]>=200000,69507,IF(Payroll_Data_Analysis[[#This Row],[Base Salary (Monthly)]]>=145000,52684,35103)) -> 69507 | U6: =Payroll_Data_Analysis[[#This Row],[Annual KPI Bonus Reserve]]+Payroll_Data_Analysis[[#This Row],[Vacation Reserve]]+Payroll_Data_Analysis[[#This Row],[11-Month Salary]] -> 5767385.7 | V6: =Payroll_Data_Analysis[[#This Row],[Payroll Taxes (KPI Bonus)]]+Payroll_Data_Analysis[[#This Row],[Payroll Taxes (Vacation)]]+Payroll_Data_Analysis[[#This Row],[Payroll Taxes (Salary)]] -> 1533823.5 | W6: =Payroll_Data_Analysis[[#This Row],[Total Payroll]]+Payroll_Data_Analysis[[#This Row],[Total Payroll Taxes]] -> 7301209.1
A7: Administration | B7: Emp_006 | C7: Advisor to the First Deputy CEO – Department Director | D7: =VLOOKUP(Payroll_Data_Analysis[[#This Row],[Position]],Position_Map!$A$2:$B$58,2,FALSE) -> Professional | E7: 1 | F7: 336000 | G7: 200000 | I7: =dataset!$F7-dataset!$J7-dataset!$G7-dataset!$H7 -> 120000 | J7: =dataset!$G7*0.08 -> 16000 | K7: =dataset!$F7*12 -> 4032000 | L7: =IF(dataset!$G7>=200000,38%,IF(dataset!$G7<=145000,12.3%,)) -> 0.38 | M7: =dataset!$G7*L8*12 -> 295200 | N7: =IF(Payroll_Data_Analysis[[#This Row],[Annual KPI Bonus Reserve]]<=2979000,Payroll_Data_Analysis[[#This Row],[Annual KPI Bonus Reserve]]*0.302,2979000*0.302+(Payroll_Data_Analysis[[#This Row],[Annual KPI Bonus Reserve]]-2979000)*0.151) -> 89150.4 | O7: =dataset!$K7+dataset!$M7 -> 4327200 | P7: =Payroll_Data_Analysis[[#This Row],[Annual Salary + KPI Bonus]]/12/29.3*31 -> 381522.18 | Q7: =IF(Payroll_Data_Analysis[[#This Row],[Vacation Reserve]]<=2979000,Payroll_Data_Analysis[[#This Row],[Vacation Reserve]]*0.302,2979000*0.302+(Payroll_Data_Analysis[[#This Row],[Vacation Reserve]]-2979000)*0.151) -> 115219.7 | R7: =Payroll_Data_Analysis[[#This Row],[Monthly Salary]]*11 -> 3696000 | S7: =IF(Payroll_Data_Analysis[[#This Row],[11-Month Salary]]<=2979000,Payroll_Data_Analysis[[#This Row],[11-Month Salary]]*0.302,2979000*0.302+(Payroll_Data_Analysis[[#This Row],[11-Month Salary]]-2979000)*0.151) -> 1007925 | T7: =IF(Payroll_Data_Analysis[[#This Row],[Base Salary (Monthly)]]>=200000,69507,IF(Payroll_Data_Analysis[[#This Row],[Base Salary (Monthly)]]>=145000,52684,35103)) -> 69507 | U7: =Payroll_Data_Analysis[[#This Row],[Annual KPI Bonus Reserve]]+Payroll_Data_Analysis[[#This Row],[Vacation Reserve]]+Payroll_Data_Analysis[[#This Row],[11-Month Salary]] -> 4372722.2 | V7: =Payroll_Data_Analysis[[#This Row],[Payroll Taxes (KPI Bonus)]]+Payroll_Data_Analysis[[#This Row],[Payroll Taxes (Vacation)]]+Payroll_Data_Analysis[[#This Row],[Payroll Taxes (Salary)]] -> 1212295.1 | W7: =Payroll_Data_Analysis[[#This Row],[Total Payroll]]+Payroll_Data_Analysis[[#This Row],[Total Payroll Taxes]] -> 5585017.3
A8: Administration | B8: Emp_007 | C8: Department Director Assistant | D8: =VLOOKUP(Payroll_Data_Analysis[[#This Row],[Position]],Position_Map!$A$2:$B$58,2,FALSE) -> Administration | E8: 1 | F8: 281000 | G8: 145000 | I8: =dataset!$F8-dataset!$J8-dataset!$G8-dataset!$H8 -> 124400 | J8: =dataset!$G8*0.08 -> 11600 | K8: =dataset!$F8*12 -> 3372000 | L8: =IF(dataset!$G8>=200000,38%,IF(dataset!$G8<=145000,12.3%,)) -> 0.123 | M8: =dataset!$G8*L9*12 -> 214020 | N8: =IF(Payroll_Data_Analysis[[#This Row],[Annual KPI Bonus Reserve]]<=2979000,Payroll_Data_Analysis[[#This Row],[Annual KPI Bonus Reserve]]*0.302,2979000*0.302+(Payroll_Data_Analysis[[#This Row],[Annual KPI Bonus Reserve]]-2979000)*0.151) -> 64634.04 | O8: =dataset!$K8+dataset!$M8 -> 3586020 | P8: =Payroll_Data_Analysis[[#This Row],[Annual Salary + KPI Bonus]]/12/29.3*31 -> 316173.55 | Q8: =IF(Payroll_Data_Analysis[[#This Row],[Vacation Reserve]]<=2979000,Payroll_Data_Analysis[[#This Row],[Vacation Reserve]]*0.302,2979000*0.302+(Payroll_Data_Analysis[[#This Row],[Vacation Reserve]]-2979000)*0.151) -> 95484.412 | R8: =Payroll_Data_Analysis[[#This Row],[Monthly Salary]]*11 -> 3091000 | S8: =IF(Payroll_Data_Analysis[[#This Row],[11-Month Salary]]<=2979000,Payroll_Data_Analysis[[#This Row],[11-Month Salary]]*0.302,2979000*0.302+(Payroll_Data_Analysis[[#This Row],[11-Month Salary]]-2979000)*0.151) -> 916570 | T8: =IF(Payroll_Data_Analysis[[#This Row],[Base Salary (Monthly)]]>=200000,69507,IF(Payroll_Data_Analysis[[#This Row],[Base Salary (Monthly)]]>=145000,52684,35103)) -> 52684 | U8: =Payroll_Data_Analysis[[#This Row],[Annual KPI Bonus Reserve]]+Payroll_Data_Analysis[[#This Row],[Vacation Reserve]]+Payroll_Data_Analysis[[#This Row],[11-Month Salary]] -> 3621193.5 | V8: =Payroll_Data_Analysis[[#This Row],[Payroll Taxes (KPI Bonus)]]+Payroll_Data_Analysis[[#This Row],[Payroll Taxes (Vacation)]]+Payroll_Data_Analysis[[#This Row],[Payroll Taxes (Salary)]] -> 1076688.5 | W8: =Payroll_Data_Analysis[[#This Row],[Total Payroll]]+Payroll_Data_Analysis[[#This Row],[Total Payroll Taxes]] -> 4697882
A9: Administration | B9: Emp_008 | C9: Assistant | D9: =VLOOKUP(Payroll_Data_Analysis[[#This Row],[Position]],Position_Map!$A$2:$B$58,2,FALSE) -> Administration | E9: 1 | F9: 231600 | G9: 145000 | I9: =dataset!$F9-dataset!$J9-dataset!$G9-dataset!$H9 -> 75000 | J9: =dataset!$G9*0.08 -> 11600 | K9: =dataset!$F9*12 -> 2779200 | L9: =IF(dataset!$G9>=200000,38%,IF(dataset!$G9<=145000,12.3%,)) -> 0.123 | M9: =dataset!$G9*L10*12 -> 214020 | N9: =IF(Payroll_Data_Analysis[[#This Row],[Annual KPI Bonus Reserve]]<=2979000,Payroll_Data_Analysis[[#This Row],[Annual KPI Bonus Reserve]]*0.302,2979000*0.302+(Payroll_Data_Analysis[[#This Row],[Annual KPI Bonus Reserve]]-2979000)*0.151) -> 64634.04 | O9: =dataset!$K9+dataset!$M9 -> 2993220 | P9: =Payroll_Data_Analysis[[#This Row],[Annual Salary + KPI Bonus]]/12/29.3*31 -> 263907.34 | Q9: =IF(Payroll_Data_Analysis[[#This Row],[Vacation Reserve]]<=2979000,Payroll_Data_Analysis[[#This Row],[Vacation Reserve]]*0.302,2979000*0.302+(Payroll_Data_Analysis[[#This Row],[Vacation Reserve]]-2979000)*0.151) -> 79700.016 | R9: =Payroll_Data_Analysis[[#This Row],[Monthly Salary]]*11 -> 2547600 | S9: =IF(Payroll_Data_Analysis[[#This Row],[11-Month Salary]]<=2979000,Payroll_Data_Analysis[[#This Row],[11-Month Salary]]*0.302,2979000*0.302+(Payroll_Data_Analysis[[#This Row],[11-Month Salary]]-2979000)*0.151) -> 769375.2 | T9: =IF(Payroll_Data_Analysis[[#This Row],[Base Salary (Monthly)]]>=200000,69507,IF(Payroll_Data_Analysis[[#This Row],[Base Salary (Monthly)]]>=145000,52684,35103)) -> 52684 | U9: =Payroll_Data_Analysis[[#This Row],[Annual KPI Bonus Reserve]]+Payroll_Data_Analysis[[#This Row],[Vacation Reserve]]+Payroll_Data_Analysis[[#This Row],[11-Month Salary]] -> 3025527.3 | V9: =Payroll_Data_Analysis[[#This Row],[Payroll Taxes (KPI Bonus)]]+Payroll_Data_Analysis[[#This Row],[Payroll Taxes (Vacation)]]+Payroll_Data_Analysis[[#This Row],[Payroll Taxes (Salary)]] -> 913709.26 | W9: =Payroll_Data_Analysis[[#This Row],[Total Payroll]]+Payroll_Data_Analysis[[#This Row],[Total Payroll Taxes]] -> 3939236.6
A10: Pricing & Accounting | B10: Emp_009 | C10: Department Manager | D10: =VLOOKUP(Payroll_Data_Analysis[[#This Row],[Position]],Position_Map!$A$2:$B$58,2,FALSE) -> Management | E10: 1 | F10: 286000 | G10: 145000 | I10: =dataset!$F10-dataset!$J10-dataset!$G10-dataset!$H10 -> 129400 | J10: =dataset!$G10*0.08 -> 11600 | K10: =dataset!$F10*12 -> 3432000 | L10: =IF(dataset!$G10>=200000,38%,IF(dataset!$G10<=145000,12.3%,)) -> 0.123 | M10: =dataset!$G10*L11*12 -> 214020 | N10: =IF(Payroll_Data_Analysis[[#This Row],[Annual KPI Bonus Reserve]]<=2979000,Payroll_Data_Analysis[[#This Row],[Annual KPI Bonus Reserve]]*0.302,2979000*0.302+(Payroll_Data_Analysis[[#This Row],[Annual KPI Bonus Reserve]]-2979000)*0.151) -> 64634.04 | O10: =dataset!$K10+dataset!$M10 -> 3646020 | P10: =Payroll_Data_Analysis[[#This Row],[Annual Salary + KPI Bonus]]/12/29.3*31 -> 321463.65 | Q10: =IF(Payroll_Data_Analysis[[#This Row],[Vacation Reserve]]<=2979000,Payroll_Data_Analysis[[#This Row],[Vacation Reserve]]*0.302,2979000*0.302+(Payroll_Data_Analysis[[#This Row],[Vacation Reserve]]-2979000)*0.151) -> 97082.023 | R10: =Payroll_Data_Analysis[[#This Row],[Monthly Salary]]*11 -> 3146000 | S10: =IF(Payroll_Data_Analysis[[#This Row],[11-Month Salary]]<=2979000,Payroll_Data_Analysis[[#This Row],[11-Month Salary]]*0.302,2979000*0.302+(Payroll_Data_Analysis[[#This Row],[11-Month Salary]]-2979000)*0.151) -> 924875 | T10: =IF(Payroll_Data_Analysis[[#This Row],[Base Salary (Monthly)]]>=200000,69507,IF(Payroll_Data_Analysis[[#This Row],[Base Salary (Monthly)]]>=145000,52684,35103)) -> 52684 | U10: =Payroll_Data_Analysis[[#This Row],[Annual KPI Bonus Reserve]]+Payroll_Data_Analysis[[#This Row],[Vacation Reserve]]+Payroll_Data_Analysis[[#This Row],[11-Month Salary]] -> 3681483.7 | V10: =Payroll_Data_Analysis[[#This Row],[Payroll Taxes (KPI Bonus)]]+Payroll_Data_Analysis[[#This Row],[Payroll Taxes (Vacation)]]+Payroll_Data_Analysis[[#This Row],[Payroll Taxes (Salary)]] -> 1086591.1 | W10: =Payroll_Data_Analysis[[#This Row],[Total Payroll]]+Payroll_Data_Analysis[[#This Row],[Total Payroll Taxes]] -> 4768074.7
A11: Pricing & Accounting | B11: Emp_010 | C11: Deputy Department Manager | D11: =VLOOKUP(Payroll_Data_Analysis[[#This Row],[Position]],Position_Map!$A$2:$B$58,2,FALSE) -> Management | E11: 1 | F11: 186600 | G11: 145000 | I11: =dataset!$F11-dataset!$J11-dataset!$G11-dataset!$H11 -> 30000 | J11: =dataset!$G11*0.08 -> 11600 | K11: =dataset!$F11*12 -> 2239200 | L11: =IF(dataset!$G11>=200000,38%,IF(dataset!$G11<=145000,12.3%,)) -> 0.123 | M11: =dataset!$G11*L12*12 -> 214020 | N11: =IF(Payroll_Data_Analysis[[#This Row],[Annual KPI Bonus Reserve]]<=2979000,Payroll_Data_Analysis[[#This Row],[Annual KPI Bonus Reserve]]*0.302,2979000*0.302+(Payroll_Data_Analysis[[#This Row],[Annual KPI Bonus Reserve]]-2979000)*0.151) -> 64634.04 | O11: =dataset!$K11+dataset!$M11 -> 2453220 | P11: =Payroll_Data_Analysis[[#This Row],[Annual Salary + KPI Bonus]]/12/29.3*31 -> 216296.42 | Q11: =IF(Payroll_Data_Analysis[[#This Row],[Vacation Reserve]]<=2979000,Payroll_Data_Analysis[[#This Row],[Vacation Reserve]]*0.302,2979000*0.302+(Payroll_Data_Analysis[[#This Row],[Vacation Reserve]]-2979000)*0.151) -> 65321.518 | R11: =Payroll_Data_Analysis[[#This Row],[Monthly Salary]]*11 -> 2052600 | S11: =IF(Payroll_Data_Analysis[[#This Row],[11-Month Salary]]<=2979000,Payroll_Data_Analysis[[#This Row],[11-Month Salary]]*0.302,2979000*0.302+(Payroll_Data_Analysis[[#This Row],[11-Month Salary]]-2979000)*0.151) -> 619885.2 | T11: =IF(Payroll_Data_Analysis[[#This Row],[Base Salary (Monthly)]]>=200000,69507,IF(Payroll_Data_Analysis[[#This Row],[Base Salary (Monthly)]]>=145000,52684,35103)) -> 52684 | U11: =Payroll_Data_Analysis[[#This Row],[Annual KPI Bonus Reserve]]+Payroll_Data_Analysis[[#This Row],[Vacation Reserve]]+Payroll_Data_Analysis[[#This Row],[11-Month Salary]] -> 2482916.4 | V11: =Payroll_Data_Analysis[[#This Row],[Payroll Taxes (KPI Bonus)]]+Payroll_Data_Analysis[[#This Row],[Payroll Taxes (Vacation)]]+Payroll_Data_Analysis[[#This Row],[Payroll Taxes (Salary)]] -> 749840.76 | W11: =Payroll_Data_Analysis[[#This Row],[Total Payroll]]+Payroll_Data_Analysis[[#This Row],[Total Payroll Taxes]] -> 3232757.2
A12: Pricing & Accounting | B12: Emp_011 | C12: Deputy Department Manager | D12: =VLOOKUP(Payroll_Data_Analysis[[#This Row],[Position]],Position_Map!$A$2:$B$58,2,FALSE) -> Management | E12: 1 | F12: 158000 | G12: 100000 | I12: =dataset!$F12-dataset!$J12-dataset!$G12-dataset!$H12 -> 50000 | J12: =dataset!$G12*0.08 -> 8000 | K12: =dataset!$F12*12 -> 1896000 | L12: =IF(dataset!$G12>=200000,38%,IF(dataset!$G12<=145000,12.3%,)) -> 0.123 | M12: =dataset!$G12*L13*12 -> 147600 | N12: =IF(Payroll_Data_Analysis[[#This Row],[Annual KPI Bonus Reserve]]<=2979000,Payroll_Data_Analysis[[#This Row],[Annual KPI Bonus Reserve]]*0.302,2979000*0.302+(Payroll_Data_Analysis[[#This Row],[Annual KPI Bonus Reserve]]-2979000)*0.151) -> 44575.2 | O12: =dataset!$K12+dataset!$M12 -> 2043600 | P12: =Payroll_Data_Analysis[[#This Row],[Annual Salary + KPI Bonus]]/12/29.3*31 -> 180180.89 | Q12: =IF(Payroll_Data_Analysis[[#This Row],[Vacation Reserve]]<=2979000,Payroll_Data_Analysis[[#This Row],[Vacation Reserve]]*0.302,2979000*0.302+(Payroll_Data_Analysis[[#This Row],[Vacation Reserve]]-2979000)*0.151) -> 54414.628 | R12: =Payroll_Data_Analysis[[#This Row],[Monthly Salary]]*11 -> 1738000 | S12: =IF(Payroll_Data_Analysis[[#This Row],[11-Month Salary]]<=2979000,Payroll_Data_Analysis[[#This Row],[11-Month Salary]]*0.302,2979000*0.302+(Payroll_Data_Analysis[[#This Row],[11-Month Salary]]-2979000)*0.151) -> 524876 | T12: =IF(Payroll_Data_Analysis[[#This Row],[Base Salary (Monthly)]]>=200000,69507,IF(Payroll_Data_Analysis[[#This Row],[Base Salary (Monthly)]]>=145000,52684,35103)) -> 35103 | U12: =Payroll_Data_Analysis[[#This Row],[Annual KPI Bonus Reserve]]+Payroll_Data_Analysis[[#This Row],[Vacation Reserve]]+Payroll_Data_Analysis[[#This Row],[11-Month Salary]] -> 2065780.9 | V12: =Payroll_Data_Analysis[[#This Row],[Payroll Taxes (KPI Bonus)]]+Payroll_Data_Analysis[[#This Row],[Payroll Taxes (Vacation)]]+Payroll_Data_Analysis[[#This Row],[Payroll Taxes (Salary)]] -> 623865.83 | W12: =Payroll_Data_Analysis[[#This Row],[Total Payroll]]+Payroll_Data_Analysis[[#This Row],[Total Payroll Taxes]] -> 2689646.7
A13: Pricing & Accounting | B13: Emp_012 | C13: Senior Specialist | D13: =VLOOKUP(Payroll_Data_Analysis[[#This Row],[Position]],Position_Map!$A$2:$B$58,2,FALSE) -> Professional | E13: 1 | F13: 94800 | G13: 60000 | I13: =dataset!$F13-dataset!$J13-dataset!$G13-dataset!$H13 -> 30000 | J13: =dataset!$G13*0.08 -> 4800 | K13: =dataset!$F13*12 -> 1137600 | L13: =IF(dataset!$G13>=200000,38%,IF(dataset!$G13<=145000,12.3%,)) -> 0.123 | M13: =dataset!$G13*L14*12 -> 88560 | N13: =IF(Payroll_Data_Analysis[[#This Row],[Annual KPI Bonus Reserve]]<=2979000,Payroll_Data_Analysis[[#This Row],[Annual KPI Bonus Reserve]]*0.302,2979000*0.302+(Payroll_Data_Analysis[[#This Row],[Annual KPI Bonus Reserve]]-2979000)*0.151) -> 26745.12 | O13: =dataset!$K13+dataset!$M13 -> 1226160 | P13: =Payroll_Data_Analysis[[#This Row],[Annual Salary + KPI Bonus]]/12/29.3*31 -> 108108.53 | Q13: =IF(Payroll_Data_Analysis[[#This Row],[Vacation Reserve]]<=2979000,Payroll_Data_Analysis[[#This Row],[Vacation Reserve]]*0.302,2979000*0.302+(Payroll_Data_Analysis[[#This Row],[Vacation Reserve]]-2979000)*0.151) -> 32648.777 | R13: =Payroll_Data_Analysis[[#This Row],[Monthly Salary]]*11 -> 1042800 | S13: =IF(Payroll_Data_Analysis[[#This Row],[11-Month Salary]]<=2979000,Payroll_Data_Analysis[[#This Row],[11-Month Salary]]*0.302,2979000*0.302+(Payroll_Data_Analysis[[#This Row],[11-Month Salary]]-2979000)*0.151) -> 314925.6 | T13: =IF(Payroll_Data_Analysis[[#This Row],[Base Salary (Monthly)]]>=200000,69507,IF(Payroll_Data_Analysis[[#This Row],[Base Salary (Monthly)]]>=145000,52684,35103)) -> 35103 | U13: =Payroll_Data_Analysis[[#This Row],[Annual KPI Bonus Reserve]]+Payroll_Data_Analysis[[#This Row],[Vacation Reserve]]+Payroll_Data_Analysis[[#This Row],[11-Month Salary]] -> 1239468.5 | V13: =Payroll_Data_Analysis[[#This Row],[Payroll Taxes (KPI Bonus)]]+Payroll_Data_Analysis[[#This Row],[Payroll Taxes (Vacation)]]+Payroll_Data_Analysis[[#This Row],[Payroll Taxes (Salary)]] -> 374319.5 | W13: =Payroll_Data_Analysis[[#This Row],[Total Payroll]]+Payroll_Data_Analysis[[#This Row],[Total Payroll Taxes]] -> 1613788
A14: Pricing & Accounting | B14: Emp_013 | C14: Senior Specialist | D14: =VLOOKUP(Payroll_Data_Analysis[[#This Row],[Position]],Position_Map!$A$2:$B$58,2,FALSE) -> Professional | E14: 1 | F14: 74000 | G14: 50000 | I14: =dataset!$F14-dataset!$J14-dataset!$G14-dataset!$H14 -> 20000 | J14: =dataset!$G14*0.08 -> 4000 | K14: =dataset!$F14*12 -> 888000 | L14: =IF(dataset!$G14>=200000,38%,IF(dataset!$G14<=145000,12.3%,)) -> 0.123 | M14: =dataset!$G14*L15*12 -> 73800 | N14: =IF(Payroll_Data_Analysis[[#This Row],[Annual KPI Bonus Reserve]]<=2979000,Payroll_Data_Analysis[[#This Row],[Annual KPI Bonus Reserve]]*0.302,2979000*0.302+(Payroll_Data_Analysis[[#This Row],[Annual KPI Bonus Reserve]]-2979000)*0.151) -> 22287.6 | O14: =dataset!$K14+dataset!$M14 -> 961800 | P14: =Payroll_Data_Analysis[[#This Row],[Annual Salary + KPI Bonus]]/12/29.3*31 -> 84800.341 | Q14: =IF(Payroll_Data_Analysis[[#This Row],[Vacation Reserve]]<=2979000,Payroll_Data_Analysis[[#This Row],[Vacation Reserve]]*0.302,2979000*0.302+(Payroll_Data_Analysis[[#This Row],[Vacation Reserve]]-2979000)*0.151) -> 25609.703 | R14: =Payroll_Data_Analysis[[#This Row],[Monthly Salary]]*11 -> 814000 | S14: =IF(Payroll_Data_Analysis[[#This Row],[11-Month Salary]]<=2979000,Payroll_Data_Analysis[[#This Row],[11-Month Salary]]*0.302,2979000*0.302+(Payroll_Data_Analysis[[#This Row],[11-Month Salary]]-2979000)*0.151) -> 245828 | T14: =IF(Payroll_Data_Analysis[[#This Row],[Base Salary (Monthly)]]>=200000,69507,IF(Payroll_Data_Analysis[[#This Row],[Base Salary (Monthly)]]>=145000,52684,35103)) -> 35103 | U14: =Payroll_Data_Analysis[[#This Row],[Annual KPI Bonus Reserve]]+Payroll_Data_Analysis[[#This Row],[Vacation Reserve]]+Payroll_Data_Analysis[[#This Row],[11-Month Salary]] -> 972600.34 | V14: =Payroll_Data_Analysis[[#This Row],[Payroll Taxes (KPI Bonus)]]+Payroll_Data_Analysis[[#This Row],[Payroll Taxes (Vacation)]]+Payroll_Data_Analysis[[#This Row],[Payroll Taxes (Salary)]] -> 293725.3 | W14: =Payroll_Data_Analysis[[#This Row],[Total Payroll]]+Payroll_Data_Analysis[[#This Row],[Total Payroll Taxes]] -> 1266325.6
... A95: Engineering | B95: Emp_094 | C95: Senior Engineer | D95: =VLOOKUP(Payroll_Data_Analysis[[#This Row],[Position]],Position_Map!$A$2:$B$58,2,FALSE) -> Engineering | E95: 1 | F95: 158000 | G95: 100000 | I95: =dataset!$F95-dataset!$J95-dataset!$G95-dataset!$H95 -> 50000 | J95: =dataset!$G95*0.08 -> 8000 | K95: =dataset!$F95*12 -> 1896000 | L95: =IF(dataset!$G95>=200000,38%,IF(dataset!$G95<=145000,12.3%,)) -> 0.123 | M95: =dataset!$G95*L96*12 -> 456000 | N95: =IF(Payroll_Data_Analysis[[#This Row],[Annual KPI Bonus Reserve]]<=2979000,Payroll_Data_Analysis[[#This Row],[Annual KPI Bonus Reserve]]*0.302,2979000*0.302+(Payroll_Data_Analysis[[#This Row],[Annual KPI Bonus Reserve]]-2979000)*0.151) -> 137712 | O95: =dataset!$K95+dataset!$M95 -> 2352000 | P95: =Payroll_Data_Analysis[[#This Row],[Annual Salary + KPI Bonus]]/12/29.3*31 -> 207372.01 | Q95: =IF(Payroll_Data_Analysis[[#This Row],[Vacation Reserve]]<=2979000,Payroll_Data_Analysis[[#This Row],[Vacation Reserve]]*0.302,2979000*0.302+(Payroll_Data_Analysis[[#This Row],[Vacation Reserve]]-2979000)*0.151) -> 62626.348 | R95: =Payroll_Data_Analysis[[#This Row],[Monthly Salary]]*11 -> 1738000 | S95: =IF(Payroll_Data_Analysis[[#This Row],[11-Month Salary]]<=2979000,Payroll_Data_Analysis[[#This Row],[11-Month Salary]]*0.302,2979000*0.302+(Payroll_Data_Analysis[[#This Row],[11-Month Salary]]-2979000)*0.151) -> 524876 | T95: =IF(Payroll_Data_Analysis[[#This Row],[Base Salary (Monthly)]]>=200000,69507,IF(Payroll_Data_Analysis[[#This Row],[Base Salary (Monthly)]]>=145000,52684,35103)) -> 35103 | U95: =Payroll_Data_Analysis[[#This Row],[Annual KPI Bonus Reserve]]+Payroll_Data_Analysis[[#This Row],[Vacation Reserve]]+Payroll_Data_Analysis[[#This Row],[11-Month Salary]] -> 2401372 | V95: =Payroll_Data_Analysis[[#This Row],[Payroll Taxes (KPI Bonus)]]+Payroll_Data_Analysis[[#This Row],[Payroll Taxes (Vacation)]]+Payroll_Data_Analysis[[#This Row],[Payroll Taxes (Salary)]] -> 725214.35 | W95: =Payroll_Data_Analysis[[#This Row],[Total Payroll]]+Payroll_Data_Analysis[[#This Row],[Total Payroll Taxes]] -> 3126586.4
A96: Engineering | B96: Emp_095 | C96: Deputy CEO – Department Manager | D96: =VLOOKUP(Payroll_Data_Analysis[[#This Row],[Position]],Position_Map!$A$2:$B$58,2,FALSE) -> Executive | E96: 1 | F96: 396000 | G96: 200000 | H96: 20000 | I96: =dataset!$F96-dataset!$J96-dataset!$G96-dataset!$H96 -> 160000 | J96: =dataset!$G96*0.08 -> 16000 | K96: =dataset!$F96*12 -> 4752000 | L96: =IF(dataset!$G96>=200000,38%,IF(dataset!$G96<=145000,12.3%,)) -> 0.38 | M96: =dataset!$G96*L97*12 -> 295200 | N96: =IF(Payroll_Data_Analysis[[#This Row],[Annual KPI Bonus Reserve]]<=2979000,Payroll_Data_Analysis[[#This Row],[Annual KPI Bonus Reserve]]*0.302,2979000*0.302+(Payroll_Data_Analysis[[#This Row],[Annual KPI Bonus Reserve]]-2979000)*0.151) -> 89150.4 | O96: =dataset!$K96+dataset!$M96 -> 5047200 | P96: =Payroll_Data_Analysis[[#This Row],[Annual Salary + KPI Bonus]]/12/29.3*31 -> 445003.41 | Q96: =IF(Payroll_Data_Analysis[[#This Row],[Vacation Reserve]]<=2979000,Payroll_Data_Analysis[[#This Row],[Vacation Reserve]]*0.302,2979000*0.302+(Payroll_Data_Analysis[[#This Row],[Vacation Reserve]]-2979000)*0.151) -> 134391.03 | R96: =Payroll_Data_Analysis[[#This Row],[Monthly Salary]]*11 -> 4356000 | S96: =IF(Payroll_Data_Analysis[[#This Row],[11-Month Salary]]<=2979000,Payroll_Data_Analysis[[#This Row],[11-Month Salary]]*0.302,2979000*0.302+(Payroll_Data_Analysis[[#This Row],[11-Month Salary]]-2979000)*0.151) -> 1107585 | T96: =IF(Payroll_Data_Analysis[[#This Row],[Base Salary (Monthly)]]>=200000,69507,IF(Payroll_Data_Analysis[[#This Row],[Base Salary (Monthly)]]>=145000,52684,35103)) -> 69507 | U96: =Payroll_Data_Analysis[[#This Row],[Annual KPI Bonus Reserve]]+Payroll_Data_Analysis[[#This Row],[Vacation Reserve]]+Payroll_Data_Analysis[[#This Row],[11-Month Salary]] -> 5096203.4 | V96: =Payroll_Data_Analysis[[#This Row],[Payroll Taxes (KPI Bonus)]]+Payroll_Data_Analysis[[#This Row],[Payroll Taxes (Vacation)]]+Payroll_Data_Analysis[[#This Row],[Payroll Taxes (Salary)]] -> 1331126.4 | W96: =Payroll_Data_Analysis[[#This Row],[Total Payroll]]+Payroll_Data_Analysis[[#This Row],[Total Payroll Taxes]] -> 6427329.8
A97: Economic Security | B97: Emp_096 | C97: Deputy Department Manager | D97: =VLOOKUP(Payroll_Data_Analysis[[#This Row],[Position]],Position_Map!$A$2:$B$58,2,FALSE) -> Management | E97: 1 | F97: 211600 | G97: 145000 | I97: =dataset!$F97-dataset!$J97-dataset!$G97-dataset!$H97 -> 55000 | J97: =dataset!$G97*0.08 -> 11600 | K97: =dataset!$F97*12 -> 2539200 | L97: =IF(dataset!$G97>=200000,38%,IF(dataset!$G97<=145000,12.3%,)) -> 0.123 | M97: =dataset!$G97*L98*12 -> 214020 | N97: =IF(Payroll_Data_Analysis[[#This Row],[Annual KPI Bonus Reserve]]<=2979000,Payroll_Data_Analysis[[#This Row],[Annual KPI Bonus Reserve]]*0.302,2979000*0.302+(Payroll_Data_Analysis[[#This Row],[Annual KPI Bonus Reserve]]-2979000)*0.151) -> 64634.04 | O97: =dataset!$K97+dataset!$M97 -> 2753220 | P97: =Payroll_Data_Analysis[[#This Row],[Annual Salary + KPI Bonus]]/12/29.3*31 -> 242746.93 | Q97: =IF(Payroll_Data_Analysis[[#This Row],[Vacation Reserve]]<=2979000,Payroll_Data_Analysis[[#This Row],[Vacation Reserve]]*0.302,2979000*0.302+(Payroll_Data_Analysis[[#This Row],[Vacation Reserve]]-2979000)*0.151) -> 73309.572 | R97: =Payroll_Data_Analysis[[#This Row],[Monthly Salary]]*11 -> 2327600 | S97: =IF(Payroll_Data_Analysis[[#This Row],[11-Month Salary]]<=2979000,Payroll_Data_Analysis[[#This Row],[11-Month Salary]]*0.302,2979000*0.302+(Payroll_Data_Analysis[[#This Row],[11-Month Salary]]-2979000)*0.151) -> 702935.2 | T97: =IF(Payroll_Data_Analysis[[#This Row],[Base Salary (Monthly)]]>=200000,69507,IF(Payroll_Data_Analysis[[#This Row],[Base Salary (Monthly)]]>=145000,52684,35103)) -> 52684 | U97: =Payroll_Data_Analysis[[#This Row],[Annual KPI Bonus Reserve]]+Payroll_Data_Analysis[[#This Row],[Vacation Reserve]]+Payroll_Data_Analysis[[#This Row],[11-Month Salary]] -> 2784366.9 | V97: =Payroll_Data_Analysis[[#This Row],[Payroll Taxes (KPI Bonus)]]+Payroll_Data_Analysis[[#This Row],[Payroll Taxes (Vacation)]]+Payroll_Data_Analysis[[#This Row],[Payroll Taxes (Salary)]] -> 840878.81 | W97: =Payroll_Data_Analysis[[#This Row],[Total Payroll]]+Payroll_Data_Analysis[[#This Row],[Total Payroll Taxes]] -> 3625245.7
A98: Economic Security | B98: Emp_097 | C98: Lead Specialist | D98: =VLOOKUP(Payroll_Data_Analysis[[#This Row],[Position]],Position_Map!$A$2:$B$58,2,FALSE) -> Professional | E98: 1 | F98: 138000 | G98: 100000 | I98: =dataset!$F98-dataset!$J98-dataset!$G98-dataset!$H98 -> 30000 | J98: =dataset!$G98*0.08 -> 8000 | K98: =dataset!$F98*12 -> 1656000 | L98: =IF(dataset!$G98>=200000,38%,IF(dataset!$G98<=145000,12.3%,)) -> 0.123 | M98: =dataset!$G98*L99*12 -> 147600 | N98: =IF(Payroll_Data_Analysis[[#This Row],[Annual KPI Bonus Reserve]]<=2979000,Payroll_Data_Analysis[[#This Row],[Annual KPI Bonus Reserve]]*0.302,2979000*0.302+(Payroll_Data_Analysis[[#This Row],[Annual KPI Bonus Reserve]]-2979000)*0.151) -> 44575.2 | O98: =dataset!$K98+dataset!$M98 -> 1803600 | P98: =Payroll_Data_Analysis[[#This Row],[Annual Salary + KPI Bonus]]/12/29.3*31 -> 159020.48 | Q98: =IF(Payroll_Data_Analysis[[#This Row],[Vacation Reserve]]<=2979000,Payroll_Data_Analysis[[#This Row],[Vacation Reserve]]*0.302,2979000*0.302+(Payroll_Data_Analysis[[#This Row],[Vacation Reserve]]-2979000)*0.151) -> 48024.184 | R98: =Payroll_Data_Analysis[[#This Row],[Monthly Salary]]*11 -> 1518000 | S98: =IF(Payroll_Data_Analysis[[#This Row],[11-Month Salary]]<=2979000,Payroll_Data_Analysis[[#This Row],[11-Month Salary]]*0.302,2979000*0.302+(Payroll_Data_Analysis[[#This Row],[11-Month Salary]]-2979000)*0.151) -> 458436 | T98: =IF(Payroll_Data_Analysis[[#This Row],[Base Salary (Monthly)]]>=200000,69507,IF(Payroll_Data_Analysis[[#This Row],[Base Salary (Monthly)]]>=145000,52684,35103)) -> 35103 | U98: =Payroll_Data_Analysis[[#This Row],[Annual KPI Bonus Reserve]]+Payroll_Data_Analysis[[#This Row],[Vacation Reserve]]+Payroll_Data_Analysis[[#This Row],[11-Month Salary]] -> 1824620.5 | V98: =Payroll_Data_Analysis[[#This Row],[Payroll Taxes (KPI Bonus)]]+Payroll_Data_Analysis[[#This Row],[Payroll Taxes (Vacation)]]+Payroll_Data_Analysis[[#This Row],[Payroll Taxes (Salary)]] -> 551035.38 | W98: =Payroll_Data_Analysis[[#This Row],[Total Payroll]]+Payroll_Data_Analysis[[#This Row],[Total Payroll Taxes]] -> 2375655.9
A99: Economic Security | B99: Emp_098 | C99: Lead Specialist | D99: =VLOOKUP(Payroll_Data_Analysis[[#This Row],[Position]],Position_Map!$A$2:$B$58,2,FALSE) -> Professional | E99: 1 | F99: 211100 | G99: 145000 | I99: =dataset!$F99-dataset!$J99-dataset!$G99-dataset!$H99 -> 54500 | J99: =dataset!$G99*0.08 -> 11600 | K99: =dataset!$F99*12 -> 2533200 | L99: =IF(dataset!$G99>=200000,38%,IF(dataset!$G99<=145000,12.3%,)) -> 0.123 | M99: =dataset!$G99*L100*12 -> 214020 | N99: =IF(Payroll_Data_Analysis[[#This Row],[Annual KPI Bonus Reserve]]<=2979000,Payroll_Data_Analysis[[#This Row],[Annual KPI Bonus Reserve]]*0.302,2979000*0.302+(Payroll_Data_Analysis[[#This Row],[Annual KPI Bonus Reserve]]-2979000)*0.151) -> 64634.04 | O99: =dataset!$K99+dataset!$M99 -> 2747220 | P99: =Payroll_Data_Analysis[[#This Row],[Annual Salary + KPI Bonus]]/12/29.3*31 -> 242217.92 | Q99: =IF(Payroll_Data_Analysis[[#This Row],[Vacation Reserve]]<=2979000,Payroll_Data_Analysis[[#This Row],[Vacation Reserve]]*0.302,2979000*0.302+(Payroll_Data_Analysis[[#This Row],[Vacation Reserve]]-2979000)*0.151) -> 73149.811 | R99: =Payroll_Data_Analysis[[#This Row],[Monthly Salary]]*11 -> 2322100 | S99: =IF(Payroll_Data_Analysis[[#This Row],[11-Month Salary]]<=2979000,Payroll_Data_Analysis[[#This Row],[11-Month Salary]]*0.302,2979000*0.302+(Payroll_Data_Analysis[[#This Row],[11-Month Salary]]-2979000)*0.151) -> 701274.2 | T99: =IF(Payroll_Data_Analysis[[#This Row],[Base Salary (Monthly)]]>=200000,69507,IF(Payroll_Data_Analysis[[#This Row],[Base Salary (Monthly)]]>=145000,52684,35103)) -> 52684 | U99: =Payroll_Data_Analysis[[#This Row],[Annual KPI Bonus Reserve]]+Payroll_Data_Analysis[[#This Row],[Vacation Reserve]]+Payroll_Data_Analysis[[#This Row],[11-Month Salary]] -> 2778337.9 | V99: =Payroll_Data_Analysis[[#This Row],[Payroll Taxes (KPI Bonus)]]+Payroll_Data_Analysis[[#This Row],[Payroll Taxes (Vacation)]]+Payroll_Data_Analysis[[#This Row],[Payroll Taxes (Salary)]] -> 839058.05 | W99: =Payroll_Data_Analysis[[#This Row],[Total Payroll]]+Payroll_Data_Analysis[[#This Row],[Total Payroll Taxes]] -> 3617396
A100: Economic Security | B100: Emp_099 | C100: Lead Specialist | D100: =VLOOKUP(Payroll_Data_Analysis[[#This Row],[Position]],Position_Map!$A$2:$B$58,2,FALSE) -> Professional | E100: 1 | F100: 211100 | G100: 145000 | I100: =dataset!$F100-dataset!$J100-dataset!$G100-dataset!$H100 -> 54500 | J100: =dataset!$G100*0.08 -> 11600 | K100: =dataset!$F100*12 -> 2533200 | L100: =IF(dataset!$G100>=200000,38%,IF(dataset!$G100<=145000,12.3%,)) -> 0.123 | M100: =dataset!$G100*L101*12 -> 214020 | N100: =IF(Payroll_Data_Analysis[[#This Row],[Annual KPI Bonus Reserve]]<=2979000,Payroll_Data_Analysis[[#This Row],[Annual KPI Bonus Reserve]]*0.302,2979000*0.302+(Payroll_Data_Analysis[[#This Row],[Annual KPI Bonus Reserve]]-2979000)*0.151) -> 64634.04 | O100: =dataset!$K100+dataset!$M100 -> 2747220 | P100: =Payroll_Data_Analysis[[#This Row],[Annual Salary + KPI Bonus]]/12/29.3*31 -> 242217.92 | Q100: =IF(Payroll_Data_Analysis[[#This Row],[Vacation Reserve]]<=2979000,Payroll_Data_Analysis[[#This Row],[Vacation Reserve]]*0.302,2979000*0.302+(Payroll_Data_Analysis[[#This Row],[Vacation Reserve]]-2979000)*0.151) -> 73149.811 | R100: =Payroll_Data_Analysis[[#This Row],[Monthly Salary]]*11 -> 2322100 | S100: =IF(Payroll_Data_Analysis[[#This Row],[11-Month Salary]]<=2979000,Payroll_Data_Analysis[[#This Row],[11-Month Salary]]*0.302,2979000*0.302+(Payroll_Data_Analysis[[#This Row],[11-Month Salary]]-2979000)*0.151) -> 701274.2 | T100: =IF(Payroll_Data_Analysis[[#This Row],[Base Salary (Monthly)]]>=200000,69507,IF(Payroll_Data_Analysis[[#This Row],[Base Salary (Monthly)]]>=145000,52684,35103)) -> 52684 | U100: =Payroll_Data_Analysis[[#This Row],[Annual KPI Bonus Reserve]]+Payroll_Data_Analysis[[#This Row],[Vacation Reserve]]+Payroll_Data_Analysis[[#This Row],[11-Month Salary]] -> 2778337.9 | V100: =Payroll_Data_Analysis[[#This Row],[Payroll Taxes (KPI Bonus)]]+Payroll_Data_Analysis[[#This Row],[Payroll Taxes (Vacation)]]+Payroll_Data_Analysis[[#This Row],[Payroll Taxes (Salary)]] -> 839058.05 | W100: =Payroll_Data_Analysis[[#This Row],[Total Payroll]]+Payroll_Data_Analysis[[#This Row],[Total Payroll Taxes]] -> 3617396
A101: Economic Security | B101: Emp_100 | C101: Department Manager | D101: =VLOOKUP(Payroll_Data_Analysis[[#This Row],[Position]],Position_Map!$A$2:$B$58,2,FALSE) -> Management | E101: 1 | F101: 261600 | G101: 145000 | I101: =dataset!$F101-dataset!$J101-dataset!$G101-dataset!$H101 -> 105000 | J101: =dataset!$G101*0.08 -> 11600 | K101: =dataset!$F101*12 -> 3139200 | L101: =IF(dataset!$G101>=200000,38%,IF(dataset!$G101<=145000,12.3%,)) -> 0.123 | M101: =dataset!$G101*L102*12 -> 214020 | N101: =IF(Payroll_Data_Analysis[[#This Row],[Annual KPI Bonus Reserve]]<=2979000,Payroll_Data_Analysis[[#This Row],[Annual KPI Bonus Reserve]]*0.302,2979000*0.302+(Payroll_Data_Analysis[[#This Row],[Annual KPI Bonus Reserve]]-2979000)*0.151) -> 64634.04 | O101: =dataset!$K101+dataset!$M101 -> 3353220 | P101: =Payroll_Data_Analysis[[#This Row],[Annual Salary + KPI Bonus]]/12/29.3*31 -> 295647.95 | Q101: =IF(Payroll_Data_Analysis[[#This Row],[Vacation Reserve]]<=2979000,Payroll_Data_Analysis[[#This Row],[Vacation Reserve]]*0.302,2979000*0.302+(Payroll_Data_Analysis[[#This Row],[Vacation Reserve]]-2979000)*0.151) -> 89285.682 | R101: =Payroll_Data_Analysis[[#This Row],[Monthly Salary]]*11 -> 2877600 | S101: =IF(Payroll_Data_Analysis[[#This Row],[11-Month Salary]]<=2979000,Payroll_Data_Analysis[[#This Row],[11-Month Salary]]*0.302,2979000*0.302+(Payroll_Data_Analysis[[#This Row],[11-Month Salary]]-2979000)*0.151) -> 869035.2 | T101: =IF(Payroll_Data_Analysis[[#This Row],[Base Salary (Monthly)]]>=200000,69507,IF(Payroll_Data_Analysis[[#This Row],[Base Salary (Monthly)]]>=145000,52684,35103)) -> 52684 | U101: =Payroll_Data_Analysis[[#This Row],[Annual KPI Bonus Reserve]]+Payroll_Data_Analysis[[#This Row],[Vacation Reserve]]+Payroll_Data_Analysis[[#This Row],[11-Month Salary]] -> 3387268 | V101: =Payroll_Data_Analysis[[#This Row],[Payroll Taxes (KPI Bonus)]]+Payroll_Data_Analysis[[#This Row],[Payroll Taxes (Vacation)]]+Payroll_Data_Analysis[[#This Row],[Payroll Taxes (Salary)]] -> 1022954.9 | W101: =Payroll_Data_Analysis[[#This Row],[Total Payroll]]+Payroll_Data_Analysis[[#This Row],[Total Payroll Taxes]] -> 4410222.9
A102: Economic Security | B102: Emp_101 | C102: Lead Specialist | D102: =VLOOKUP(Payroll_Data_Analysis[[#This Row],[Position]],Position_Map!$A$2:$B$58,2,FALSE) -> Professional | E102: 1 | F102: 158000 | G102: 100000 | I102: =dataset!$F102-dataset!$J102-dataset!$G102-dataset!$H102 -> 50000 | J102: =dataset!$G102*0.08 -> 8000 | K102: =dataset!$F102*12 -> 1896000 | L102: =IF(dataset!$G102>=200000,38%,IF(dataset!$G102<=145000,12.3%,)) -> 0.123 | M102: =dataset!$G102*L103*12 -> 147600 | N102: =IF(Payroll_Data_Analysis[[#This Row],[Annual KPI Bonus Reserve]]<=2979000,Payroll_Data_Analysis[[#This Row],[Annual KPI Bonus Reserve]]*0.302,2979000*0.302+(Payroll_Data_Analysis[[#This Row],[Annual KPI Bonus Reserve]]-2979000)*0.151) -> 44575.2 | O102: =dataset!$K102+dataset!$M102 -> 2043600 | P102: =Payroll_Data_Analysis[[#This Row],[Annual Salary + KPI Bonus]]/12/29.3*31 -> 180180.89 | Q102: =IF(Payroll_Data_Analysis[[#This Row],[Vacation Reserve]]<=2979000,Payroll_Data_Analysis[[#This Row],[Vacation Reserve]]*0.302,2979000*0.302+(Payroll_Data_Analysis[[#This Row],[Vacation Reserve]]-2979000)*0.151) -> 54414.628 | R102: =Payroll_Data_Analysis[[#This Row],[Monthly Salary]]*11 -> 1738000 | S102: =IF(Payroll_Data_Analysis[[#This Row],[11-Month Salary]]<=2979000,Payroll_Data_Analysis[[#This Row],[11-Month Salary]]*0.302,2979000*0.302+(Payroll_Data_Analysis[[#This Row],[11-Month Salary]]-2979000)*0.151) -> 524876 | T102: =IF(Payroll_Data_Analysis[[#This Row],[Base Salary (Monthly)]]>=200000,69507,IF(Payroll_Data_Analysis[[#This Row],[Base Salary (Monthly)]]>=145000,52684,35103)) -> 35103 | U102: =Payroll_Data_Analysis[[#This Row],[Annual KPI Bonus Reserve]]+Payroll_Data_Analysis[[#This Row],[Vacation Reserve]]+Payroll_Data_Analysis[[#This Row],[11-Month Salary]] -> 2065780.9 | V102: =Payroll_Data_Analysis[[#This Row],[Payroll Taxes (KPI Bonus)]]+Payroll_Data_Analysis[[#This Row],[Payroll Taxes (Vacation)]]+Payroll_Data_Analysis[[#This Row],[Payroll Taxes (Salary)]] -> 623865.83 | W102: =Payroll_Data_Analysis[[#This Row],[Total Payroll]]+Payroll_Data_Analysis[[#This Row],[Total Payroll Taxes]] -> 2689646.7
A103: Economic Security | B103: Emp_102 | C103: Senior Specialist | D103: =VLOOKUP(Payroll_Data_Analysis[[#This Row],[Position]],Position_Map!$A$2:$B$58,2,FALSE) -> Professional | E103: 1 | F103: 126400 | G103: 80000 | I103: =dataset!$F103-dataset!$J103-dataset!$G103-dataset!$H103 -> 40000 | J103: =dataset!$G103*0.08 -> 6400 | K103: =dataset!$F103*12 -> 1516800 | L103: =IF(dataset!$G103>=200000,38%,IF(dataset!$G103<=145000,12.3%,)) -> 0.123 | M103: =dataset!$G103*L104*12 -> 118080 | N103: =IF(Payroll_Data_Analysis[[#This Row],[Annual KPI Bonus Reserve]]<=2979000,Payroll_Data_Analysis[[#This Row],[Annual KPI Bonus Reserve]]*0.302,2979000*0.302+(Payroll_Data_Analysis[[#This Row],[Annual KPI Bonus Reserve]]-2979000)*0.151) -> 35660.16 | O103: =dataset!$K103+dataset!$M103 -> 1634880 | P103: =Payroll_Data_Analysis[[#This Row],[Annual Salary + KPI Bonus]]/12/29.3*31 -> 144144.71 | Q103: =IF(Payroll_Data_Analysis[[#This Row],[Vacation Reserve]]<=2979000,Payroll_Data_Analysis[[#This Row],[Vacation Reserve]]*0.302,2979000*0.302+(Payroll_Data_Analysis[[#This Row],[Vacation Reserve]]-2979000)*0.151) -> 43531.702 | R103: =Payroll_Data_Analysis[[#This Row],[Monthly Salary]]*11 -> 1390400 | S103: =IF(Payroll_Data_Analysis[[#This Row],[11-Month Salary]]<=2979000,Payroll_Data_Analysis[[#This Row],[11-Month Salary]]*0.302,2979000*0.302+(Payroll_Data_Analysis[[#This Row],[11-Month Salary]]-2979000)*0.151) -> 419900.8 | T103: =IF(Payroll_Data_Analysis[[#This Row],[Base Salary (Monthly)]]>=200000,69507,IF(Payroll_Data_Analysis[[#This Row],[Base Salary (Monthly)]]>=145000,52684,35103)) -> 35103 | U103: =Payroll_Data_Analysis[[#This Row],[Annual KPI Bonus Reserve]]+Payroll_Data_Analysis[[#This Row],[Vacation Reserve]]+Payroll_Data_Analysis[[#This Row],[11-Month Salary]] -> 1652624.7 | V103: =Payroll_Data_Analysis[[#This Row],[Payroll Taxes (KPI Bonus)]]+Payroll_Data_Analysis[[#This Row],[Payroll Taxes (Vacation)]]+Payroll_Data_Analysis[[#This Row],[Payroll Taxes (Salary)]] -> 499092.66 | W103: =Payroll_Data_Analysis[[#This Row],[Total Payroll]]+Payroll_Data_Analysis[[#This Row],[Total Payroll Taxes]] -> 2151717.4
A104: Economic Security | B104: Emp_103 | C104: Senior Engineer | D104: =VLOOKUP(Payroll_Data_Analysis[[#This Row],[Position]],Position_Map!$A$2:$B$58,2,FALSE) -> Engineering | E104: 1 | F104: 173000 | G104: 100000 | I104: =dataset!$F104-dataset!$J104-dataset!$G104-dataset!$H104 -> 65000 | J104: =dataset!$G104*0.08 -> 8000 | K104: =dataset!$F104*12 -> 2076000 | L104: =IF(dataset!$G104>=200000,38%,IF(dataset!$G104<=145000,12.3%,)) -> 0.123 | M104: =dataset!$G104*L105*12 -> 147600 | N104: =IF(Payroll_Data_Analysis[[#This Row],[Annual KPI Bonus Reserve]]<=2979000,Payroll_Data_Analysis[[#This Row],[Annual KPI Bonus Reserve]]*0.302,2979000*0.302+(Payroll_Data_Analysis[[#This Row],[Annual KPI Bonus Reserve]]-2979000)*0.151) -> 44575.2 | O104: =dataset!$K104+dataset!$M104 -> 2223600 | P104: =Payroll_Data_Analysis[[#This Row],[Annual Salary + KPI Bonus]]/12/29.3*31 -> 196051.19 | Q104: =IF(Payroll_Data_Analysis[[#This Row],[Vacation Reserve]]<=2979000,Payroll_Data_Analysis[[#This Row],[Vacation Reserve]]*0.302,2979000*0.302+(Payroll_Data_Analysis[[#This Row],[Vacation Reserve]]-2979000)*0.151) -> 59207.461 | R104: =Payroll_Data_Analysis[[#This Row],[Monthly Salary]]*11 -> 1903000 | S104: =IF(Payroll_Data_Analysis[[#This Row],[11-Month Salary]]<=2979000,Payroll_Data_Analysis[[#This Row],[11-Month Salary]]*0.302,2979000*0.302+(Payroll_Data_Analysis[[#This Row],[11-Month Salary]]-2979000)*0.151) -> 574706 | T104: =IF(Payroll_Data_Analysis[[#This Row],[Base Salary (Monthly)]]>=200000,69507,IF(Payroll_Data_Analysis[[#This Row],[Base Salary (Monthly)]]>=145000,52684,35103)) -> 35103 | U104: =Payroll_Data_Analysis[[#This Row],[Annual KPI Bonus Reserve]]+Payroll_Data_Analysis[[#This Row],[Vacation Reserve]]+Payroll_Data_Analysis[[#This Row],[11-Month Salary]] -> 2246651.2 | V104: =Payroll_Data_Analysis[[#This Row],[Payroll Taxes (KPI Bonus)]]+Payroll_Data_Analysis[[#This Row],[Payroll Taxes (Vacation)]]+Payroll_Data_Analysis[[#This Row],[Payroll Taxes (Salary)]] -> 678488.66 | W104: =Payroll_Data_Analysis[[#This Row],[Total Payroll]]+Payroll_Data_Analysis[[#This Row],[Total Payroll Taxes]] -> 2925139.9
A105: Building Operations № 1 | B105: Emp_105 | C105: Department Director | D105: =VLOOKUP(Payroll_Data_Analysis[[#This Row],[Position]],Position_Map!$A$2:$B$58,2,FALSE) -> Management | E105: 1 | F105: 238600 | G105: 145000 | I105: =dataset!$F105-dataset!$J105-dataset!$G105-dataset!$H105 -> 82000 | J105: =dataset!$G105*0.08 -> 11600 | K105: =dataset!$F105*12 -> 2863200 | L105: =IF(dataset!$G105>=200000,38%,IF(dataset!$G105<=145000,12.3%,)) -> 0.123 | M105: =dataset!$G105*L106*12 -> 214020 | N105: =IF(Payroll_Data_Analysis[[#This Row],[Annual KPI Bonus Reserve]]<=2979000,Payroll_Data_Analysis[[#This Row],[Annual KPI Bonus Reserve]]*0.302,2979000*0.302+(Payroll_Data_Analysis[[#This Row],[Annual KPI Bonus Reserve]]-2979000)*0.151) -> 64634.04 | O105: =dataset!$K105+dataset!$M105 -> 3077220 | P105: =Payroll_Data_Analysis[[#This Row],[Annual Salary + KPI Bonus]]/12/29.3*31 -> 271313.48 | Q105: =IF(Payroll_Data_Analysis[[#This Row],[Vacation Reserve]]<=2979000,Payroll_Data_Analysis[[#This Row],[Vacation Reserve]]*0.302,2979000*0.302+(Payroll_Data_Analysis[[#This Row],[Vacation Reserve]]-2979000)*0.151) -> 81936.671 | R105: =Payroll_Data_Analysis[[#This Row],[Monthly Salary]]*11 -> 2624600 | S105: =IF(Payroll_Data_Analysis[[#This Row],[11-Month Salary]]<=2979000,Payroll_Data_Analysis[[#This Row],[11-Month Salary]]*0.302,2979000*0.302+(Payroll_Data_Analysis[[#This Row],[11-Month Salary]]-2979000)*0.151) -> 792629.2 | T105: =IF(Payroll_Data_Analysis[[#This Row],[Base Salary (Monthly)]]>=200000,69507,IF(Payroll_Data_Analysis[[#This Row],[Base Salary (Monthly)]]>=145000,52684,35103)) -> 52684 | U105: =Payroll_Data_Analysis[[#This Row],[Annual KPI Bonus Reserve]]+Payroll_Data_Analysis[[#This Row],[Vacation Reserve]]+Payroll_Data_Analysis[[#This Row],[11-Month Salary]] -> 3109933.5 | V105: =Payroll_Data_Analysis[[#This Row],[Payroll Taxes (KPI Bonus)]]+Payroll_Data_Analysis[[#This Row],[Payroll Taxes (Vacation)]]+Payroll_Data_Analysis[[#This Row],[Payroll Taxes (Salary)]] -> 939199.91 | W105: =Payroll_Data_Analysis[[#This Row],[Total Payroll]]+Payroll_Data_Analysis[[#This Row],[Total Payroll Taxes]] -> 4049133.4
A106: Building Operations № 1 | B106: Emp_106 | C106: Chief Engineer | D106: =VLOOKUP(Payroll_Data_Analysis[[#This Row],[Position]],Position_Map!$A$2:$B$58,2,FALSE) -> Engineering | E106: 1 | F106: 211600 | G106: 145000 | I106: =dataset!$F106-dataset!$J106-dataset!$G106-dataset!$H106 -> 55000 | J106: =dataset!$G106*0.08 -> 11600 | K106: =dataset!$F106*12 -> 2539200 | L106: =IF(dataset!$G106>=200000,38%,IF(dataset!$G106<=145000,12.3%,)) -> 0.123 | M106: =dataset!$G106*L107*12 -> 214020 | N106: =IF(Payroll_Data_Analysis[[#This Row],[Annual KPI Bonus Reserve]]<=2979000,Payroll_Data_Analysis[[#This Row],[Annual KPI Bonus Reserve]]*0.302,2979000*0.302+(Payroll_Data_Analysis[[#This Row],[Annual KPI Bonus Reserve]]-2979000)*0.151) -> 64634.04 | O106: =dataset!$K106+dataset!$M106 -> 2753220 | P106: =Payroll_Data_Analysis[[#This Row],[Annual Salary + KPI Bonus]]/12/29.3*31 -> 242746.93 | Q106: =IF(Payroll_Data_Analysis[[#This Row],[Vacation Reserve]]<=2979000,Payroll_Data_Analysis[[#This Row],[Vacation Reserve]]*0.302,2979000*0.302+(Payroll_Data_Analysis[[#This Row],[Vacation Reserve]]-2979000)*0.151) -> 73309.572 | R106: =Payroll_Data_Analysis[[#This Row],[Monthly Salary]]*11 -> 2327600 | S106: =IF(Payroll_Data_Analysis[[#This Row],[11-Month Salary]]<=2979000,Payroll_Data_Analysis[[#This Row],[11-Month Salary]]*0.302,2979000*0.302+(Payroll_Data_Analysis[[#This Row],[11-Month Salary]]-2979000)*0.151) -> 702935.2 | T106: =IF(Payroll_Data_Analysis[[#This Row],[Base Salary (Monthly)]]>=200000,69507,IF(Payroll_Data_Analysis[[#This Row],[Base Salary (Monthly)]]>=145000,52684,35103)) -> 52684 | U106: =Payroll_Data_Analysis[[#This Row],[Annual KPI Bonus Reserve]]+Payroll_Data_Analysis[[#This Row],[Vacation Reserve]]+Payroll_Data_Analysis[[#This Row],[11-Month Salary]] -> 2784366.9 | V106: =Payroll_Data_Analysis[[#This Row],[Payroll Taxes (KPI Bonus)]]+Payroll_Data_Analysis[[#This Row],[Payroll Taxes (Vacation)]]+Payroll_Data_Analysis[[#This Row],[Payroll Taxes (Salary)]] -> 840878.81 | W106: =Payroll_Data_Analysis[[#This Row],[Total Payroll]]+Payroll_Data_Analysis[[#This Row],[Total Payroll Taxes]] -> 3625245.7
A107: Building Operations № 1 | B107: Emp_107 | C107: Assistant | D107: =VLOOKUP(Payroll_Data_Analysis[[#This Row],[Position]],Position_Map!$A$2:$B$58,2,FALSE) -> Administration | E107: 1 | F107: 261600 | G107: 145000 | I107: =dataset!$F107-dataset!$J107-dataset!$G107-dataset!$H107 -> 105000 | J107: =dataset!$G107*0.08 -> 11600 | K107: =dataset!$F107*12 -> 3139200 | L107: =IF(dataset!$G107>=200000,38%,IF(dataset!$G107<=145000,12.3%,)) -> 0.123 | M107: =dataset!$G107*L108*12 -> 661200 | N107: =IF(Payroll_Data_Analysis[[#This Row],[Annual KPI Bonus Reserve]]<=2979000,Payroll_Data_Analysis[[#This Row],[Annual KPI Bonus Reserve]]*0.302,2979000*0.302+(Payroll_Data_Analysis[[#This Row],[Annual KPI Bonus Reserve]]-2979000)*0.151) -> 199682.4 | O107: =dataset!$K107+dataset!$M107 -> 3800400 | P107: =Payroll_Data_Analysis[[#This Row],[Annual Salary + KPI Bonus]]/12/29.3*31 -> 335075.09 | Q107: =IF(Payroll_Data_Analysis[[#This Row],[Vacation Reserve]]<=2979000,Payroll_Data_Analysis[[#This Row],[Vacation Reserve]]*0.302,2979000*0.302+(Payroll_Data_Analysis[[#This Row],[Vacation Reserve]]-2979000)*0.151) -> 101192.68 | R107: =Payroll_Data_Analysis[[#This Row],[Monthly Salary]]*11 -> 2877600 | S107: =IF(Payroll_Data_Analysis[[#This Row],[11-Month Salary]]<=2979000,Payroll_Data_Analysis[[#This Row],[11-Month Salary]]*0.302,2979000*0.302+(Payroll_Data_Analysis[[#This Row],[11-Month Salary]]-2979000)*0.151) -> 869035.2 | T107: =IF(Payroll_Data_Analysis[[#This Row],[Base Salary (Monthly)]]>=200000,69507,IF(Payroll_Data_Analysis[[#This Row],[Base Salary (Monthly)]]>=145000,52684,35103)) -> 52684 | U107: =Payroll_Data_Analysis[[#This Row],[Annual KPI Bonus Reserve]]+Payroll_Data_Analysis[[#This Row],[Vacation Reserve]]+Payroll_Data_Analysis[[#This Row],[11-Month Salary]] -> 3873875.1 | V107: =Payroll_Data_Analysis[[#This Row],[Payroll Taxes (KPI Bonus)]]+Payroll_Data_Analysis[[#This Row],[Payroll Taxes (Vacation)]]+Payroll_Data_Analysis[[#This Row],[Payroll Taxes (Salary)]] -> 1169910.3 | W107: =Payroll_Data_Analysis[[#This Row],[Total Payroll]]+Payroll_Data_Analysis[[#This Row],[Total Payroll Taxes]] -> 5043785.4
A108: Building Operations № 1 | B108: Emp_108 | C108: Advisor | D108: =VLOOKUP(Payroll_Data_Analysis[[#This Row],[Position]],Position_Map!$A$2:$B$58,2,FALSE) -> Professional | E108: 1 | F108: 301000 | G108: 200000 | I108: =dataset!$F108-dataset!$J108-dataset!$G108-dataset!$H108 -> 85000 | J108: =dataset!$G108*0.08 -> 16000 | K108: =dataset!$F108*12 -> 3612000 | L108: =IF(dataset!$G108>=200000,38%,IF(dataset!$G108<=145000,12.3%,)) -> 0.38 | M108: =dataset!$G108*L109*12 -> 295200 | N108: =IF(Payroll_Data_Analysis[[#This Row],[Annual KPI Bonus Reserve]]<=2979000,Payroll_Data_Analysis[[#This Row],[Annual KPI Bonus Reserve]]*0.302,2979000*0.302+(Payroll_Data_Analysis[[#This Row],[Annual KPI Bonus Reserve]]-2979000)*0.151) -> 89150.4 | O108: =dataset!$K108+dataset!$M108 -> 3907200 | P108: =Payroll_Data_Analysis[[#This Row],[Annual Salary + KPI Bonus]]/12/29.3*31 -> 344491.47 | Q108: =IF(Payroll_Data_Analysis[[#This Row],[Vacation Reserve]]<=2979000,Payroll_Data_Analysis[[#This Row],[Vacation Reserve]]*0.302,2979000*0.302+(Payroll_Data_Analysis[[#This Row],[Vacation Reserve]]-2979000)*0.151) -> 104036.42 | R108: =Payroll_Data_Analysis[[#This Row],[Monthly Salary]]*11 -> 3311000 | S108: =IF(Payroll_Data_Analysis[[#This Row],[11-Month Salary]]<=2979000,Payroll_Data_Analysis[[#This Row],[11-Month Salary]]*0.302,2979000*0.302+(Payroll_Data_Analysis[[#This Row],[11-Month Salary]]-2979000)*0.151) -> 949790 | T108: =IF(Payroll_Data_Analysis[[#This Row],[Base Salary (Monthly)]]>=200000,69507,IF(Payroll_Data_Analysis[[#This Row],[Base Salary (Monthly)]]>=145000,52684,35103)) -> 69507 | U108: =Payroll_Data_Analysis[[#This Row],[Annual KPI Bonus Reserve]]+Payroll_Data_Analysis[[#This Row],[Vacation Reserve]]+Payroll_Data_Analysis[[#This Row],[11-Month Salary]] -> 3950691.5 | V108: =Payroll_Data_Analysis[[#This Row],[Payroll Taxes (KPI Bonus)]]+Payroll_Data_Analysis[[#This Row],[Payroll Taxes (Vacation)]]+Payroll_Data_Analysis[[#This Row],[Payroll Taxes (Salary)]] -> 1142976.8 | W108: =Payroll_Data_Analysis[[#This Row],[Total Payroll]]+Payroll_Data_Analysis[[#This Row],[Total Payroll Taxes]] -> 5093668.3
... A225: Building Operations № 3 | B225: Emp_225 | C225: Building Maintenance Technician | D225: =VLOOKUP(Payroll_Data_Analysis[[#This Row],[Position]],Position_Map!$A$2:$B$58,2,FALSE) -> Technical | E225: 1 | F225: 74000 | G225: 50000 | I225: =dataset!$F225-dataset!$J225-dataset!$G225-dataset!$H225 -> 20000 | J225: =dataset!$G225*0.08 -> 4000 | K225: =dataset!$F225*12 -> 888000 | L225: =IF(dataset!$G225>=200000,38%,IF(dataset!$G225<=145000,12.3%,)) -> 0.123 | M225: =dataset!$G225*L226*12 -> 73800 | N225: =IF(Payroll_Data_Analysis[[#This Row],[Annual KPI Bonus Reserve]]<=2979000,Payroll_Data_Analysis[[#This Row],[Annual KPI Bonus Reserve]]*0.302,2979000*0.302+(Payroll_Data_Analysis[[#This Row],[Annual KPI Bonus Reserve]]-2979000)*0.151) -> 22287.6 | O225: =dataset!$K225+dataset!$M225 -> 961800 | P225: =Payroll_Data_Analysis[[#This Row],[Annual Salary + KPI Bonus]]/12/29.3*31 -> 84800.341 | Q225: =IF(Payroll_Data_Analysis[[#This Row],[Vacation Reserve]]<=2979000,Payroll_Data_Analysis[[#This Row],[Vacation Reserve]]*0.302,2979000*0.302+(Payroll_Data_Analysis[[#This Row],[Vacation Reserve]]-2979000)*0.151) -> 25609.703 | R225: =Payroll_Data_Analysis[[#This Row],[Monthly Salary]]*11 -> 814000 | S225: =IF(Payroll_Data_Analysis[[#This Row],[11-Month Salary]]<=2979000,Payroll_Data_Analysis[[#This Row],[11-Month Salary]]*0.302,2979000*0.302+(Payroll_Data_Analysis[[#This Row],[11-Month Salary]]-2979000)*0.151) -> 245828 | T225: =IF(Payroll_Data_Analysis[[#This Row],[Base Salary (Monthly)]]>=200000,69507,IF(Payroll_Data_Analysis[[#This Row],[Base Salary (Monthly)]]>=145000,52684,35103)) -> 35103 | U225: =Payroll_Data_Analysis[[#This Row],[Annual KPI Bonus Reserve]]+Payroll_Data_Analysis[[#This Row],[Vacation Reserve]]+Payroll_Data_Analysis[[#This Row],[11-Month Salary]] -> 972600.34 | V225: =Payroll_Data_Analysis[[#This Row],[Payroll Taxes (KPI Bonus)]]+Payroll_Data_Analysis[[#This Row],[Payroll Taxes (Vacation)]]+Payroll_Data_Analysis[[#This Row],[Payroll Taxes (Salary)]] -> 293725.3 | W225: =Payroll_Data_Analysis[[#This Row],[Total Payroll]]+Payroll_Data_Analysis[[#This Row],[Total Payroll Taxes]] -> 1266325.6
A226: Fire & Safety Systems | B226: Emp_226 | C226: Head of Division | D226: =VLOOKUP(Payroll_Data_Analysis[[#This Row],[Position]],Position_Map!$A$2:$B$58,2,FALSE) -> Management | E226: 1 | F226: 286100 | G226: 145000 | H226: 14500 | I226: =dataset!$F226-dataset!$J226-dataset!$G226-dataset!$H226 -> 115000 | J226: =dataset!$G226*0.08 -> 11600 | K226: =dataset!$F226*12 -> 3433200 | L226: =IF(dataset!$G226>=200000,38%,IF(dataset!$G226<=145000,12.3%,)) -> 0.123 | M226: =dataset!$G226*L227*12 -> 214020 | N226: =IF(Payroll_Data_Analysis[[#This Row],[Annual KPI Bonus Reserve]]<=2979000,Payroll_Data_Analysis[[#This Row],[Annual KPI Bonus Reserve]]*0.302,2979000*0.302+(Payroll_Data_Analysis[[#This Row],[Annual KPI Bonus Reserve]]-2979000)*0.151) -> 64634.04 | O226: =dataset!$K226+dataset!$M226 -> 3647220 | P226: =Payroll_Data_Analysis[[#This Row],[Annual Salary + KPI Bonus]]/12/29.3*31 -> 321569.45 | Q226: =IF(Payroll_Data_Analysis[[#This Row],[Vacation Reserve]]<=2979000,Payroll_Data_Analysis[[#This Row],[Vacation Reserve]]*0.302,2979000*0.302+(Payroll_Data_Analysis[[#This Row],[Vacation Reserve]]-2979000)*0.151) -> 97113.975 | R226: =Payroll_Data_Analysis[[#This Row],[Monthly Salary]]*11 -> 3147100 | S226: =IF(Payroll_Data_Analysis[[#This Row],[11-Month Salary]]<=2979000,Payroll_Data_Analysis[[#This Row],[11-Month Salary]]*0.302,2979000*0.302+(Payroll_Data_Analysis[[#This Row],[11-Month Salary]]-2979000)*0.151) -> 925041.1 | T226: =IF(Payroll_Data_Analysis[[#This Row],[Base Salary (Monthly)]]>=200000,69507,IF(Payroll_Data_Analysis[[#This Row],[Base Salary (Monthly)]]>=145000,52684,35103)) -> 52684 | U226: =Payroll_Data_Analysis[[#This Row],[Annual KPI Bonus Reserve]]+Payroll_Data_Analysis[[#This Row],[Vacation Reserve]]+Payroll_Data_Analysis[[#This Row],[11-Month Salary]] -> 3682689.5 | V226: =Payroll_Data_Analysis[[#This Row],[Payroll Taxes (KPI Bonus)]]+Payroll_Data_Analysis[[#This Row],[Payroll Taxes (Vacation)]]+Payroll_Data_Analysis[[#This Row],[Payroll Taxes (Salary)]] -> 1086789.1 | W226: =Payroll_Data_Analysis[[#This Row],[Total Payroll]]+Payroll_Data_Analysis[[#This Row],[Total Payroll Taxes]] -> 4769478.6
A227: Fire & Safety Systems | B227: Emp_227 | C227: Lead Specialist | D227: =VLOOKUP(Payroll_Data_Analysis[[#This Row],[Position]],Position_Map!$A$2:$B$58,2,FALSE) -> Professional | E227: 1 | F227: 158000 | G227: 100000 | I227: =dataset!$F227-dataset!$J227-dataset!$G227-dataset!$H227 -> 50000 | J227: =dataset!$G227*0.08 -> 8000 | K227: =dataset!$F227*12 -> 1896000 | L227: =IF(dataset!$G227>=200000,38%,IF(dataset!$G227<=145000,12.3%,)) -> 0.123 | M227: =dataset!$G227*L228*12 -> 147600 | N227: =IF(Payroll_Data_Analysis[[#This Row],[Annual KPI Bonus Reserve]]<=2979000,Payroll_Data_Analysis[[#This Row],[Annual KPI Bonus Reserve]]*0.302,2979000*0.302+(Payroll_Data_Analysis[[#This Row],[Annual KPI Bonus Reserve]]-2979000)*0.151) -> 44575.2 | O227: =dataset!$K227+dataset!$M227 -> 2043600 | P227: =Payroll_Data_Analysis[[#This Row],[Annual Salary + KPI Bonus]]/12/29.3*31 -> 180180.89 | Q227: =IF(Payroll_Data_Analysis[[#This Row],[Vacation Reserve]]<=2979000,Payroll_Data_Analysis[[#This Row],[Vacation Reserve]]*0.302,2979000*0.302+(Payroll_Data_Analysis[[#This Row],[Vacation Reserve]]-2979000)*0.151) -> 54414.628 | R227: =Payroll_Data_Analysis[[#This Row],[Monthly Salary]]*11 -> 1738000 | S227: =IF(Payroll_Data_Analysis[[#This Row],[11-Month Salary]]<=2979000,Payroll_Data_Analysis[[#This Row],[11-Month Salary]]*0.302,2979000*0.302+(Payroll_Data_Analysis[[#This Row],[11-Month Salary]]-2979000)*0.151) -> 524876 | T227: =IF(Payroll_Data_Analysis[[#This Row],[Base Salary (Monthly)]]>=200000,69507,IF(Payroll_Data_Analysis[[#This Row],[Base Salary (Monthly)]]>=145000,52684,35103)) -> 35103 | U227: =Payroll_Data_Analysis[[#This Row],[Annual KPI Bonus Reserve]]+Payroll_Data_Analysis[[#This Row],[Vacation Reserve]]+Payroll_Data_Analysis[[#This Row],[11-Month Salary]] -> 2065780.9 | V227: =Payroll_Data_Analysis[[#This Row],[Payroll Taxes (KPI Bonus)]]+Payroll_Data_Analysis[[#This Row],[Payroll Taxes (Vacation)]]+Payroll_Data_Analysis[[#This Row],[Payroll Taxes (Salary)]] -> 623865.83 | W227: =Payroll_Data_Analysis[[#This Row],[Total Payroll]]+Payroll_Data_Analysis[[#This Row],[Total Payroll Taxes]] -> 2689646.7
A228: Fire & Safety Systems | B228: Emp_228 | C228: Department Manager | D228: =VLOOKUP(Payroll_Data_Analysis[[#This Row],[Position]],Position_Map!$A$2:$B$58,2,FALSE) -> Management | E228: 1 | F228: 231600 | G228: 145000 | I228: =dataset!$F228-dataset!$J228-dataset!$G228-dataset!$H228 -> 75000 | J228: =dataset!$G228*0.08 -> 11600 | K228: =dataset!$F228*12 -> 2779200 | L228: =IF(dataset!$G228>=200000,38%,IF(dataset!$G228<=145000,12.3%,)) -> 0.123 | M228: =dataset!$G228*L229*12 -> 214020 | N228: =IF(Payroll_Data_Analysis[[#This Row],[Annual KPI Bonus Reserve]]<=2979000,Payroll_Data_Analysis[[#This Row],[Annual KPI Bonus Reserve]]*0.302,2979000*0.302+(Payroll_Data_Analysis[[#This Row],[Annual KPI Bonus Reserve]]-2979000)*0.151) -> 64634.04 | O228: =dataset!$K228+dataset!$M228 -> 2993220 | P228: =Payroll_Data_Analysis[[#This Row],[Annual Salary + KPI Bonus]]/12/29.3*31 -> 263907.34 | Q228: =IF(Payroll_Data_Analysis[[#This Row],[Vacation Reserve]]<=2979000,Payroll_Data_Analysis[[#This Row],[Vacation Reserve]]*0.302,2979000*0.302+(Payroll_Data_Analysis[[#This Row],[Vacation Reserve]]-2979000)*0.151) -> 79700.016 | R228: =Payroll_Data_Analysis[[#This Row],[Monthly Salary]]*11 -> 2547600 | S228: =IF(Payroll_Data_Analysis[[#This Row],[11-Month Salary]]<=2979000,Payroll_Data_Analysis[[#This Row],[11-Month Salary]]*0.302,2979000*0.302+(Payroll_Data_Analysis[[#This Row],[11-Month Salary]]-2979000)*0.151) -> 769375.2 | T228: =IF(Payroll_Data_Analysis[[#This Row],[Base Salary (Monthly)]]>=200000,69507,IF(Payroll_Data_Analysis[[#This Row],[Base Salary (Monthly)]]>=145000,52684,35103)) -> 52684 | U228: =Payroll_Data_Analysis[[#This Row],[Annual KPI Bonus Reserve]]+Payroll_Data_Analysis[[#This Row],[Vacation Reserve]]+Payroll_Data_Analysis[[#This Row],[11-Month Salary]] -> 3025527.3 | V228: =Payroll_Data_Analysis[[#This Row],[Payroll Taxes (KPI Bonus)]]+Payroll_Data_Analysis[[#This Row],[Payroll Taxes (Vacation)]]+Payroll_Data_Analysis[[#This Row],[Payroll Taxes (Salary)]] -> 913709.26 | W228: =Payroll_Data_Analysis[[#This Row],[Total Payroll]]+Payroll_Data_Analysis[[#This Row],[Total Payroll Taxes]] -> 3939236.6
A229: Fire & Safety Systems | B229: Emp_229 | C229: Deputy Department Manager | D229: =VLOOKUP(Payroll_Data_Analysis[[#This Row],[Position]],Position_Map!$A$2:$B$58,2,FALSE) -> Management | E229: 1 | F229: 211600 | G229: 145000 | I229: =dataset!$F229-dataset!$J229-dataset!$G229-dataset!$H229 -> 55000 | J229: =dataset!$G229*0.08 -> 11600 | K229: =dataset!$F229*12 -> 2539200 | L229: =IF(dataset!$G229>=200000,38%,IF(dataset!$G229<=145000,12.3%,)) -> 0.123 | M229: =dataset!$G229*L230*12 -> 214020 | N229: =IF(Payroll_Data_Analysis[[#This Row],[Annual KPI Bonus Reserve]]<=2979000,Payroll_Data_Analysis[[#This Row],[Annual KPI Bonus Reserve]]*0.302,2979000*0.302+(Payroll_Data_Analysis[[#This Row],[Annual KPI Bonus Reserve]]-2979000)*0.151) -> 64634.04 | O229: =dataset!$K229+dataset!$M229 -> 2753220 | P229: =Payroll_Data_Analysis[[#This Row],[Annual Salary + KPI Bonus]]/12/29.3*31 -> 242746.93 | Q229: =IF(Payroll_Data_Analysis[[#This Row],[Vacation Reserve]]<=2979000,Payroll_Data_Analysis[[#This Row],[Vacation Reserve]]*0.302,2979000*0.302+(Payroll_Data_Analysis[[#This Row],[Vacation Reserve]]-2979000)*0.151) -> 73309.572 | R229: =Payroll_Data_Analysis[[#This Row],[Monthly Salary]]*11 -> 2327600 | S229: =IF(Payroll_Data_Analysis[[#This Row],[11-Month Salary]]<=2979000,Payroll_Data_Analysis[[#This Row],[11-Month Salary]]*0.302,2979000*0.302+(Payroll_Data_Analysis[[#This Row],[11-Month Salary]]-2979000)*0.151) -> 702935.2 | T229: =IF(Payroll_Data_Analysis[[#This Row],[Base Salary (Monthly)]]>=200000,69507,IF(Payroll_Data_Analysis[[#This Row],[Base Salary (Monthly)]]>=145000,52684,35103)) -> 52684 | U229: =Payroll_Data_Analysis[[#This Row],[Annual KPI Bonus Reserve]]+Payroll_Data_Analysis[[#This Row],[Vacation Reserve]]+Payroll_Data_Analysis[[#This Row],[11-Month Salary]] -> 2784366.9 | V229: =Payroll_Data_Analysis[[#This Row],[Payroll Taxes (KPI Bonus)]]+Payroll_Data_Analysis[[#This Row],[Payroll Taxes (Vacation)]]+Payroll_Data_Analysis[[#This Row],[Payroll Taxes (Salary)]] -> 840878.81 | W229: =Payroll_Data_Analysis[[#This Row],[Total Payroll]]+Payroll_Data_Analysis[[#This Row],[Total Payroll Taxes]] -> 3625245.7
A230: Fire & Safety Systems | B230: Emp_230 | C230: Senior Engineer | D230: =VLOOKUP(Payroll_Data_Analysis[[#This Row],[Position]],Position_Map!$A$2:$B$58,2,FALSE) -> Engineering | E230: 1 | F230: 136400 | G230: 100000 | I230: =dataset!$F230-dataset!$J230-dataset!$G230-dataset!$H230 -> 28400 | J230: =dataset!$G230*0.08 -> 8000 | K230: =dataset!$F230*12 -> 1636800 | L230: =IF(dataset!$G230>=200000,38%,IF(dataset!$G230<=145000,12.3%,)) -> 0.123 | M230: =dataset!$G230*L231*12 -> 147600 | N230: =IF(Payroll_Data_Analysis[[#This Row],[Annual KPI Bonus Reserve]]<=2979000,Payroll_Data_Analysis[[#This Row],[Annual KPI Bonus Reserve]]*0.302,2979000*0.302+(Payroll_Data_Analysis[[#This Row],[Annual KPI Bonus Reserve]]-2979000)*0.151) -> 44575.2 | O230: =dataset!$K230+dataset!$M230 -> 1784400 | P230: =Payroll_Data_Analysis[[#This Row],[Annual Salary + KPI Bonus]]/12/29.3*31 -> 157327.65 | Q230: =IF(Payroll_Data_Analysis[[#This Row],[Vacation Reserve]]<=2979000,Payroll_Data_Analysis[[#This Row],[Vacation Reserve]]*0.302,2979000*0.302+(Payroll_Data_Analysis[[#This Row],[Vacation Reserve]]-2979000)*0.151) -> 47512.949 | R230: =Payroll_Data_Analysis[[#This Row],[Monthly Salary]]*11 -> 1500400 | S230: =IF(Payroll_Data_Analysis[[#This Row],[11-Month Salary]]<=2979000,Payroll_Data_Analysis[[#This Row],[11-Month Salary]]*0.302,2979000*0.302+(Payroll_Data_Analysis[[#This Row],[11-Month Salary]]-2979000)*0.151) -> 453120.8 | T230: =IF(Payroll_Data_Analysis[[#This Row],[Base Salary (Monthly)]]>=200000,69507,IF(Payroll_Data_Analysis[[#This Row],[Base Salary (Monthly)]]>=145000,52684,35103)) -> 35103 | U230: =Payroll_Data_Analysis[[#This Row],[Annual KPI Bonus Reserve]]+Payroll_Data_Analysis[[#This Row],[Vacation Reserve]]+Payroll_Data_Analysis[[#This Row],[11-Month Salary]] -> 1805327.6 | V230: =Payroll_Data_Analysis[[#This Row],[Payroll Taxes (KPI Bonus)]]+Payroll_Data_Analysis[[#This Row],[Payroll Taxes (Vacation)]]+Payroll_Data_Analysis[[#This Row],[Payroll Taxes (Salary)]] -> 545208.95 | W230: =Payroll_Data_Analysis[[#This Row],[Total Payroll]]+Payroll_Data_Analysis[[#This Row],[Total Payroll Taxes]] -> 2350536.6
A231: Fire & Safety Systems | B231: Emp_231 | C231: Senior Engineer | D231: =VLOOKUP(Payroll_Data_Analysis[[#This Row],[Position]],Position_Map!$A$2:$B$58,2,FALSE) -> Engineering | E231: 1 | F231: 136400 | G231: 100000 | I231: =dataset!$F231-dataset!$J231-dataset!$G231-dataset!$H231 -> 28400 | J231: =dataset!$G231*0.08 -> 8000 | K231: =dataset!$F231*12 -> 1636800 | L231: =IF(dataset!$G231>=200000,38%,IF(dataset!$G231<=145000,12.3%,)) -> 0.123 | M231: =dataset!$G231*L232*12 -> 147600 | N231: =IF(Payroll_Data_Analysis[[#This Row],[Annual KPI Bonus Reserve]]<=2979000,Payroll_Data_Analysis[[#This Row],[Annual KPI Bonus Reserve]]*0.302,2979000*0.302+(Payroll_Data_Analysis[[#This Row],[Annual KPI Bonus Reserve]]-2979000)*0.151) -> 44575.2 | O231: =dataset!$K231+dataset!$M231 -> 1784400 | P231: =Payroll_Data_Analysis[[#This Row],[Annual Salary + KPI Bonus]]/12/29.3*31 -> 157327.65 | Q231: =IF(Payroll_Data_Analysis[[#This Row],[Vacation Reserve]]<=2979000,Payroll_Data_Analysis[[#This Row],[Vacation Reserve]]*0.302,2979000*0.302+(Payroll_Data_Analysis[[#This Row],[Vacation Reserve]]-2979000)*0.151) -> 47512.949 | R231: =Payroll_Data_Analysis[[#This Row],[Monthly Salary]]*11 -> 1500400 | S231: =IF(Payroll_Data_Analysis[[#This Row],[11-Month Salary]]<=2979000,Payroll_Data_Analysis[[#This Row],[11-Month Salary]]*0.302,2979000*0.302+(Payroll_Data_Analysis[[#This Row],[11-Month Salary]]-2979000)*0.151) -> 453120.8 | T231: =IF(Payroll_Data_Analysis[[#This Row],[Base Salary (Monthly)]]>=200000,69507,IF(Payroll_Data_Analysis[[#This Row],[Base Salary (Monthly)]]>=145000,52684,35103)) -> 35103 | U231: =Payroll_Data_Analysis[[#This Row],[Annual KPI Bonus Reserve]]+Payroll_Data_Analysis[[#This Row],[Vacation Reserve]]+Payroll_Data_Analysis[[#This Row],[11-Month Salary]] -> 1805327.6 | V231: =Payroll_Data_Analysis[[#This Row],[Payroll Taxes (KPI Bonus)]]+Payroll_Data_Analysis[[#This Row],[Payroll Taxes (Vacation)]]+Payroll_Data_Analysis[[#This Row],[Payroll Taxes (Salary)]] -> 545208.95 | W231: =Payroll_Data_Analysis[[#This Row],[Total Payroll]]+Payroll_Data_Analysis[[#This Row],[Total Payroll Taxes]] -> 2350536.6
A232: Fire & Safety Systems | B232: Emp_232 | C232: Lead Specialist | D232: =VLOOKUP(Payroll_Data_Analysis[[#This Row],[Position]],Position_Map!$A$2:$B$58,2,FALSE) -> Professional | E232: 1 | F232: 94800 | G232: 60000 | I232: =dataset!$F232-dataset!$J232-dataset!$G232-dataset!$H232 -> 30000 | J232: =dataset!$G232*0.08 -> 4800 | K232: =dataset!$F232*12 -> 1137600 | L232: =IF(dataset!$G232>=200000,38%,IF(dataset!$G232<=145000,12.3%,)) -> 0.123 | M232: =dataset!$G232*L233*12 -> 88560 | N232: =IF(Payroll_Data_Analysis[[#This Row],[Annual KPI Bonus Reserve]]<=2979000,Payroll_Data_Analysis[[#This Row],[Annual KPI Bonus Reserve]]*0.302,2979000*0.302+(Payroll_Data_Analysis[[#This Row],[Annual KPI Bonus Reserve]]-2979000)*0.151) -> 26745.12 | O232: =dataset!$K232+dataset!$M232 -> 1226160 | P232: =Payroll_Data_Analysis[[#This Row],[Annual Salary + KPI Bonus]]/12/29.3*31 -> 108108.53 | Q232: =IF(Payroll_Data_Analysis[[#This Row],[Vacation Reserve]]<=2979000,Payroll_Data_Analysis[[#This Row],[Vacation Reserve]]*0.302,2979000*0.302+(Payroll_Data_Analysis[[#This Row],[Vacation Reserve]]-2979000)*0.151) -> 32648.777 | R232: =Payroll_Data_Analysis[[#This Row],[Monthly Salary]]*11 -> 1042800 | S232: =IF(Payroll_Data_Analysis[[#This Row],[11-Month Salary]]<=2979000,Payroll_Data_Analysis[[#This Row],[11-Month Salary]]*0.302,2979000*0.302+(Payroll_Data_Analysis[[#This Row],[11-Month Salary]]-2979000)*0.151) -> 314925.6 | T232: =IF(Payroll_Data_Analysis[[#This Row],[Base Salary (Monthly)]]>=200000,69507,IF(Payroll_Data_Analysis[[#This Row],[Base Salary (Monthly)]]>=145000,52684,35103)) -> 35103 | U232: =Payroll_Data_Analysis[[#This Row],[Annual KPI Bonus Reserve]]+Payroll_Data_Analysis[[#This Row],[Vacation Reserve]]+Payroll_Data_Analysis[[#This Row],[11-Month Salary]] -> 1239468.5 | V232: =Payroll_Data_Analysis[[#This Row],[Payroll Taxes (KPI Bonus)]]+Payroll_Data_Analysis[[#This Row],[Payroll Taxes (Vacation)]]+Payroll_Data_Analysis[[#This Row],[Payroll Taxes (Salary)]] -> 374319.5 | W232: =Payroll_Data_Analysis[[#This Row],[Total Payroll]]+Payroll_Data_Analysis[[#This Row],[Total Payroll Taxes]] -> 1613788
A233: Fire & Safety Systems | B233: Emp_233 | C233: Senior Specialist | D233: =VLOOKUP(Payroll_Data_Analysis[[#This Row],[Position]],Position_Map!$A$2:$B$58,2,FALSE) -> Professional | E233: 1 | F233: 126400 | G233: 100000 | I233: =dataset!$F233-dataset!$J233-dataset!$G233-dataset!$H233 -> 18400 | J233: =dataset!$G233*0.08 -> 8000 | K233: =dataset!$F233*12 -> 1516800 | L233: =IF(dataset!$G233>=200000,38%,IF(dataset!$G233<=145000,12.3%,)) -> 0.123 | M233: =dataset!$G233*L234*12 -> 147600 | N233: =IF(Payroll_Data_Analysis[[#This Row],[Annual KPI Bonus Reserve]]<=2979000,Payroll_Data_Analysis[[#This Row],[Annual KPI Bonus Reserve]]*0.302,2979000*0.302+(Payroll_Data_Analysis[[#This Row],[Annual KPI Bonus Reserve]]-2979000)*0.151) -> 44575.2 | O233: =dataset!$K233+dataset!$M233 -> 1664400 | P233: =Payroll_Data_Analysis[[#This Row],[Annual Salary + KPI Bonus]]/12/29.3*31 -> 146747.44 | Q233: =IF(Payroll_Data_Analysis[[#This Row],[Vacation Reserve]]<=2979000,Payroll_Data_Analysis[[#This Row],[Vacation Reserve]]*0.302,2979000*0.302+(Payroll_Data_Analysis[[#This Row],[Vacation Reserve]]-2979000)*0.151) -> 44317.727 | R233: =Payroll_Data_Analysis[[#This Row],[Monthly Salary]]*11 -> 1390400 | S233: =IF(Payroll_Data_Analysis[[#This Row],[11-Month Salary]]<=2979000,Payroll_Data_Analysis[[#This Row],[11-Month Salary]]*0.302,2979000*0.302+(Payroll_Data_Analysis[[#This Row],[11-Month Salary]]-2979000)*0.151) -> 419900.8 | T233: =IF(Payroll_Data_Analysis[[#This Row],[Base Salary (Monthly)]]>=200000,69507,IF(Payroll_Data_Analysis[[#This Row],[Base Salary (Monthly)]]>=145000,52684,35103)) -> 35103 | U233: =Payroll_Data_Analysis[[#This Row],[Annual KPI Bonus Reserve]]+Payroll_Data_Analysis[[#This Row],[Vacation Reserve]]+Payroll_Data_Analysis[[#This Row],[11-Month Salary]] -> 1684747.4 | V233: =Payroll_Data_Analysis[[#This Row],[Payroll Taxes (KPI Bonus)]]+Payroll_Data_Analysis[[#This Row],[Payroll Taxes (Vacation)]]+Payroll_Data_Analysis[[#This Row],[Payroll Taxes (Salary)]] -> 508793.73 | W233: =Payroll_Data_Analysis[[#This Row],[Total Payroll]]+Payroll_Data_Analysis[[#This Row],[Total Payroll Taxes]] -> 2193541.2
A234: Fire & Safety Systems | B234: Emp_234 | C234: Engineer | D234: =VLOOKUP(Payroll_Data_Analysis[[#This Row],[Position]],Position_Map!$A$2:$B$58,2,FALSE) -> Engineering | E234: 1 | F234: 158000 | G234: 100000 | I234: =dataset!$F234-dataset!$J234-dataset!$G234-dataset!$H234 -> 50000 | J234: =dataset!$G234*0.08 -> 8000 | K234: =dataset!$F234*12 -> 1896000 | L234: =IF(dataset!$G234>=200000,38%,IF(dataset!$G234<=145000,12.3%,)) -> 0.123 | M234: =dataset!$G234*L235*12 -> 147600 | N234: =IF(Payroll_Data_Analysis[[#This Row],[Annual KPI Bonus Reserve]]<=2979000,Payroll_Data_Analysis[[#This Row],[Annual KPI Bonus Reserve]]*0.302,2979000*0.302+(Payroll_Data_Analysis[[#This Row],[Annual KPI Bonus Reserve]]-2979000)*0.151) -> 44575.2 | O234: =dataset!$K234+dataset!$M234 -> 2043600 | P234: =Payroll_Data_Analysis[[#This Row],[Annual Salary + KPI Bonus]]/12/29.3*31 -> 180180.89 | Q234: =IF(Payroll_Data_Analysis[[#This Row],[Vacation Reserve]]<=2979000,Payroll_Data_Analysis[[#This Row],[Vacation Reserve]]*0.302,2979000*0.302+(Payroll_Data_Analysis[[#This Row],[Vacation Reserve]]-2979000)*0.151) -> 54414.628 | R234: =Payroll_Data_Analysis[[#This Row],[Monthly Salary]]*11 -> 1738000 | S234: =IF(Payroll_Data_Analysis[[#This Row],[11-Month Salary]]<=2979000,Payroll_Data_Analysis[[#This Row],[11-Month Salary]]*0.302,2979000*0.302+(Payroll_Data_Analysis[[#This Row],[11-Month Salary]]-2979000)*0.151) -> 524876 | T234: =IF(Payroll_Data_Analysis[[#This Row],[Base Salary (Monthly)]]>=200000,69507,IF(Payroll_Data_Analysis[[#This Row],[Base Salary (Monthly)]]>=145000,52684,35103)) -> 35103 | U234: =Payroll_Data_Analysis[[#This Row],[Annual KPI Bonus Reserve]]+Payroll_Data_Analysis[[#This Row],[Vacation Reserve]]+Payroll_Data_Analysis[[#This Row],[11-Month Salary]] -> 2065780.9 | V234: =Payroll_Data_Analysis[[#This Row],[Payroll Taxes (KPI Bonus)]]+Payroll_Data_Analysis[[#This Row],[Payroll Taxes (Vacation)]]+Payroll_Data_Analysis[[#This Row],[Payroll Taxes (Salary)]] -> 623865.83 | W234: =Payroll_Data_Analysis[[#This Row],[Total Payroll]]+Payroll_Data_Analysis[[#This Row],[Total Payroll Taxes]] -> 2689646.7
A235: Fire & Safety Systems | B235: Emp_235 | C235: Specialist | D235: =VLOOKUP(Payroll_Data_Analysis[[#This Row],[Position]],Position_Map!$A$2:$B$58,2,FALSE) -> Professional | E235: 1 | F235: 81000 | G235: 60000 | I235: =dataset!$F235-dataset!$J235-dataset!$G235-dataset!$H235 -> 16200 | J235: =dataset!$G235*0.08 -> 4800 | K235: =dataset!$F235*12 -> 972000 | L235: =IF(dataset!$G235>=200000,38%,IF(dataset!$G235<=145000,12.3%,)) -> 0.123 | M235: =dataset!$G235*L236*12 -> 88560 | N235: =IF(Payroll_Data_Analysis[[#This Row],[Annual KPI Bonus Reserve]]<=2979000,Payroll_Data_Analysis[[#This Row],[Annual KPI Bonus Reserve]]*0.302,2979000*0.302+(Payroll_Data_Analysis[[#This Row],[Annual KPI Bonus Reserve]]-2979000)*0.151) -> 26745.12 | O235: =dataset!$K235+dataset!$M235 -> 1060560 | P235: =Payroll_Data_Analysis[[#This Row],[Annual Salary + KPI Bonus]]/12/29.3*31 -> 93507.85 | Q235: =IF(Payroll_Data_Analysis[[#This Row],[Vacation Reserve]]<=2979000,Payroll_Data_Analysis[[#This Row],[Vacation Reserve]]*0.302,2979000*0.302+(Payroll_Data_Analysis[[#This Row],[Vacation Reserve]]-2979000)*0.151) -> 28239.371 | R235: =Payroll_Data_Analysis[[#This Row],[Monthly Salary]]*11 -> 891000 | S235: =IF(Payroll_Data_Analysis[[#This Row],[11-Month Salary]]<=2979000,Payroll_Data_Analysis[[#This Row],[11-Month Salary]]*0.302,2979000*0.302+(Payroll_Data_Analysis[[#This Row],[11-Month Salary]]-2979000)*0.151) -> 269082 | T235: =IF(Payroll_Data_Analysis[[#This Row],[Base Salary (Monthly)]]>=200000,69507,IF(Payroll_Data_Analysis[[#This Row],[Base Salary (Monthly)]]>=145000,52684,35103)) -> 35103 | U235: =Payroll_Data_Analysis[[#This Row],[Annual KPI Bonus Reserve]]+Payroll_Data_Analysis[[#This Row],[Vacation Reserve]]+Payroll_Data_Analysis[[#This Row],[11-Month Salary]] -> 1073067.8 | V235: =Payroll_Data_Analysis[[#This Row],[Payroll Taxes (KPI Bonus)]]+Payroll_Data_Analysis[[#This Row],[Payroll Taxes (Vacation)]]+Payroll_Data_Analysis[[#This Row],[Payroll Taxes (Salary)]] -> 324066.49 | W235: =Payroll_Data_Analysis[[#This Row],[Total Payroll]]+Payroll_Data_Analysis[[#This Row],[Total Payroll Taxes]] -> 1397134.3
A236: Fire & Safety Systems | B236: Emp_236 | C236: Department Manager | D236: =VLOOKUP(Payroll_Data_Analysis[[#This Row],[Position]],Position_Map!$A$2:$B$58,2,FALSE) -> Management | E236: 1 | F236: 221600 | G236: 145000 | I236: =dataset!$F236-dataset!$J236-dataset!$G236-dataset!$H236 -> 65000 | J236: =dataset!$G236*0.08 -> 11600 | K236: =dataset!$F236*12 -> 2659200 | L236: =IF(dataset!$G236>=200000,38%,IF(dataset!$G236<=145000,12.3%,)) -> 0.123 | M236: =dataset!$G236*L237*12 -> 214020 | N236: =IF(Payroll_Data_Analysis[[#This Row],[Annual KPI Bonus Reserve]]<=2979000,Payroll_Data_Analysis[[#This Row],[Annual KPI Bonus Reserve]]*0.302,2979000*0.302+(Payroll_Data_Analysis[[#This Row],[Annual KPI Bonus Reserve]]-2979000)*0.151) -> 64634.04 | O236: =dataset!$K236+dataset!$M236 -> 2873220 | P236: =Payroll_Data_Analysis[[#This Row],[Annual Salary + KPI Bonus]]/12/29.3*31 -> 253327.13 | Q236: =IF(Payroll_Data_Analysis[[#This Row],[Vacation Reserve]]<=2979000,Payroll_Data_Analysis[[#This Row],[Vacation Reserve]]*0.302,2979000*0.302+(Payroll_Data_Analysis[[#This Row],[Vacation Reserve]]-2979000)*0.151) -> 76504.794 | R236: =Payroll_Data_Analysis[[#This Row],[Monthly Salary]]*11 -> 2437600 | S236: =IF(Payroll_Data_Analysis[[#This Row],[11-Month Salary]]<=2979000,Payroll_Data_Analysis[[#This Row],[11-Month Salary]]*0.302,2979000*0.302+(Payroll_Data_Analysis[[#This Row],[11-Month Salary]]-2979000)*0.151) -> 736155.2 | T236: =IF(Payroll_Data_Analysis[[#This Row],[Base Salary (Monthly)]]>=200000,69507,IF(Payroll_Data_Analysis[[#This Row],[Base Salary (Monthly)]]>=145000,52684,35103)) -> 52684 | U236: =Payroll_Data_Analysis[[#This Row],[Annual KPI Bonus Reserve]]+Payroll_Data_Analysis[[#This Row],[Vacation Reserve]]+Payroll_Data_Analysis[[#This Row],[11-Month Salary]] -> 2904947.1 | V236: =Payroll_Data_Analysis[[#This Row],[Payroll Taxes (KPI Bonus)]]+Payroll_Data_Analysis[[#This Row],[Payroll Taxes (Vacation)]]+Payroll_Data_Analysis[[#This Row],[Payroll Taxes (Salary)]] -> 877294.03 | W236: =Payroll_Data_Analysis[[#This Row],[Total Payroll]]+Payroll_Data_Analysis[[#This Row],[Total Payroll Taxes]] -> 3782241.2
A237: Fire & Safety Systems | B237: Emp_237 | C237: Deputy Department Manager | D237: =VLOOKUP(Payroll_Data_Analysis[[#This Row],[Position]],Position_Map!$A$2:$B$58,2,FALSE) -> Management | E237: 1 | F237: 173000 | G237: 100000 | I237: =dataset!$F237-dataset!$J237-dataset!$G237-dataset!$H237 -> 65000 | J237: =dataset!$G237*0.08 -> 8000 | K237: =dataset!$F237*12 -> 2076000 | L237: =IF(dataset!$G237>=200000,38%,IF(dataset!$G237<=145000,12.3%,)) -> 0.123 | M237: =dataset!$G237*L238*12 -> 147600 | N237: =IF(Payroll_Data_Analysis[[#This Row],[Annual KPI Bonus Reserve]]<=2979000,Payroll_Data_Analysis[[#This Row],[Annual KPI Bonus Reserve]]*0.302,2979000*0.302+(Payroll_Data_Analysis[[#This Row],[Annual KPI Bonus Reserve]]-2979000)*0.151) -> 44575.2 | O237: =dataset!$K237+dataset!$M237 -> 2223600 | P237: =Payroll_Data_Analysis[[#This Row],[Annual Salary + KPI Bonus]]/12/29.3*31 -> 196051.19 | Q237: =IF(Payroll_Data_Analysis[[#This Row],[Vacation Reserve]]<=2979000,Payroll_Data_Analysis[[#This Row],[Vacation Reserve]]*0.302,2979000*0.302+(Payroll_Data_Analysis[[#This Row],[Vacation Reserve]]-2979000)*0.151) -> 59207.461 | R237: =Payroll_Data_Analysis[[#This Row],[Monthly Salary]]*11 -> 1903000 | S237: =IF(Payroll_Data_Analysis[[#This Row],[11-Month Salary]]<=2979000,Payroll_Data_Analysis[[#This Row],[11-Month Salary]]*0.302,2979000*0.302+(Payroll_Data_Analysis[[#This Row],[11-Month Salary]]-2979000)*0.151) -> 574706 | T237: =IF(Payroll_Data_Analysis[[#This Row],[Base Salary (Monthly)]]>=200000,69507,IF(Payroll_Data_Analysis[[#This Row],[Base Salary (Monthly)]]>=145000,52684,35103)) -> 35103 | U237: =Payroll_Data_Analysis[[#This Row],[Annual KPI Bonus Reserve]]+Payroll_Data_Analysis[[#This Row],[Vacation Reserve]]+Payroll_Data_Analysis[[#This Row],[11-Month Salary]] -> 2246651.2 | V237: =Payroll_Data_Analysis[[#This Row],[Payroll Taxes (KPI Bonus)]]+Payroll_Data_Analysis[[#This Row],[Payroll Taxes (Vacation)]]+Payroll_Data_Analysis[[#This Row],[Payroll Taxes (Salary)]] -> 678488.66 | W237: =Payroll_Data_Analysis[[#This Row],[Total Payroll]]+Payroll_Data_Analysis[[#This Row],[Total Payroll Taxes]] -> 2925139.9
A238: Fire & Safety Systems | B238: Emp_238 | C238: Senior Engineer | D238: =VLOOKUP(Payroll_Data_Analysis[[#This Row],[Position]],Position_Map!$A$2:$B$58,2,FALSE) -> Engineering | E238: 1 | F238: 124400 | G238: 100000 | I238: =dataset!$F238-dataset!$J238-dataset!$G238-dataset!$H238 -> 16400 | J238: =dataset!$G238*0.08 -> 8000 | K238: =dataset!$F238*12 -> 1492800 | L238: =IF(dataset!$G238>=200000,38%,IF(dataset!$G238<=145000,12.3%,)) -> 0.123 | M238: =dataset!$G238*L239*12 -> 147600 | N238: =IF(Payroll_Data_Analysis[[#This Row],[Annual KPI Bonus Reserve]]<=2979000,Payroll_Data_Analysis[[#This Row],[Annual KPI Bonus Reserve]]*0.302,2979000*0.302+(Payroll_Data_Analysis[[#This Row],[Annual KPI Bonus Reserve]]-2979000)*0.151) -> 44575.2 | O238: =dataset!$K238+dataset!$M238 -> 1640400 | P238: =Payroll_Data_Analysis[[#This Row],[Annual Salary + KPI Bonus]]/12/29.3*31 -> 144631.4 | Q238: =IF(Payroll_Data_Analysis[[#This Row],[Vacation Reserve]]<=2979000,Payroll_Data_Analysis[[#This Row],[Vacation Reserve]]*0.302,2979000*0.302+(Payroll_Data_Analysis[[#This Row],[Vacation Reserve]]-2979000)*0.151) -> 43678.683 | R238: =Payroll_Data_Analysis[[#This Row],[Monthly Salary]]*11 -> 1368400 | S238: =IF(Payroll_Data_Analysis[[#This Row],[11-Month Salary]]<=2979000,Payroll_Data_Analysis[[#This Row],[11-Month Salary]]*0.302,2979000*0.302+(Payroll_Data_Analysis[[#This Row],[11-Month Salary]]-2979000)*0.151) -> 413256.8 | T238: =IF(Payroll_Data_Analysis[[#This Row],[Base Salary (Monthly)]]>=200000,69507,IF(Payroll_Data_Analysis[[#This Row],[Base Salary (Monthly)]]>=145000,52684,35103)) -> 35103 | U238: =Payroll_Data_Analysis[[#This Row],[Annual KPI Bonus Reserve]]+Payroll_Data_Analysis[[#This Row],[Vacation Reserve]]+Payroll_Data_Analysis[[#This Row],[11-Month Salary]] -> 1660631.4 | V238: =Payroll_Data_Analysis[[#This Row],[Payroll Taxes (KPI Bonus)]]+Payroll_Data_Analysis[[#This Row],[Payroll Taxes (Vacation)]]+Payroll_Data_Analysis[[#This Row],[Payroll Taxes (Salary)]] -> 501510.68 | W238: =Payroll_Data_Analysis[[#This Row],[Total Payroll]]+Payroll_Data_Analysis[[#This Row],[Total Payroll Taxes]] -> 2162142.1
... A497: Emergency & Fire Safety | B497: Emp_497 | C497: Engineer | D497: =VLOOKUP(Payroll_Data_Analysis[[#This Row],[Position]],Position_Map!$A$2:$B$58,2,FALSE) -> Engineering | E497: 1 | F497: 101400 | G497: 80000 | I497: =dataset!$F497-dataset!$J497-dataset!$G497-dataset!$H497 -> 15000 | J497: =dataset!$G497*0.08 -> 6400 | K497: =dataset!$F497*12 -> 1216800 | L497: =IF(dataset!$G497>=200000,38%,IF(dataset!$G497<=145000,12.3%,)) -> 0.123 | M497: =dataset!$G497*L498*12 -> 364800 | N497: =IF(Payroll_Data_Analysis[[#This Row],[Annual KPI Bonus Reserve]]<=2979000,Payroll_Data_Analysis[[#This Row],[Annual KPI Bonus Reserve]]*0.302,2979000*0.302+(Payroll_Data_Analysis[[#This Row],[Annual KPI Bonus Reserve]]-2979000)*0.151) -> 110169.6 | O497: =dataset!$K497+dataset!$M497 -> 1581600 | P497: =Payroll_Data_Analysis[[#This Row],[Annual Salary + KPI Bonus]]/12/29.3*31 -> 139447.1 | Q497: =IF(Payroll_Data_Analysis[[#This Row],[Vacation Reserve]]<=2979000,Payroll_Data_Analysis[[#This Row],[Vacation Reserve]]*0.302,2979000*0.302+(Payroll_Data_Analysis[[#This Row],[Vacation Reserve]]-2979000)*0.151) -> 42113.024 | R497: =Payroll_Data_Analysis[[#This Row],[Monthly Salary]]*11 -> 1115400 | S497: =IF(Payroll_Data_Analysis[[#This Row],[11-Month Salary]]<=2979000,Payroll_Data_Analysis[[#This Row],[11-Month Salary]]*0.302,2979000*0.302+(Payroll_Data_Analysis[[#This Row],[11-Month Salary]]-2979000)*0.151) -> 336850.8 | T497: =IF(Payroll_Data_Analysis[[#This Row],[Base Salary (Monthly)]]>=200000,69507,IF(Payroll_Data_Analysis[[#This Row],[Base Salary (Monthly)]]>=145000,52684,35103)) -> 35103 | U497: =Payroll_Data_Analysis[[#This Row],[Annual KPI Bonus Reserve]]+Payroll_Data_Analysis[[#This Row],[Vacation Reserve]]+Payroll_Data_Analysis[[#This Row],[11-Month Salary]] -> 1619647.1 | V497: =Payroll_Data_Analysis[[#This Row],[Payroll Taxes (KPI Bonus)]]+Payroll_Data_Analysis[[#This Row],[Payroll Taxes (Vacation)]]+Payroll_Data_Analysis[[#This Row],[Payroll Taxes (Salary)]] -> 489133.42 | W497: =Payroll_Data_Analysis[[#This Row],[Total Payroll]]+Payroll_Data_Analysis[[#This Row],[Total Payroll Taxes]] -> 2108780.5
A498: Finance | B498: Emp_498 | C498: Department Director | D498: =VLOOKUP(Payroll_Data_Analysis[[#This Row],[Position]],Position_Map!$A$2:$B$58,2,FALSE) -> Management | E498: 1 | F498: 396000 | G498: 200000 | H498: 20000 | I498: =dataset!$F498-dataset!$J498-dataset!$G498-dataset!$H498 -> 160000 | J498: =dataset!$G498*0.08 -> 16000 | K498: =dataset!$F498*12 -> 4752000 | L498: =IF(dataset!$G498>=200000,38%,IF(dataset!$G498<=145000,12.3%,)) -> 0.38 | M498: =dataset!$G498*L499*12 -> 295200 | N498: =IF(Payroll_Data_Analysis[[#This Row],[Annual KPI Bonus Reserve]]<=2979000,Payroll_Data_Analysis[[#This Row],[Annual KPI Bonus Reserve]]*0.302,2979000*0.302+(Payroll_Data_Analysis[[#This Row],[Annual KPI Bonus Reserve]]-2979000)*0.151) -> 89150.4 | O498: =dataset!$K498+dataset!$M498 -> 5047200 | P498: =Payroll_Data_Analysis[[#This Row],[Annual Salary + KPI Bonus]]/12/29.3*31 -> 445003.41 | Q498: =IF(Payroll_Data_Analysis[[#This Row],[Vacation Reserve]]<=2979000,Payroll_Data_Analysis[[#This Row],[Vacation Reserve]]*0.302,2979000*0.302+(Payroll_Data_Analysis[[#This Row],[Vacation Reserve]]-2979000)*0.151) -> 134391.03 | R498: =Payroll_Data_Analysis[[#This Row],[Monthly Salary]]*11 -> 4356000 | S498: =IF(Payroll_Data_Analysis[[#This Row],[11-Month Salary]]<=2979000,Payroll_Data_Analysis[[#This Row],[11-Month Salary]]*0.302,2979000*0.302+(Payroll_Data_Analysis[[#This Row],[11-Month Salary]]-2979000)*0.151) -> 1107585 | T498: =IF(Payroll_Data_Analysis[[#This Row],[Base Salary (Monthly)]]>=200000,69507,IF(Payroll_Data_Analysis[[#This Row],[Base Salary (Monthly)]]>=145000,52684,35103)) -> 69507 | U498: =Payroll_Data_Analysis[[#This Row],[Annual KPI Bonus Reserve]]+Payroll_Data_Analysis[[#This Row],[Vacation Reserve]]+Payroll_Data_Analysis[[#This Row],[11-Month Salary]] -> 5096203.4 | V498: =Payroll_Data_Analysis[[#This Row],[Payroll Taxes (KPI Bonus)]]+Payroll_Data_Analysis[[#This Row],[Payroll Taxes (Vacation)]]+Payroll_Data_Analysis[[#This Row],[Payroll Taxes (Salary)]] -> 1331126.4 | W498: =Payroll_Data_Analysis[[#This Row],[Total Payroll]]+Payroll_Data_Analysis[[#This Row],[Total Payroll Taxes]] -> 6427329.8
A499: Finance | B499: Emp_499 | C499: Head of Division | D499: =VLOOKUP(Payroll_Data_Analysis[[#This Row],[Position]],Position_Map!$A$2:$B$58,2,FALSE) -> Management | E499: 1 | F499: 266000 | G499: 145000 | I499: =dataset!$F499-dataset!$J499-dataset!$G499-dataset!$H499 -> 109400 | J499: =dataset!$G499*0.08 -> 11600 | K499: =dataset!$F499*12 -> 3192000 | L499: =IF(dataset!$G499>=200000,38%,IF(dataset!$G499<=145000,12.3%,)) -> 0.123 | M499: =dataset!$G499*L500*12 -> 214020 | N499: =IF(Payroll_Data_Analysis[[#This Row],[Annual KPI Bonus Reserve]]<=2979000,Payroll_Data_Analysis[[#This Row],[Annual KPI Bonus Reserve]]*0.302,2979000*0.302+(Payroll_Data_Analysis[[#This Row],[Annual KPI Bonus Reserve]]-2979000)*0.151) -> 64634.04 | O499: =dataset!$K499+dataset!$M499 -> 3406020 | P499: =Payroll_Data_Analysis[[#This Row],[Annual Salary + KPI Bonus]]/12/29.3*31 -> 300303.24 | Q499: =IF(Payroll_Data_Analysis[[#This Row],[Vacation Reserve]]<=2979000,Payroll_Data_Analysis[[#This Row],[Vacation Reserve]]*0.302,2979000*0.302+(Payroll_Data_Analysis[[#This Row],[Vacation Reserve]]-2979000)*0.151) -> 90691.579 | R499: =Payroll_Data_Analysis[[#This Row],[Monthly Salary]]*11 -> 2926000 | S499: =IF(Payroll_Data_Analysis[[#This Row],[11-Month Salary]]<=2979000,Payroll_Data_Analysis[[#This Row],[11-Month Salary]]*0.302,2979000*0.302+(Payroll_Data_Analysis[[#This Row],[11-Month Salary]]-2979000)*0.151) -> 883652 | T499: =IF(Payroll_Data_Analysis[[#This Row],[Base Salary (Monthly)]]>=200000,69507,IF(Payroll_Data_Analysis[[#This Row],[Base Salary (Monthly)]]>=145000,52684,35103)) -> 52684 | U499: =Payroll_Data_Analysis[[#This Row],[Annual KPI Bonus Reserve]]+Payroll_Data_Analysis[[#This Row],[Vacation Reserve]]+Payroll_Data_Analysis[[#This Row],[11-Month Salary]] -> 3440323.2 | V499: =Payroll_Data_Analysis[[#This Row],[Payroll Taxes (KPI Bonus)]]+Payroll_Data_Analysis[[#This Row],[Payroll Taxes (Vacation)]]+Payroll_Data_Analysis[[#This Row],[Payroll Taxes (Salary)]] -> 1038977.6 | W499: =Payroll_Data_Analysis[[#This Row],[Total Payroll]]+Payroll_Data_Analysis[[#This Row],[Total Payroll Taxes]] -> 4479300.9
A500: Finance | B500: Emp_500 | C500: Deputy Head of Division | D500: =VLOOKUP(Payroll_Data_Analysis[[#This Row],[Position]],Position_Map!$A$2:$B$58,2,FALSE) -> Management | E500: 1 | F500: 271600 | G500: 145000 | I500: =dataset!$F500-dataset!$J500-dataset!$G500-dataset!$H500 -> 115000 | J500: =dataset!$G500*0.08 -> 11600 | K500: =dataset!$F500*12 -> 3259200 | L500: =IF(dataset!$G500>=200000,38%,IF(dataset!$G500<=145000,12.3%,)) -> 0.123 | M500: =dataset!$G500*L501*12 -> 214020 | N500: =IF(Payroll_Data_Analysis[[#This Row],[Annual KPI Bonus Reserve]]<=2979000,Payroll_Data_Analysis[[#This Row],[Annual KPI Bonus Reserve]]*0.302,2979000*0.302+(Payroll_Data_Analysis[[#This Row],[Annual KPI Bonus Reserve]]-2979000)*0.151) -> 64634.04 | O500: =dataset!$K500+dataset!$M500 -> 3473220 | P500: =Payroll_Data_Analysis[[#This Row],[Annual Salary + KPI Bonus]]/12/29.3*31 -> 306228.16 | Q500: =IF(Payroll_Data_Analysis[[#This Row],[Vacation Reserve]]<=2979000,Payroll_Data_Analysis[[#This Row],[Vacation Reserve]]*0.302,2979000*0.302+(Payroll_Data_Analysis[[#This Row],[Vacation Reserve]]-2979000)*0.151) -> 92480.903 | R500: =Payroll_Data_Analysis[[#This Row],[Monthly Salary]]*11 -> 2987600 | S500: =IF(Payroll_Data_Analysis[[#This Row],[11-Month Salary]]<=2979000,Payroll_Data_Analysis[[#This Row],[11-Month Salary]]*0.302,2979000*0.302+(Payroll_Data_Analysis[[#This Row],[11-Month Salary]]-2979000)*0.151) -> 900956.6 | T500: =IF(Payroll_Data_Analysis[[#This Row],[Base Salary (Monthly)]]>=200000,69507,IF(Payroll_Data_Analysis[[#This Row],[Base Salary (Monthly)]]>=145000,52684,35103)) -> 52684 | U500: =Payroll_Data_Analysis[[#This Row],[Annual KPI Bonus Reserve]]+Payroll_Data_Analysis[[#This Row],[Vacation Reserve]]+Payroll_Data_Analysis[[#This Row],[11-Month Salary]] -> 3507848.2 | V500: =Payroll_Data_Analysis[[#This Row],[Payroll Taxes (KPI Bonus)]]+Payroll_Data_Analysis[[#This Row],[Payroll Taxes (Vacation)]]+Payroll_Data_Analysis[[#This Row],[Payroll Taxes (Salary)]] -> 1058071.5 | W500: =Payroll_Data_Analysis[[#This Row],[Total Payroll]]+Payroll_Data_Analysis[[#This Row],[Total Payroll Taxes]] -> 4565919.7
A501: Finance | B501: Emp_501 | C501: Lead Specialist | D501: =VLOOKUP(Payroll_Data_Analysis[[#This Row],[Position]],Position_Map!$A$2:$B$58,2,FALSE) -> Professional | E501: 1 | F501: 158000 | G501: 100000 | I501: =dataset!$F501-dataset!$J501-dataset!$G501-dataset!$H501 -> 50000 | J501: =dataset!$G501*0.08 -> 8000 | K501: =dataset!$F501*12 -> 1896000 | L501: =IF(dataset!$G501>=200000,38%,IF(dataset!$G501<=145000,12.3%,)) -> 0.123 | M501: =dataset!$G501*L502*12 -> 147600 | N501: =IF(Payroll_Data_Analysis[[#This Row],[Annual KPI Bonus Reserve]]<=2979000,Payroll_Data_Analysis[[#This Row],[Annual KPI Bonus Reserve]]*0.302,2979000*0.302+(Payroll_Data_Analysis[[#This Row],[Annual KPI Bonus Reserve]]-2979000)*0.151) -> 44575.2 | O501: =dataset!$K501+dataset!$M501 -> 2043600 | P501: =Payroll_Data_Analysis[[#This Row],[Annual Salary + KPI Bonus]]/12/29.3*31 -> 180180.89 | Q501: =IF(Payroll_Data_Analysis[[#This Row],[Vacation Reserve]]<=2979000,Payroll_Data_Analysis[[#This Row],[Vacation Reserve]]*0.302,2979000*0.302+(Payroll_Data_Analysis[[#This Row],[Vacation Reserve]]-2979000)*0.151) -> 54414.628 | R501: =Payroll_Data_Analysis[[#This Row],[Monthly Salary]]*11 -> 1738000 | S501: =IF(Payroll_Data_Analysis[[#This Row],[11-Month Salary]]<=2979000,Payroll_Data_Analysis[[#This Row],[11-Month Salary]]*0.302,2979000*0.302+(Payroll_Data_Analysis[[#This Row],[11-Month Salary]]-2979000)*0.151) -> 524876 | T501: =IF(Payroll_Data_Analysis[[#This Row],[Base Salary (Monthly)]]>=200000,69507,IF(Payroll_Data_Analysis[[#This Row],[Base Salary (Monthly)]]>=145000,52684,35103)) -> 35103 | U501: =Payroll_Data_Analysis[[#This Row],[Annual KPI Bonus Reserve]]+Payroll_Data_Analysis[[#This Row],[Vacation Reserve]]+Payroll_Data_Analysis[[#This Row],[11-Month Salary]] -> 2065780.9 | V501: =Payroll_Data_Analysis[[#This Row],[Payroll Taxes (KPI Bonus)]]+Payroll_Data_Analysis[[#This Row],[Payroll Taxes (Vacation)]]+Payroll_Data_Analysis[[#This Row],[Payroll Taxes (Salary)]] -> 623865.83 | W501: =Payroll_Data_Analysis[[#This Row],[Total Payroll]]+Payroll_Data_Analysis[[#This Row],[Total Payroll Taxes]] -> 2689646.7
A502: Finance | B502: Emp_502 | C502: Senior Specialist | D502: =VLOOKUP(Payroll_Data_Analysis[[#This Row],[Position]],Position_Map!$A$2:$B$58,2,FALSE) -> Professional | E502: 1 | F502: 116400 | G502: 80000 | I502: =dataset!$F502-dataset!$J502-dataset!$G502-dataset!$H502 -> 30000 | J502: =dataset!$G502*0.08 -> 6400 | K502: =dataset!$F502*12 -> 1396800 | L502: =IF(dataset!$G502>=200000,38%,IF(dataset!$G502<=145000,12.3%,)) -> 0.123 | M502: =dataset!$G502*L503*12 -> 118080 | N502: =IF(Payroll_Data_Analysis[[#This Row],[Annual KPI Bonus Reserve]]<=2979000,Payroll_Data_Analysis[[#This Row],[Annual KPI Bonus Reserve]]*0.302,2979000*0.302+(Payroll_Data_Analysis[[#This Row],[Annual KPI Bonus Reserve]]-2979000)*0.151) -> 35660.16 | O502: =dataset!$K502+dataset!$M502 -> 1514880 | P502: =Payroll_Data_Analysis[[#This Row],[Annual Salary + KPI Bonus]]/12/29.3*31 -> 133564.51 | Q502: =IF(Payroll_Data_Analysis[[#This Row],[Vacation Reserve]]<=2979000,Payroll_Data_Analysis[[#This Row],[Vacation Reserve]]*0.302,2979000*0.302+(Payroll_Data_Analysis[[#This Row],[Vacation Reserve]]-2979000)*0.151) -> 40336.481 | R502: =Payroll_Data_Analysis[[#This Row],[Monthly Salary]]*11 -> 1280400 | S502: =IF(Payroll_Data_Analysis[[#This Row],[11-Month Salary]]<=2979000,Payroll_Data_Analysis[[#This Row],[11-Month Salary]]*0.302,2979000*0.302+(Payroll_Data_Analysis[[#This Row],[11-Month Salary]]-2979000)*0.151) -> 386680.8 | T502: =IF(Payroll_Data_Analysis[[#This Row],[Base Salary (Monthly)]]>=200000,69507,IF(Payroll_Data_Analysis[[#This Row],[Base Salary (Monthly)]]>=145000,52684,35103)) -> 35103 | U502: =Payroll_Data_Analysis[[#This Row],[Annual KPI Bonus Reserve]]+Payroll_Data_Analysis[[#This Row],[Vacation Reserve]]+Payroll_Data_Analysis[[#This Row],[11-Month Salary]] -> 1532044.5 | V502: =Payroll_Data_Analysis[[#This Row],[Payroll Taxes (KPI Bonus)]]+Payroll_Data_Analysis[[#This Row],[Payroll Taxes (Vacation)]]+Payroll_Data_Analysis[[#This Row],[Payroll Taxes (Salary)]] -> 462677.44 | W502: =Payroll_Data_Analysis[[#This Row],[Total Payroll]]+Payroll_Data_Analysis[[#This Row],[Total Payroll Taxes]] -> 1994721.9
A503: Finance | B503: Emp_503 | C503: Senior Specialist | D503: =VLOOKUP(Payroll_Data_Analysis[[#This Row],[Position]],Position_Map!$A$2:$B$58,2,FALSE) -> Professional | E503: 1 | F503: 173000 | G503: 100000 | I503: =dataset!$F503-dataset!$J503-dataset!$G503-dataset!$H503 -> 65000 | J503: =dataset!$G503*0.08 -> 8000 | K503: =dataset!$F503*12 -> 2076000 | L503: =IF(dataset!$G503>=200000,38%,IF(dataset!$G503<=145000,12.3%,)) -> 0.123 | M503: =dataset!$G503*L504*12 -> 147600 | N503: =IF(Payroll_Data_Analysis[[#This Row],[Annual KPI Bonus Reserve]]<=2979000,Payroll_Data_Analysis[[#This Row],[Annual KPI Bonus Reserve]]*0.302,2979000*0.302+(Payroll_Data_Analysis[[#This Row],[Annual KPI Bonus Reserve]]-2979000)*0.151) -> 44575.2 | O503: =dataset!$K503+dataset!$M503 -> 2223600 | P503: =Payroll_Data_Analysis[[#This Row],[Annual Salary + KPI Bonus]]/12/29.3*31 -> 196051.19 | Q503: =IF(Payroll_Data_Analysis[[#This Row],[Vacation Reserve]]<=2979000,Payroll_Data_Analysis[[#This Row],[Vacation Reserve]]*0.302,2979000*0.302+(Payroll_Data_Analysis[[#This Row],[Vacation Reserve]]-2979000)*0.151) -> 59207.461 | R503: =Payroll_Data_Analysis[[#This Row],[Monthly Salary]]*11 -> 1903000 | S503: =IF(Payroll_Data_Analysis[[#This Row],[11-Month Salary]]<=2979000,Payroll_Data_Analysis[[#This Row],[11-Month Salary]]*0.302,2979000*0.302+(Payroll_Data_Analysis[[#This Row],[11-Month Salary]]-2979000)*0.151) -> 574706 | T503: =IF(Payroll_Data_Analysis[[#This Row],[Base Salary (Monthly)]]>=200000,69507,IF(Payroll_Data_Analysis[[#This Row],[Base Salary (Monthly)]]>=145000,52684,35103)) -> 35103 | U503: =Payroll_Data_Analysis[[#This Row],[Annual KPI Bonus Reserve]]+Payroll_Data_Analysis[[#This Row],[Vacation Reserve]]+Payroll_Data_Analysis[[#This Row],[11-Month Salary]] -> 2246651.2 | V503: =Payroll_Data_Analysis[[#This Row],[Payroll Taxes (KPI Bonus)]]+Payroll_Data_Analysis[[#This Row],[Payroll Taxes (Vacation)]]+Payroll_Data_Analysis[[#This Row],[Payroll Taxes (Salary)]] -> 678488.66 | W503: =Payroll_Data_Analysis[[#This Row],[Total Payroll]]+Payroll_Data_Analysis[[#This Row],[Total Payroll Taxes]] -> 2925139.9
A504: Finance | B504: Emp_504 | C504: Senior Specialist | D504: =VLOOKUP(Payroll_Data_Analysis[[#This Row],[Position]],Position_Map!$A$2:$B$58,2,FALSE) -> Professional | E504: 1 | F504: 140500 | G504: 100000 | I504: =dataset!$F504-dataset!$J504-dataset!$G504-dataset!$H504 -> 32500 | J504: =dataset!$G504*0.08 -> 8000 | K504: =dataset!$F504*12 -> 1686000 | L504: =IF(dataset!$G504>=200000,38%,IF(dataset!$G504<=145000,12.3%,)) -> 0.123 | M504: =dataset!$G504*L505*12 -> 147600 | N504: =IF(Payroll_Data_Analysis[[#This Row],[Annual KPI Bonus Reserve]]<=2979000,Payroll_Data_Analysis[[#This Row],[Annual KPI Bonus Reserve]]*0.302,2979000*0.302+(Payroll_Data_Analysis[[#This Row],[Annual KPI Bonus Reserve]]-2979000)*0.151) -> 44575.2 | O504: =dataset!$K504+dataset!$M504 -> 1833600 | P504: =Payroll_Data_Analysis[[#This Row],[Annual Salary + KPI Bonus]]/12/29.3*31 -> 161665.53 | Q504: =IF(Payroll_Data_Analysis[[#This Row],[Vacation Reserve]]<=2979000,Payroll_Data_Analysis[[#This Row],[Vacation Reserve]]*0.302,2979000*0.302+(Payroll_Data_Analysis[[#This Row],[Vacation Reserve]]-2979000)*0.151) -> 48822.99 | R504: =Payroll_Data_Analysis[[#This Row],[Monthly Salary]]*11 -> 1545500 | S504: =IF(Payroll_Data_Analysis[[#This Row],[11-Month Salary]]<=2979000,Payroll_Data_Analysis[[#This Row],[11-Month Salary]]*0.302,2979000*0.302+(Payroll_Data_Analysis[[#This Row],[11-Month Salary]]-2979000)*0.151) -> 466741 | T504: =IF(Payroll_Data_Analysis[[#This Row],[Base Salary (Monthly)]]>=200000,69507,IF(Payroll_Data_Analysis[[#This Row],[Base Salary (Monthly)]]>=145000,52684,35103)) -> 35103 | U504: =Payroll_Data_Analysis[[#This Row],[Annual KPI Bonus Reserve]]+Payroll_Data_Analysis[[#This Row],[Vacation Reserve]]+Payroll_Data_Analysis[[#This Row],[11-Month Salary]] -> 1854765.5 | V504: =Payroll_Data_Analysis[[#This Row],[Payroll Taxes (KPI Bonus)]]+Payroll_Data_Analysis[[#This Row],[Payroll Taxes (Vacation)]]+Payroll_Data_Analysis[[#This Row],[Payroll Taxes (Salary)]] -> 560139.19 | W504: =Payroll_Data_Analysis[[#This Row],[Total Payroll]]+Payroll_Data_Analysis[[#This Row],[Total Payroll Taxes]] -> 2414904.7
A505: Finance | B505: Emp_505 | C505: Department Manager | D505: =VLOOKUP(Payroll_Data_Analysis[[#This Row],[Position]],Position_Map!$A$2:$B$58,2,FALSE) -> Management | E505: 1 | F505: 261600 | G505: 145000 | I505: =dataset!$F505-dataset!$J505-dataset!$G505-dataset!$H505 -> 105000 | J505: =dataset!$G505*0.08 -> 11600 | K505: =dataset!$F505*12 -> 3139200 | L505: =IF(dataset!$G505>=200000,38%,IF(dataset!$G505<=145000,12.3%,)) -> 0.123 | M505: =dataset!$G505*L506*12 -> 214020 | N505: =IF(Payroll_Data_Analysis[[#This Row],[Annual KPI Bonus Reserve]]<=2979000,Payroll_Data_Analysis[[#This Row],[Annual KPI Bonus Reserve]]*0.302,2979000*0.302+(Payroll_Data_Analysis[[#This Row],[Annual KPI Bonus Reserve]]-2979000)*0.151) -> 64634.04 | O505: =dataset!$K505+dataset!$M505 -> 3353220 | P505: =Payroll_Data_Analysis[[#This Row],[Annual Salary + KPI Bonus]]/12/29.3*31 -> 295647.95 | Q505: =IF(Payroll_Data_Analysis[[#This Row],[Vacation Reserve]]<=2979000,Payroll_Data_Analysis[[#This Row],[Vacation Reserve]]*0.302,2979000*0.302+(Payroll_Data_Analysis[[#This Row],[Vacation Reserve]]-2979000)*0.151) -> 89285.682 | R505: =Payroll_Data_Analysis[[#This Row],[Monthly Salary]]*11 -> 2877600 | S505: =IF(Payroll_Data_Analysis[[#This Row],[11-Month Salary]]<=2979000,Payroll_Data_Analysis[[#This Row],[11-Month Salary]]*0.302,2979000*0.302+(Payroll_Data_Analysis[[#This Row],[11-Month Salary]]-2979000)*0.151) -> 869035.2 | T505: =IF(Payroll_Data_Analysis[[#This Row],[Base Salary (Monthly)]]>=200000,69507,IF(Payroll_Data_Analysis[[#This Row],[Base Salary (Monthly)]]>=145000,52684,35103)) -> 52684 | U505: =Payroll_Data_Analysis[[#This Row],[Annual KPI Bonus Reserve]]+Payroll_Data_Analysis[[#This Row],[Vacation Reserve]]+Payroll_Data_Analysis[[#This Row],[11-Month Salary]] -> 3387268 | V505: =Payroll_Data_Analysis[[#This Row],[Payroll Taxes (KPI Bonus)]]+Payroll_Data_Analysis[[#This Row],[Payroll Taxes (Vacation)]]+Payroll_Data_Analysis[[#This Row],[Payroll Taxes (Salary)]] -> 1022954.9 | W505: =Payroll_Data_Analysis[[#This Row],[Total Payroll]]+Payroll_Data_Analysis[[#This Row],[Total Payroll Taxes]] -> 4410222.9
A506: Finance | B506: Emp_506 | C506: Lead Specialist | D506: =VLOOKUP(Payroll_Data_Analysis[[#This Row],[Position]],Position_Map!$A$2:$B$58,2,FALSE) -> Professional | E506: 1 | F506: 186600 | G506: 145000 | I506: =dataset!$F506-dataset!$J506-dataset!$G506-dataset!$H506 -> 30000 | J506: =dataset!$G506*0.08 -> 11600 | K506: =dataset!$F506*12 -> 2239200 | L506: =IF(dataset!$G506>=200000,38%,IF(dataset!$G506<=145000,12.3%,)) -> 0.123 | M506: =dataset!$G506*L507*12 -> 214020 | N506: =IF(Payroll_Data_Analysis[[#This Row],[Annual KPI Bonus Reserve]]<=2979000,Payroll_Data_Analysis[[#This Row],[Annual KPI Bonus Reserve]]*0.302,2979000*0.302+(Payroll_Data_Analysis[[#This Row],[Annual KPI Bonus Reserve]]-2979000)*0.151) -> 64634.04 | O506: =dataset!$K506+dataset!$M506 -> 2453220 | P506: =Payroll_Data_Analysis[[#This Row],[Annual Salary + KPI Bonus]]/12/29.3*31 -> 216296.42 | Q506: =IF(Payroll_Data_Analysis[[#This Row],[Vacation Reserve]]<=2979000,Payroll_Data_Analysis[[#This Row],[Vacation Reserve]]*0.302,2979000*0.302+(Payroll_Data_Analysis[[#This Row],[Vacation Reserve]]-2979000)*0.151) -> 65321.518 | R506: =Payroll_Data_Analysis[[#This Row],[Monthly Salary]]*11 -> 2052600 | S506: =IF(Payroll_Data_Analysis[[#This Row],[11-Month Salary]]<=2979000,Payroll_Data_Analysis[[#This Row],[11-Month Salary]]*0.302,2979000*0.302+(Payroll_Data_Analysis[[#This Row],[11-Month Salary]]-2979000)*0.151) -> 619885.2 | T506: =IF(Payroll_Data_Analysis[[#This Row],[Base Salary (Monthly)]]>=200000,69507,IF(Payroll_Data_Analysis[[#This Row],[Base Salary (Monthly)]]>=145000,52684,35103)) -> 52684 | U506: =Payroll_Data_Analysis[[#This Row],[Annual KPI Bonus Reserve]]+Payroll_Data_Analysis[[#This Row],[Vacation Reserve]]+Payroll_Data_Analysis[[#This Row],[11-Month Salary]] -> 2482916.4 | V506: =Payroll_Data_Analysis[[#This Row],[Payroll Taxes (KPI Bonus)]]+Payroll_Data_Analysis[[#This Row],[Payroll Taxes (Vacation)]]+Payroll_Data_Analysis[[#This Row],[Payroll Taxes (Salary)]] -> 749840.76 | W506: =Payroll_Data_Analysis[[#This Row],[Total Payroll]]+Payroll_Data_Analysis[[#This Row],[Total Payroll Taxes]] -> 3232757.2
A507: Finance | B507: Emp_507 | C507: Senior Specialist | D507: =VLOOKUP(Payroll_Data_Analysis[[#This Row],[Position]],Position_Map!$A$2:$B$58,2,FALSE) -> Professional | E507: 1 | F507: 104800 | G507: 60000 | I507: =dataset!$F507-dataset!$J507-dataset!$G507-dataset!$H507 -> 40000 | J507: =dataset!$G507*0.08 -> 4800 | K507: =dataset!$F507*12 -> 1257600 | L507: =IF(dataset!$G507>=200000,38%,IF(dataset!$G507<=145000,12.3%,)) -> 0.123 | M507: =dataset!$G507*L508*12 -> 88560 | N507: =IF(Payroll_Data_Analysis[[#This Row],[Annual KPI Bonus Reserve]]<=2979000,Payroll_Data_Analysis[[#This Row],[Annual KPI Bonus Reserve]]*0.302,2979000*0.302+(Payroll_Data_Analysis[[#This Row],[Annual KPI Bonus Reserve]]-2979000)*0.151) -> 26745.12 | O507: =dataset!$K507+dataset!$M507 -> 1346160 | P507: =Payroll_Data_Analysis[[#This Row],[Annual Salary + KPI Bonus]]/12/29.3*31 -> 118688.74 | Q507: =IF(Payroll_Data_Analysis[[#This Row],[Vacation Reserve]]<=2979000,Payroll_Data_Analysis[[#This Row],[Vacation Reserve]]*0.302,2979000*0.302+(Payroll_Data_Analysis[[#This Row],[Vacation Reserve]]-2979000)*0.151) -> 35843.999 | R507: =Payroll_Data_Analysis[[#This Row],[Monthly Salary]]*11 -> 1152800 | S507: =IF(Payroll_Data_Analysis[[#This Row],[11-Month Salary]]<=2979000,Payroll_Data_Analysis[[#This Row],[11-Month Salary]]*0.302,2979000*0.302+(Payroll_Data_Analysis[[#This Row],[11-Month Salary]]-2979000)*0.151) -> 348145.6 | T507: =IF(Payroll_Data_Analysis[[#This Row],[Base Salary (Monthly)]]>=200000,69507,IF(Payroll_Data_Analysis[[#This Row],[Base Salary (Monthly)]]>=145000,52684,35103)) -> 35103 | U507: =Payroll_Data_Analysis[[#This Row],[Annual KPI Bonus Reserve]]+Payroll_Data_Analysis[[#This Row],[Vacation Reserve]]+Payroll_Data_Analysis[[#This Row],[11-Month Salary]] -> 1360048.7 | V507: =Payroll_Data_Analysis[[#This Row],[Payroll Taxes (KPI Bonus)]]+Payroll_Data_Analysis[[#This Row],[Payroll Taxes (Vacation)]]+Payroll_Data_Analysis[[#This Row],[Payroll Taxes (Salary)]] -> 410734.72 | W507: =Payroll_Data_Analysis[[#This Row],[Total Payroll]]+Payroll_Data_Analysis[[#This Row],[Total Payroll Taxes]] -> 1770783.5
A508: Finance | B508: Emp_508 | C508: Lead Specialist | D508: =VLOOKUP(Payroll_Data_Analysis[[#This Row],[Position]],Position_Map!$A$2:$B$58,2,FALSE) -> Professional | E508: 1 | F508: 186600 | G508: 145000 | I508: =dataset!$F508-dataset!$J508-dataset!$G508-dataset!$H508 -> 30000 | J508: =dataset!$G508*0.08 -> 11600 | K508: =dataset!$F508*12 -> 2239200 | L508: =IF(dataset!$G508>=200000,38%,IF(dataset!$G508<=145000,12.3%,)) -> 0.123 | M508: =dataset!$G508*L509*12 -> 214020 | N508: =IF(Payroll_Data_Analysis[[#This Row],[Annual KPI Bonus Reserve]]<=2979000,Payroll_Data_Analysis[[#This Row],[Annual KPI Bonus Reserve]]*0.302,2979000*0.302+(Payroll_Data_Analysis[[#This Row],[Annual KPI Bonus Reserve]]-2979000)*0.151) -> 64634.04 | O508: =dataset!$K508+dataset!$M508 -> 2453220 | P508: =Payroll_Data_Analysis[[#This Row],[Annual Salary + KPI Bonus]]/12/29.3*31 -> 216296.42 | Q508: =IF(Payroll_Data_Analysis[[#This Row],[Vacation Reserve]]<=2979000,Payroll_Data_Analysis[[#This Row],[Vacation Reserve]]*0.302,2979000*0.302+(Payroll_Data_Analysis[[#This Row],[Vacation Reserve]]-2979000)*0.151) -> 65321.518 | R508: =Payroll_Data_Analysis[[#This Row],[Monthly Salary]]*11 -> 2052600 | S508: =IF(Payroll_Data_Analysis[[#This Row],[11-Month Salary]]<=2979000,Payroll_Data_Analysis[[#This Row],[11-Month Salary]]*0.302,2979000*0.302+(Payroll_Data_Analysis[[#This Row],[11-Month Salary]]-2979000)*0.151) -> 619885.2 | T508: =IF(Payroll_Data_Analysis[[#This Row],[Base Salary (Monthly)]]>=200000,69507,IF(Payroll_Data_Analysis[[#This Row],[Base Salary (Monthly)]]>=145000,52684,35103)) -> 52684 | U508: =Payroll_Data_Analysis[[#This Row],[Annual KPI Bonus Reserve]]+Payroll_Data_Analysis[[#This Row],[Vacation Reserve]]+Payroll_Data_Analysis[[#This Row],[11-Month Salary]] -> 2482916.4 | V508: =Payroll_Data_Analysis[[#This Row],[Payroll Taxes (KPI Bonus)]]+Payroll_Data_Analysis[[#This Row],[Payroll Taxes (Vacation)]]+Payroll_Data_Analysis[[#This Row],[Payroll Taxes (Salary)]] -> 749840.76 | W508: =Payroll_Data_Analysis[[#This Row],[Total Payroll]]+Payroll_Data_Analysis[[#This Row],[Total Payroll Taxes]] -> 3232757.2
A509: Finance | B509: Emp_509 | C509: Senior Specialist | D509: =VLOOKUP(Payroll_Data_Analysis[[#This Row],[Position]],Position_Map!$A$2:$B$58,2,FALSE) -> Professional | E509: 1 | F509: 81000 | G509: 50000 | I509: =dataset!$F509-dataset!$J509-dataset!$G509-dataset!$H509 -> 27000 | J509: =dataset!$G509*0.08 -> 4000 | K509: =dataset!$F509*12 -> 972000 | L509: =IF(dataset!$G509>=200000,38%,IF(dataset!$G509<=145000,12.3%,)) -> 0.123 | M509: =dataset!$G509*L510*12 -> 228000 | N509: =IF(Payroll_Data_Analysis[[#This Row],[Annual KPI Bonus Reserve]]<=2979000,Payroll_Data_Analysis[[#This Row],[Annual KPI Bonus Reserve]]*0.302,2979000*0.302+(Payroll_Data_Analysis[[#This Row],[Annual KPI Bonus Reserve]]-2979000)*0.151) -> 68856 | O509: =dataset!$K509+dataset!$M509 -> 1200000 | P509: =Payroll_Data_Analysis[[#This Row],[Annual Salary + KPI Bonus]]/12/29.3*31 -> 105802.05 | Q509: =IF(Payroll_Data_Analysis[[#This Row],[Vacation Reserve]]<=2979000,Payroll_Data_Analysis[[#This Row],[Vacation Reserve]]*0.302,2979000*0.302+(Payroll_Data_Analysis[[#This Row],[Vacation Reserve]]-2979000)*0.151) -> 31952.218 | R509: =Payroll_Data_Analysis[[#This Row],[Monthly Salary]]*11 -> 891000 | S509: =IF(Payroll_Data_Analysis[[#This Row],[11-Month Salary]]<=2979000,Payroll_Data_Analysis[[#This Row],[11-Month Salary]]*0.302,2979000*0.302+(Payroll_Data_Analysis[[#This Row],[11-Month Salary]]-2979000)*0.151) -> 269082 | T509: =IF(Payroll_Data_Analysis[[#This Row],[Base Salary (Monthly)]]>=200000,69507,IF(Payroll_Data_Analysis[[#This Row],[Base Salary (Monthly)]]>=145000,52684,35103)) -> 35103 | U509: =Payroll_Data_Analysis[[#This Row],[Annual KPI Bonus Reserve]]+Payroll_Data_Analysis[[#This Row],[Vacation Reserve]]+Payroll_Data_Analysis[[#This Row],[11-Month Salary]] -> 1224802 | V509: =Payroll_Data_Analysis[[#This Row],[Payroll Taxes (KPI Bonus)]]+Payroll_Data_Analysis[[#This Row],[Payroll Taxes (Vacation)]]+Payroll_Data_Analysis[[#This Row],[Payroll Taxes (Salary)]] -> 369890.22 | W509: =Payroll_Data_Analysis[[#This Row],[Total Payroll]]+Payroll_Data_Analysis[[#This Row],[Total Payroll Taxes]] -> 1594692.3
A510: Operations | B510: Emp_510 | C510: Head of Division | D510: =VLOOKUP(Payroll_Data_Analysis[[#This Row],[Position]],Position_Map!$A$2:$B$58,2,FALSE) -> Management | E510: 1 | F510: 376000 | G510: 200000 | I510: =dataset!$F510-dataset!$J510-dataset!$G510-dataset!$H510 -> 160000 | J510: =dataset!$G510*0.08 -> 16000 | K510: =dataset!$F510*12 -> 4512000 | L510: =IF(dataset!$G510>=200000,38%,IF(dataset!$G510<=145000,12.3%,)) -> 0.38 | M510: =dataset!$G510*L511*12 -> 295200 | N510: =IF(Payroll_Data_Analysis[[#This Row],[Annual KPI Bonus Reserve]]<=2979000,Payroll_Data_Analysis[[#This Row],[Annual KPI Bonus Reserve]]*0.302,2979000*0.302+(Payroll_Data_Analysis[[#This Row],[Annual KPI Bonus Reserve]]-2979000)*0.151) -> 89150.4 | O510: =dataset!$K510+dataset!$M510 -> 4807200 | P510: =Payroll_Data_Analysis[[#This Row],[Annual Salary + KPI Bonus]]/12/29.3*31 -> 423843 | Q510: =IF(Payroll_Data_Analysis[[#This Row],[Vacation Reserve]]<=2979000,Payroll_Data_Analysis[[#This Row],[Vacation Reserve]]*0.302,2979000*0.302+(Payroll_Data_Analysis[[#This Row],[Vacation Reserve]]-2979000)*0.151) -> 128000.59 | R510: =Payroll_Data_Analysis[[#This Row],[Monthly Salary]]*11 -> 4136000 | S510: =IF(Payroll_Data_Analysis[[#This Row],[11-Month Salary]]<=2979000,Payroll_Data_Analysis[[#This Row],[11-Month Salary]]*0.302,2979000*0.302+(Payroll_Data_Analysis[[#This Row],[11-Month Salary]]-2979000)*0.151) -> 1074365 | T510: =IF(Payroll_Data_Analysis[[#This Row],[Base Salary (Monthly)]]>=200000,69507,IF(Payroll_Data_Analysis[[#This Row],[Base Salary (Monthly)]]>=145000,52684,35103)) -> 69507 | U510: =Payroll_Data_Analysis[[#This Row],[Annual KPI Bonus Reserve]]+Payroll_Data_Analysis[[#This Row],[Vacation Reserve]]+Payroll_Data_Analysis[[#This Row],[11-Month Salary]] -> 4855043 | V510: =Payroll_Data_Analysis[[#This Row],[Payroll Taxes (KPI Bonus)]]+Payroll_Data_Analysis[[#This Row],[Payroll Taxes (Vacation)]]+Payroll_Data_Analysis[[#This Row],[Payroll Taxes (Salary)]] -> 1291516 | W510: =Payroll_Data_Analysis[[#This Row],[Total Payroll]]+Payroll_Data_Analysis[[#This Row],[Total Payroll Taxes]] -> 6146559
... A514: Operations | B514: Emp_514 | C514: Senior Specialist | D514: =VLOOKUP(Payroll_Data_Analysis[[#This Row],[Position]],Position_Map!$A$2:$B$58,2,FALSE) -> Professional | E514: 1 | F514: 81000 | G514: 60000 | I514: =dataset!$F514-dataset!$J514-dataset!$G514-dataset!$H514 -> 16200 | J514: =dataset!$G514*0.08 -> 4800 | K514: =dataset!$F514*12 -> 972000 | L514: =IF(dataset!$G514>=200000,38%,IF(dataset!$G514<=145000,12.3%,)) -> 0.123 | M514: =dataset!$G514*L515*12 -> 88560 | N514: =IF(Payroll_Data_Analysis[[#This Row],[Annual KPI Bonus Reserve]]<=2979000,Payroll_Data_Analysis[[#This Row],[Annual KPI Bonus Reserve]]*0.302,2979000*0.302+(Payroll_Data_Analysis[[#This Row],[Annual KPI Bonus Reserve]]-2979000)*0.151) -> 26745.12 | O514: =dataset!$K514+dataset!$M514 -> 1060560 | P514: =Payroll_Data_Analysis[[#This Row],[Annual Salary + KPI Bonus]]/12/29.3*31 -> 93507.85 | Q514: =IF(Payroll_Data_Analysis[[#This Row],[Vacation Reserve]]<=2979000,Payroll_Data_Analysis[[#This Row],[Vacation Reserve]]*0.302,2979000*0.302+(Payroll_Data_Analysis[[#This Row],[Vacation Reserve]]-2979000)*0.151) -> 28239.371 | R514: =Payroll_Data_Analysis[[#This Row],[Monthly Salary]]*11 -> 891000 | S514: =IF(Payroll_Data_Analysis[[#This Row],[11-Month Salary]]<=2979000,Payroll_Data_Analysis[[#This Row],[11-Month Salary]]*0.302,2979000*0.302+(Payroll_Data_Analysis[[#This Row],[11-Month Salary]]-2979000)*0.151) -> 269082 | T514: =IF(Payroll_Data_Analysis[[#This Row],[Base Salary (Monthly)]]>=200000,69507,IF(Payroll_Data_Analysis[[#This Row],[Base Salary (Monthly)]]>=145000,52684,35103)) -> 35103 | U514: =Payroll_Data_Analysis[[#This Row],[Annual KPI Bonus Reserve]]+Payroll_Data_Analysis[[#This Row],[Vacation Reserve]]+Payroll_Data_Analysis[[#This Row],[11-Month Salary]] -> 1073067.8 | V514: =Payroll_Data_Analysis[[#This Row],[Payroll Taxes (KPI Bonus)]]+Payroll_Data_Analysis[[#This Row],[Payroll Taxes (Vacation)]]+Payroll_Data_Analysis[[#This Row],[Payroll Taxes (Salary)]] -> 324066.49 | W514: =Payroll_Data_Analysis[[#This Row],[Total Payroll]]+Payroll_Data_Analysis[[#This Row],[Total Payroll Taxes]] -> 1397134.3
A515: Operations | B515: Emp_515 | C515: Deputy Department Manager | D515: Management | E515: 1 | F515: 178000 | G515: 100000 | I515: =dataset!$F515-dataset!$J515-dataset!$G515-dataset!$H515 -> 70000 | J515: =dataset!$G515*0.08 -> 8000 | K515: =dataset!$F515*12 -> 2136000 | L515: =IF(dataset!$G515>=200000,38%,IF(dataset!$G515<=145000,12.3%,)) -> 0.123 | M515: =dataset!$G515*L516*12 -> 147600 | N515: =IF(Payroll_Data_Analysis[[#This Row],[Annual KPI Bonus Reserve]]<=2979000,Payroll_Data_Analysis[[#This Row],[Annual KPI Bonus Reserve]]*0.302,2979000*0.302+(Payroll_Data_Analysis[[#This Row],[Annual KPI Bonus Reserve]]-2979000)*0.151) -> 44575.2 | O515: =dataset!$K515+dataset!$M515 -> 2283600 | P515: =Payroll_Data_Analysis[[#This Row],[Annual Salary + KPI Bonus]]/12/29.3*31 -> 201341.3 | Q515: =IF(Payroll_Data_Analysis[[#This Row],[Vacation Reserve]]<=2979000,Payroll_Data_Analysis[[#This Row],[Vacation Reserve]]*0.302,2979000*0.302+(Payroll_Data_Analysis[[#This Row],[Vacation Reserve]]-2979000)*0.151) -> 60805.072 | R515: =Payroll_Data_Analysis[[#This Row],[Monthly Salary]]*11 -> 1958000 | S515: =IF(Payroll_Data_Analysis[[#This Row],[11-Month Salary]]<=2979000,Payroll_Data_Analysis[[#This Row],[11-Month Salary]]*0.302,2979000*0.302+(Payroll_Data_Analysis[[#This Row],[11-Month Salary]]-2979000)*0.151) -> 591316 | T515: =IF(Payroll_Data_Analysis[[#This Row],[Base Salary (Monthly)]]>=200000,69507,IF(Payroll_Data_Analysis[[#This Row],[Base Salary (Monthly)]]>=145000,52684,35103)) -> 35103 | U515: =Payroll_Data_Analysis[[#This Row],[Annual KPI Bonus Reserve]]+Payroll_Data_Analysis[[#This Row],[Vacation Reserve]]+Payroll_Data_Analysis[[#This Row],[11-Month Salary]] -> 2306941.3 | V515: =Payroll_Data_Analysis[[#This Row],[Payroll Taxes (KPI Bonus)]]+Payroll_Data_Analysis[[#This Row],[Payroll Taxes (Vacation)]]+Payroll_Data_Analysis[[#This Row],[Payroll Taxes (Salary)]] -> 696696.27 | W515: =Payroll_Data_Analysis[[#This Row],[Total Payroll]]+Payroll_Data_Analysis[[#This Row],[Total Payroll Taxes]] -> 3003637.6
A516: Operations | B516: Emp_516 | C516: Lead Specialist | D516: =VLOOKUP(Payroll_Data_Analysis[[#This Row],[Position]],Position_Map!$A$2:$B$58,2,FALSE) -> Professional | E516: 1 | F516: 231600 | G516: 145000 | I516: =dataset!$F516-dataset!$J516-dataset!$G516-dataset!$H516 -> 75000 | J516: =dataset!$G516*0.08 -> 11600 | K516: =dataset!$F516*12 -> 2779200 | L516: =IF(dataset!$G516>=200000,38%,IF(dataset!$G516<=145000,12.3%,)) -> 0.123 | M516: =dataset!$G516*L517*12 -> 214020 | N516: =IF(Payroll_Data_Analysis[[#This Row],[Annual KPI Bonus Reserve]]<=2979000,Payroll_Data_Analysis[[#This Row],[Annual KPI Bonus Reserve]]*0.302,2979000*0.302+(Payroll_Data_Analysis[[#This Row],[Annual KPI Bonus Reserve]]-2979000)*0.151) -> 64634.04 | O516: =dataset!$K516+dataset!$M516 -> 2993220 | P516: =Payroll_Data_Analysis[[#This Row],[Annual Salary + KPI Bonus]]/12/29.3*31 -> 263907.34 | Q516: =IF(Payroll_Data_Analysis[[#This Row],[Vacation Reserve]]<=2979000,Payroll_Data_Analysis[[#This Row],[Vacation Reserve]]*0.302,2979000*0.302+(Payroll_Data_Analysis[[#This Row],[Vacation Reserve]]-2979000)*0.151) -> 79700.016 | R516: =Payroll_Data_Analysis[[#This Row],[Monthly Salary]]*11 -> 2547600 | S516: =IF(Payroll_Data_Analysis[[#This Row],[11-Month Salary]]<=2979000,Payroll_Data_Analysis[[#This Row],[11-Month Salary]]*0.302,2979000*0.302+(Payroll_Data_Analysis[[#This Row],[11-Month Salary]]-2979000)*0.151) -> 769375.2 | T516: =IF(Payroll_Data_Analysis[[#This Row],[Base Salary (Monthly)]]>=200000,69507,IF(Payroll_Data_Analysis[[#This Row],[Base Salary (Monthly)]]>=145000,52684,35103)) -> 52684 | U516: =Payroll_Data_Analysis[[#This Row],[Annual KPI Bonus Reserve]]+Payroll_Data_Analysis[[#This Row],[Vacation Reserve]]+Payroll_Data_Analysis[[#This Row],[11-Month Salary]] -> 3025527.3 | V516: =Payroll_Data_Analysis[[#This Row],[Payroll Taxes (KPI Bonus)]]+Payroll_Data_Analysis[[#This Row],[Payroll Taxes (Vacation)]]+Payroll_Data_Analysis[[#This Row],[Payroll Taxes (Salary)]] -> 913709.26 | W516: =Payroll_Data_Analysis[[#This Row],[Total Payroll]]+Payroll_Data_Analysis[[#This Row],[Total Payroll Taxes]] -> 3939236.6
A517: Operations | B517: Emp_517 | C517: Lead Specialist | D517: =VLOOKUP(Payroll_Data_Analysis[[#This Row],[Position]],Position_Map!$A$2:$B$58,2,FALSE) -> Professional | E517: 1 | F517: 186600 | G517: 145000 | I517: =dataset!$F517-dataset!$J517-dataset!$G517-dataset!$H517 -> 30000 | J517: =dataset!$G517*0.08 -> 11600 | K517: =dataset!$F517*12 -> 2239200 | L517: =IF(dataset!$G517>=200000,38%,IF(dataset!$G517<=145000,12.3%,)) -> 0.123 | M517: =dataset!$G517*L518*12 -> 214020 | N517: =IF(Payroll_Data_Analysis[[#This Row],[Annual KPI Bonus Reserve]]<=2979000,Payroll_Data_Analysis[[#This Row],[Annual KPI Bonus Reserve]]*0.302,2979000*0.302+(Payroll_Data_Analysis[[#This Row],[Annual KPI Bonus Reserve]]-2979000)*0.151) -> 64634.04 | O517: =dataset!$K517+dataset!$M517 -> 2453220 | P517: =Payroll_Data_Analysis[[#This Row],[Annual Salary + KPI Bonus]]/12/29.3*31 -> 216296.42 | Q517: =IF(Payroll_Data_Analysis[[#This Row],[Vacation Reserve]]<=2979000,Payroll_Data_Analysis[[#This Row],[Vacation Reserve]]*0.302,2979000*0.302+(Payroll_Data_Analysis[[#This Row],[Vacation Reserve]]-2979000)*0.151) -> 65321.518 | R517: =Payroll_Data_Analysis[[#This Row],[Monthly Salary]]*11 -> 2052600 | S517: =IF(Payroll_Data_Analysis[[#This Row],[11-Month Salary]]<=2979000,Payroll_Data_Analysis[[#This Row],[11-Month Salary]]*0.302,2979000*0.302+(Payroll_Data_Analysis[[#This Row],[11-Month Salary]]-2979000)*0.151) -> 619885.2 | T517: =IF(Payroll_Data_Analysis[[#This Row],[Base Salary (Monthly)]]>=200000,69507,IF(Payroll_Data_Analysis[[#This Row],[Base Salary (Monthly)]]>=145000,52684,35103)) -> 52684 | U517: =Payroll_Data_Analysis[[#This Row],[Annual KPI Bonus Reserve]]+Payroll_Data_Analysis[[#This Row],[Vacation Reserve]]+Payroll_Data_Analysis[[#This Row],[11-Month Salary]] -> 2482916.4 | V517: =Payroll_Data_Analysis[[#This Row],[Payroll Taxes (KPI Bonus)]]+Payroll_Data_Analysis[[#This Row],[Payroll Taxes (Vacation)]]+Payroll_Data_Analysis[[#This Row],[Payroll Taxes (Salary)]] -> 749840.76 | W517: =Payroll_Data_Analysis[[#This Row],[Total Payroll]]+Payroll_Data_Analysis[[#This Row],[Total Payroll Taxes]] -> 3232757.2
A518: Operations | B518: Emp_518 | C518: Senior Specialist | D518: =VLOOKUP(Payroll_Data_Analysis[[#This Row],[Position]],Position_Map!$A$2:$B$58,2,FALSE) -> Professional | E518: 1 | F518: 96800 | G518: 80000 | I518: =dataset!$F518-dataset!$J518-dataset!$G518-dataset!$H518 -> 10400 | J518: =dataset!$G518*0.08 -> 6400 | K518: =dataset!$F518*12 -> 1161600 | L518: =IF(dataset!$G518>=200000,38%,IF(dataset!$G518<=145000,12.3%,)) -> 0.123 | M518: =dataset!$G518*L519*12 -> 118080 | N518: =IF(Payroll_Data_Analysis[[#This Row],[Annual KPI Bonus Reserve]]<=2979000,Payroll_Data_Analysis[[#This Row],[Annual KPI Bonus Reserve]]*0.302,2979000*0.302+(Payroll_Data_Analysis[[#This Row],[Annual KPI Bonus Reserve]]-2979000)*0.151) -> 35660.16 | O518: =dataset!$K518+dataset!$M518 -> 1279680 | P518: =Payroll_Data_Analysis[[#This Row],[Annual Salary + KPI Bonus]]/12/29.3*31 -> 112827.3 | Q518: =IF(Payroll_Data_Analysis[[#This Row],[Vacation Reserve]]<=2979000,Payroll_Data_Analysis[[#This Row],[Vacation Reserve]]*0.302,2979000*0.302+(Payroll_Data_Analysis[[#This Row],[Vacation Reserve]]-2979000)*0.151) -> 34073.846 | R518: =Payroll_Data_Analysis[[#This Row],[Monthly Salary]]*11 -> 1064800 | S518: =IF(Payroll_Data_Analysis[[#This Row],[11-Month Salary]]<=2979000,Payroll_Data_Analysis[[#This Row],[11-Month Salary]]*0.302,2979000*0.302+(Payroll_Data_Analysis[[#This Row],[11-Month Salary]]-2979000)*0.151) -> 321569.6 | T518: =IF(Payroll_Data_Analysis[[#This Row],[Base Salary (Monthly)]]>=200000,69507,IF(Payroll_Data_Analysis[[#This Row],[Base Salary (Monthly)]]>=145000,52684,35103)) -> 35103 | U518: =Payroll_Data_Analysis[[#This Row],[Annual KPI Bonus Reserve]]+Payroll_Data_Analysis[[#This Row],[Vacation Reserve]]+Payroll_Data_Analysis[[#This Row],[11-Month Salary]] -> 1295707.3 | V518: =Payroll_Data_Analysis[[#This Row],[Payroll Taxes (KPI Bonus)]]+Payroll_Data_Analysis[[#This Row],[Payroll Taxes (Vacation)]]+Payroll_Data_Analysis[[#This Row],[Payroll Taxes (Salary)]] -> 391303.61 | W518: =Payroll_Data_Analysis[[#This Row],[Total Payroll]]+Payroll_Data_Analysis[[#This Row],[Total Payroll Taxes]] -> 1687010.9
A519: Operations | B519: Emp_519 | C519: Senior Specialist | D519: =VLOOKUP(Payroll_Data_Analysis[[#This Row],[Position]],Position_Map!$A$2:$B$58,2,FALSE) -> Professional | E519: 1 | F519: 118400 | G519: 80000 | I519: =dataset!$F519-dataset!$J519-dataset!$G519-dataset!$H519 -> 32000 | J519: =dataset!$G519*0.08 -> 6400 | K519: =dataset!$F519*12 -> 1420800 | L519: =IF(dataset!$G519>=200000,38%,IF(dataset!$G519<=145000,12.3%,)) -> 0.123 | M519: =dataset!$G519*L520*12 -> 118080 | N519: =IF(Payroll_Data_Analysis[[#This Row],[Annual KPI Bonus Reserve]]<=2979000,Payroll_Data_Analysis[[#This Row],[Annual KPI Bonus Reserve]]*0.302,2979000*0.302+(Payroll_Data_Analysis[[#This Row],[Annual KPI Bonus Reserve]]-2979000)*0.151) -> 35660.16 | O519: =dataset!$K519+dataset!$M519 -> 1538880 | P519: =Payroll_Data_Analysis[[#This Row],[Annual Salary + KPI Bonus]]/12/29.3*31 -> 135680.55 | Q519: =IF(Payroll_Data_Analysis[[#This Row],[Vacation Reserve]]<=2979000,Payroll_Data_Analysis[[#This Row],[Vacation Reserve]]*0.302,2979000*0.302+(Payroll_Data_Analysis[[#This Row],[Vacation Reserve]]-2979000)*0.151) -> 40975.525 | R519: =Payroll_Data_Analysis[[#This Row],[Monthly Salary]]*11 -> 1302400 | S519: =IF(Payroll_Data_Analysis[[#This Row],[11-Month Salary]]<=2979000,Payroll_Data_Analysis[[#This Row],[11-Month Salary]]*0.302,2979000*0.302+(Payroll_Data_Analysis[[#This Row],[11-Month Salary]]-2979000)*0.151) -> 393324.8 | T519: =IF(Payroll_Data_Analysis[[#This Row],[Base Salary (Monthly)]]>=200000,69507,IF(Payroll_Data_Analysis[[#This Row],[Base Salary (Monthly)]]>=145000,52684,35103)) -> 35103 | U519: =Payroll_Data_Analysis[[#This Row],[Annual KPI Bonus Reserve]]+Payroll_Data_Analysis[[#This Row],[Vacation Reserve]]+Payroll_Data_Analysis[[#This Row],[11-Month Salary]] -> 1556160.5 | V519: =Payroll_Data_Analysis[[#This Row],[Payroll Taxes (KPI Bonus)]]+Payroll_Data_Analysis[[#This Row],[Payroll Taxes (Vacation)]]+Payroll_Data_Analysis[[#This Row],[Payroll Taxes (Salary)]] -> 469960.48 | W519: =Payroll_Data_Analysis[[#This Row],[Total Payroll]]+Payroll_Data_Analysis[[#This Row],[Total Payroll Taxes]] -> 2026121
A520: Operations | B520: Emp_520 | C520: Senior Specialist | D520: =VLOOKUP(Payroll_Data_Analysis[[#This Row],[Position]],Position_Map!$A$2:$B$58,2,FALSE) -> Professional | E520: 1 | F520: 118400 | G520: 80000 | I520: =dataset!$F520-dataset!$J520-dataset!$G520-dataset!$H520 -> 32000 | J520: =dataset!$G520*0.08 -> 6400 | K520: =dataset!$F520*12 -> 1420800 | L520: =IF(dataset!$G520>=200000,38%,IF(dataset!$G520<=145000,12.3%,)) -> 0.123 | M520: =dataset!$G520*L521*12 -> 118080 | N520: =IF(Payroll_Data_Analysis[[#This Row],[Annual KPI Bonus Reserve]]<=2979000,Payroll_Data_Analysis[[#This Row],[Annual KPI Bonus Reserve]]*0.302,2979000*0.302+(Payroll_Data_Analysis[[#This Row],[Annual KPI Bonus Reserve]]-2979000)*0.151) -> 35660.16 | O520: =dataset!$K520+dataset!$M520 -> 1538880 | P520: =Payroll_Data_Analysis[[#This Row],[Annual Salary + KPI Bonus]]/12/29.3*31 -> 135680.55 | Q520: =IF(Payroll_Data_Analysis[[#This Row],[Vacation Reserve]]<=2979000,Payroll_Data_Analysis[[#This Row],[Vacation Reserve]]*0.302,2979000*0.302+(Payroll_Data_Analysis[[#This Row],[Vacation Reserve]]-2979000)*0.151) -> 40975.525 | R520: =Payroll_Data_Analysis[[#This Row],[Monthly Salary]]*11 -> 1302400 | S520: =IF(Payroll_Data_Analysis[[#This Row],[11-Month Salary]]<=2979000,Payroll_Data_Analysis[[#This Row],[11-Month Salary]]*0.302,2979000*0.302+(Payroll_Data_Analysis[[#This Row],[11-Month Salary]]-2979000)*0.151) -> 393324.8 | T520: =IF(Payroll_Data_Analysis[[#This Row],[Base Salary (Monthly)]]>=200000,69507,IF(Payroll_Data_Analysis[[#This Row],[Base Salary (Monthly)]]>=145000,52684,35103)) -> 35103 | U520: =Payroll_Data_Analysis[[#This Row],[Annual KPI Bonus Reserve]]+Payroll_Data_Analysis[[#This Row],[Vacation Reserve]]+Payroll_Data_Analysis[[#This Row],[11-Month Salary]] -> 1556160.5 | V520: =Payroll_Data_Analysis[[#This Row],[Payroll Taxes (KPI Bonus)]]+Payroll_Data_Analysis[[#This Row],[Payroll Taxes (Vacation)]]+Payroll_Data_Analysis[[#This Row],[Payroll Taxes (Salary)]] -> 469960.48 | W520: =Payroll_Data_Analysis[[#This Row],[Total Payroll]]+Payroll_Data_Analysis[[#This Row],[Total Payroll Taxes]] -> 2026121
A521: Operations | B521: Emp_521 | C521: Senior Specialist | D521: =VLOOKUP(Payroll_Data_Analysis[[#This Row],[Position]],Position_Map!$A$2:$B$58,2,FALSE) -> Professional | E521: 1 | F521: 76000 | G521: 60000 | I521: =dataset!$F521-dataset!$J521-dataset!$G521-dataset!$H521 -> 11200 | J521: =dataset!$G521*0.08 -> 4800 | K521: =dataset!$F521*12 -> 912000 | L521: =IF(dataset!$G521>=200000,38%,IF(dataset!$G521<=145000,12.3%,)) -> 0.123 | M521: =dataset!$G521*L522*12 -> 88560 | N521: =IF(Payroll_Data_Analysis[[#This Row],[Annual KPI Bonus Reserve]]<=2979000,Payroll_Data_Analysis[[#This Row],[Annual KPI Bonus Reserve]]*0.302,2979000*0.302+(Payroll_Data_Analysis[[#This Row],[Annual KPI Bonus Reserve]]-2979000)*0.151) -> 26745.12 | O521: =dataset!$K521+dataset!$M521 -> 1000560 | P521: =Payroll_Data_Analysis[[#This Row],[Annual Salary + KPI Bonus]]/12/29.3*31 -> 88217.747 | Q521: =IF(Payroll_Data_Analysis[[#This Row],[Vacation Reserve]]<=2979000,Payroll_Data_Analysis[[#This Row],[Vacation Reserve]]*0.302,2979000*0.302+(Payroll_Data_Analysis[[#This Row],[Vacation Reserve]]-2979000)*0.151) -> 26641.76 | R521: =Payroll_Data_Analysis[[#This Row],[Monthly Salary]]*11 -> 836000 | S521: =IF(Payroll_Data_Analysis[[#This Row],[11-Month Salary]]<=2979000,Payroll_Data_Analysis[[#This Row],[11-Month Salary]]*0.302,2979000*0.302+(Payroll_Data_Analysis[[#This Row],[11-Month Salary]]-2979000)*0.151) -> 252472 | T521: =IF(Payroll_Data_Analysis[[#This Row],[Base Salary (Monthly)]]>=200000,69507,IF(Payroll_Data_Analysis[[#This Row],[Base Salary (Monthly)]]>=145000,52684,35103)) -> 35103 | U521: =Payroll_Data_Analysis[[#This Row],[Annual KPI Bonus Reserve]]+Payroll_Data_Analysis[[#This Row],[Vacation Reserve]]+Payroll_Data_Analysis[[#This Row],[11-Month Salary]] -> 1012777.7 | V521: =Payroll_Data_Analysis[[#This Row],[Payroll Taxes (KPI Bonus)]]+Payroll_Data_Analysis[[#This Row],[Payroll Taxes (Vacation)]]+Payroll_Data_Analysis[[#This Row],[Payroll Taxes (Salary)]] -> 305858.88 | W521: =Payroll_Data_Analysis[[#This Row],[Total Payroll]]+Payroll_Data_Analysis[[#This Row],[Total Payroll Taxes]] -> 1318636.6
A522: Operations | B522: Emp_522 | C522: Senior Specialist | D522: =VLOOKUP(Payroll_Data_Analysis[[#This Row],[Position]],Position_Map!$A$2:$B$58,2,FALSE) -> Professional | E522: 1 | F522: 54100 | G522: 30000 | I522: =dataset!$F522-dataset!$J522-dataset!$G522-dataset!$H522 -> 21700 | J522: =dataset!$G522*0.08 -> 2400 | K522: =dataset!$F522*12 -> 649200 | L522: =IF(dataset!$G522>=200000,38%,IF(dataset!$G522<=145000,12.3%,)) -> 0.123 | M522: =dataset!$G522*L523*12 -> 44280 | N522: =IF(Payroll_Data_Analysis[[#This Row],[Annual KPI Bonus Reserve]]<=2979000,Payroll_Data_Analysis[[#This Row],[Annual KPI Bonus Reserve]]*0.302,2979000*0.302+(Payroll_Data_Analysis[[#This Row],[Annual KPI Bonus Reserve]]-2979000)*0.151) -> 13372.56 | O522: =dataset!$K522+dataset!$M522 -> 693480 | P522: =Payroll_Data_Analysis[[#This Row],[Annual Salary + KPI Bonus]]/12/29.3*31 -> 61143.003 | Q522: =IF(Payroll_Data_Analysis[[#This Row],[Vacation Reserve]]<=2979000,Payroll_Data_Analysis[[#This Row],[Vacation Reserve]]*0.302,2979000*0.302+(Payroll_Data_Analysis[[#This Row],[Vacation Reserve]]-2979000)*0.151) -> 18465.187 | R522: =Payroll_Data_Analysis[[#This Row],[Monthly Salary]]*11 -> 595100 | S522: =IF(Payroll_Data_Analysis[[#This Row],[11-Month Salary]]<=2979000,Payroll_Data_Analysis[[#This Row],[11-Month Salary]]*0.302,2979000*0.302+(Payroll_Data_Analysis[[#This Row],[11-Month Salary]]-2979000)*0.151) -> 179720.2 | T522: =IF(Payroll_Data_Analysis[[#This Row],[Base Salary (Monthly)]]>=200000,69507,IF(Payroll_Data_Analysis[[#This Row],[Base Salary (Monthly)]]>=145000,52684,35103)) -> 35103 | U522: =Payroll_Data_Analysis[[#This Row],[Annual KPI Bonus Reserve]]+Payroll_Data_Analysis[[#This Row],[Vacation Reserve]]+Payroll_Data_Analysis[[#This Row],[11-Month Salary]] -> 700523 | V522: =Payroll_Data_Analysis[[#This Row],[Payroll Taxes (KPI Bonus)]]+Payroll_Data_Analysis[[#This Row],[Payroll Taxes (Vacation)]]+Payroll_Data_Analysis[[#This Row],[Payroll Taxes (Salary)]] -> 211557.95 | W522: =Payroll_Data_Analysis[[#This Row],[Total Payroll]]+Payroll_Data_Analysis[[#This Row],[Total Payroll Taxes]] -> 912080.95
A523: Operations | B523: Emp_523 | C523: Specialist | D523: =VLOOKUP(Payroll_Data_Analysis[[#This Row],[Position]],Position_Map!$A$2:$B$58,2,FALSE) -> Professional | E523: 1 | F523: 52800 | G523: 30000 | I523: =dataset!$F523-dataset!$J523-dataset!$G523-dataset!$H523 -> 20400 | J523: =dataset!$G523*0.08 -> 2400 | K523: =dataset!$F523*12 -> 633600 | L523: =IF(dataset!$G523>=200000,38%,IF(dataset!$G523<=145000,12.3%,)) -> 0.123 | M523: =dataset!$G523*L524*12 -> 44280 | N523: =IF(Payroll_Data_Analysis[[#This Row],[Annual KPI Bonus Reserve]]<=2979000,Payroll_Data_Analysis[[#This Row],[Annual KPI Bonus Reserve]]*0.302,2979000*0.302+(Payroll_Data_Analysis[[#This Row],[Annual KPI Bonus Reserve]]-2979000)*0.151) -> 13372.56 | O523: =dataset!$K523+dataset!$M523 -> 677880 | P523: =Payroll_Data_Analysis[[#This Row],[Annual Salary + KPI Bonus]]/12/29.3*31 -> 59767.577 | Q523: =IF(Payroll_Data_Analysis[[#This Row],[Vacation Reserve]]<=2979000,Payroll_Data_Analysis[[#This Row],[Vacation Reserve]]*0.302,2979000*0.302+(Payroll_Data_Analysis[[#This Row],[Vacation Reserve]]-2979000)*0.151) -> 18049.808 | R523: =Payroll_Data_Analysis[[#This Row],[Monthly Salary]]*11 -> 580800 | S523: =IF(Payroll_Data_Analysis[[#This Row],[11-Month Salary]]<=2979000,Payroll_Data_Analysis[[#This Row],[11-Month Salary]]*0.302,2979000*0.302+(Payroll_Data_Analysis[[#This Row],[11-Month Salary]]-2979000)*0.151) -> 175401.6 | T523: =IF(Payroll_Data_Analysis[[#This Row],[Base Salary (Monthly)]]>=200000,69507,IF(Payroll_Data_Analysis[[#This Row],[Base Salary (Monthly)]]>=145000,52684,35103)) -> 35103 | U523: =Payroll_Data_Analysis[[#This Row],[Annual KPI Bonus Reserve]]+Payroll_Data_Analysis[[#This Row],[Vacation Reserve]]+Payroll_Data_Analysis[[#This Row],[11-Month Salary]] -> 684847.58 | V523: =Payroll_Data_Analysis[[#This Row],[Payroll Taxes (KPI Bonus)]]+Payroll_Data_Analysis[[#This Row],[Payroll Taxes (Vacation)]]+Payroll_Data_Analysis[[#This Row],[Payroll Taxes (Salary)]] -> 206823.97 | W523: =Payroll_Data_Analysis[[#This Row],[Total Payroll]]+Payroll_Data_Analysis[[#This Row],[Total Payroll Taxes]] -> 891671.54
A524: Operations | B524: Emp_524 | C524: Team Lead | D524: =VLOOKUP(Payroll_Data_Analysis[[#This Row],[Position]],Position_Map!$A$2:$B$58,2,FALSE) -> Management | E524: 1 | F524: 138000 | G524: 100000 | I524: =dataset!$F524-dataset!$J524-dataset!$G524-dataset!$H524 -> 30000 | J524: =dataset!$G524*0.08 -> 8000 | K524: =dataset!$F524*12 -> 1656000 | L524: =IF(dataset!$G524>=200000,38%,IF(dataset!$G524<=145000,12.3%,)) -> 0.123 | M524: =dataset!$G524*L525*12 -> 147600 | N524: =IF(Payroll_Data_Analysis[[#This Row],[Annual KPI Bonus Reserve]]<=2979000,Payroll_Data_Analysis[[#This Row],[Annual KPI Bonus Reserve]]*0.302,2979000*0.302+(Payroll_Data_Analysis[[#This Row],[Annual KPI Bonus Reserve]]-2979000)*0.151) -> 44575.2 | O524: =dataset!$K524+dataset!$M524 -> 1803600 | P524: =Payroll_Data_Analysis[[#This Row],[Annual Salary + KPI Bonus]]/12/29.3*31 -> 159020.48 | Q524: =IF(Payroll_Data_Analysis[[#This Row],[Vacation Reserve]]<=2979000,Payroll_Data_Analysis[[#This Row],[Vacation Reserve]]*0.302,2979000*0.302+(Payroll_Data_Analysis[[#This Row],[Vacation Reserve]]-2979000)*0.151) -> 48024.184 | R524: =Payroll_Data_Analysis[[#This Row],[Monthly Salary]]*11 -> 1518000 | S524: =IF(Payroll_Data_Analysis[[#This Row],[11-Month Salary]]<=2979000,Payroll_Data_Analysis[[#This Row],[11-Month Salary]]*0.302,2979000*0.302+(Payroll_Data_Analysis[[#This Row],[11-Month Salary]]-2979000)*0.151) -> 458436 | T524: =IF(Payroll_Data_Analysis[[#This Row],[Base Salary (Monthly)]]>=200000,69507,IF(Payroll_Data_Analysis[[#This Row],[Base Salary (Monthly)]]>=145000,52684,35103)) -> 35103 | U524: =Payroll_Data_Analysis[[#This Row],[Annual KPI Bonus Reserve]]+Payroll_Data_Analysis[[#This Row],[Vacation Reserve]]+Payroll_Data_Analysis[[#This Row],[11-Month Salary]] -> 1824620.5 | V524: =Payroll_Data_Analysis[[#This Row],[Payroll Taxes (KPI Bonus)]]+Payroll_Data_Analysis[[#This Row],[Payroll Taxes (Vacation)]]+Payroll_Data_Analysis[[#This Row],[Payroll Taxes (Salary)]] -> 551035.38 | W524: =Payroll_Data_Analysis[[#This Row],[Total Payroll]]+Payroll_Data_Analysis[[#This Row],[Total Payroll Taxes]] -> 2375655.9
A525: Operations | B525: Emp_525 | C525: Lead Specialist | D525: =VLOOKUP(Payroll_Data_Analysis[[#This Row],[Position]],Position_Map!$A$2:$B$58,2,FALSE) -> Professional | E525: 1 | F525: 108400 | G525: 80000 | I525: =dataset!$F525-dataset!$J525-dataset!$G525-dataset!$H525 -> 22000 | J525: =dataset!$G525*0.08 -> 6400 | K525: =dataset!$F525*12 -> 1300800 | L525: =IF(dataset!$G525>=200000,38%,IF(dataset!$G525<=145000,12.3%,)) -> 0.123 | M525: =dataset!$G525*L526*12 -> 118080 | N525: =IF(Payroll_Data_Analysis[[#This Row],[Annual KPI Bonus Reserve]]<=2979000,Payroll_Data_Analysis[[#This Row],[Annual KPI Bonus Reserve]]*0.302,2979000*0.302+(Payroll_Data_Analysis[[#This Row],[Annual KPI Bonus Reserve]]-2979000)*0.151) -> 35660.16 | O525: =dataset!$K525+dataset!$M525 -> 1418880 | P525: =Payroll_Data_Analysis[[#This Row],[Annual Salary + KPI Bonus]]/12/29.3*31 -> 125100.34 | Q525: =IF(Payroll_Data_Analysis[[#This Row],[Vacation Reserve]]<=2979000,Payroll_Data_Analysis[[#This Row],[Vacation Reserve]]*0.302,2979000*0.302+(Payroll_Data_Analysis[[#This Row],[Vacation Reserve]]-2979000)*0.151) -> 37780.303 | R525: =Payroll_Data_Analysis[[#This Row],[Monthly Salary]]*11 -> 1192400 | S525: =IF(Payroll_Data_Analysis[[#This Row],[11-Month Salary]]<=2979000,Payroll_Data_Analysis[[#This Row],[11-Month Salary]]*0.302,2979000*0.302+(Payroll_Data_Analysis[[#This Row],[11-Month Salary]]-2979000)*0.151) -> 360104.8 | T525: =IF(Payroll_Data_Analysis[[#This Row],[Base Salary (Monthly)]]>=200000,69507,IF(Payroll_Data_Analysis[[#This Row],[Base Salary (Monthly)]]>=145000,52684,35103)) -> 35103 | U525: =Payroll_Data_Analysis[[#This Row],[Annual KPI Bonus Reserve]]+Payroll_Data_Analysis[[#This Row],[Vacation Reserve]]+Payroll_Data_Analysis[[#This Row],[11-Month Salary]] -> 1435580.3 | V525: =Payroll_Data_Analysis[[#This Row],[Payroll Taxes (KPI Bonus)]]+Payroll_Data_Analysis[[#This Row],[Payroll Taxes (Vacation)]]+Payroll_Data_Analysis[[#This Row],[Payroll Taxes (Salary)]] -> 433545.26 | W525: =Payroll_Data_Analysis[[#This Row],[Total Payroll]]+Payroll_Data_Analysis[[#This Row],[Total Payroll Taxes]] -> 1869125.6
A526: Operations | B526: Emp_526 | C526: Senior Specialist | D526: =VLOOKUP(Payroll_Data_Analysis[[#This Row],[Position]],Position_Map!$A$2:$B$58,2,FALSE) -> Professional | E526: 1 | F526: 84800 | G526: 60000 | I526: =dataset!$F526-dataset!$J526-dataset!$G526-dataset!$H526 -> 20000 | J526: =dataset!$G526*0.08 -> 4800 | K526: =dataset!$F526*12 -> 1017600 | L526: =IF(dataset!$G526>=200000,38%,IF(dataset!$G526<=145000,12.3%,)) -> 0.123 | M526: =dataset!$G526*L527*12 -> 88560 | N526: =IF(Payroll_Data_Analysis[[#This Row],[Annual KPI Bonus Reserve]]<=2979000,Payroll_Data_Analysis[[#This Row],[Annual KPI Bonus Reserve]]*0.302,2979000*0.302+(Payroll_Data_Analysis[[#This Row],[Annual KPI Bonus Reserve]]-2979000)*0.151) -> 26745.12 | O526: =dataset!$K526+dataset!$M526 -> 1106160 | P526: =Payroll_Data_Analysis[[#This Row],[Annual Salary + KPI Bonus]]/12/29.3*31 -> 97528.328 | Q526: =IF(Payroll_Data_Analysis[[#This Row],[Vacation Reserve]]<=2979000,Payroll_Data_Analysis[[#This Row],[Vacation Reserve]]*0.302,2979000*0.302+(Payroll_Data_Analysis[[#This Row],[Vacation Reserve]]-2979000)*0.151) -> 29453.555 | R526: =Payroll_Data_Analysis[[#This Row],[Monthly Salary]]*11 -> 932800 | S526: =IF(Payroll_Data_Analysis[[#This Row],[11-Month Salary]]<=2979000,Payroll_Data_Analysis[[#This Row],[11-Month Salary]]*0.302,2979000*0.302+(Payroll_Data_Analysis[[#This Row],[11-Month Salary]]-2979000)*0.151) -> 281705.6 | T526: =IF(Payroll_Data_Analysis[[#This Row],[Base Salary (Monthly)]]>=200000,69507,IF(Payroll_Data_Analysis[[#This Row],[Base Salary (Monthly)]]>=145000,52684,35103)) -> 35103 | U526: =Payroll_Data_Analysis[[#This Row],[Annual KPI Bonus Reserve]]+Payroll_Data_Analysis[[#This Row],[Vacation Reserve]]+Payroll_Data_Analysis[[#This Row],[11-Month Salary]] -> 1118888.3 | V526: =Payroll_Data_Analysis[[#This Row],[Payroll Taxes (KPI Bonus)]]+Payroll_Data_Analysis[[#This Row],[Payroll Taxes (Vacation)]]+Payroll_Data_Analysis[[#This Row],[Payroll Taxes (Salary)]] -> 337904.27 | W526: =Payroll_Data_Analysis[[#This Row],[Total Payroll]]+Payroll_Data_Analysis[[#This Row],[Total Payroll Taxes]] -> 1456792.6
A527: Operations | B527: Emp_527 | C527: Department Manager | D527: =VLOOKUP(Payroll_Data_Analysis[[#This Row],[Position]],Position_Map!$A$2:$B$58,2,FALSE) -> Management | E527: 1 | F527: 211600 | G527: 145000 | I527: =dataset!$F527-dataset!$J527-dataset!$G527-dataset!$H527 -> 55000 | J527: =dataset!$G527*0.08 -> 11600 | K527: =dataset!$F527*12 -> 2539200 | L527: =IF(dataset!$G527>=200000,38%,IF(dataset!$G527<=145000,12.3%,)) -> 0.123 | M527: =dataset!$G527*L528*12 -> 214020 | N527: =IF(Payroll_Data_Analysis[[#This Row],[Annual KPI Bonus Reserve]]<=2979000,Payroll_Data_Analysis[[#This Row],[Annual KPI Bonus Reserve]]*0.302,2979000*0.302+(Payroll_Data_Analysis[[#This Row],[Annual KPI Bonus Reserve]]-2979000)*0.151) -> 64634.04 | O527: =dataset!$K527+dataset!$M527 -> 2753220 | P527: =Payroll_Data_Analysis[[#This Row],[Annual Salary + KPI Bonus]]/12/29.3*31 -> 242746.93 | Q527: =IF(Payroll_Data_Analysis[[#This Row],[Vacation Reserve]]<=2979000,Payroll_Data_Analysis[[#This Row],[Vacation Reserve]]*0.302,2979000*0.302+(Payroll_Data_Analysis[[#This Row],[Vacation Reserve]]-2979000)*0.151) -> 73309.572 | R527: =Payroll_Data_Analysis[[#This Row],[Monthly Salary]]*11 -> 2327600 | S527: =IF(Payroll_Data_Analysis[[#This Row],[11-Month Salary]]<=2979000,Payroll_Data_Analysis[[#This Row],[11-Month Salary]]*0.302,2979000*0.302+(Payroll_Data_Analysis[[#This Row],[11-Month Salary]]-2979000)*0.151) -> 702935.2 | T527: =IF(Payroll_Data_Analysis[[#This Row],[Base Salary (Monthly)]]>=200000,69507,IF(Payroll_Data_Analysis[[#This Row],[Base Salary (Monthly)]]>=145000,52684,35103)) -> 52684 | U527: =Payroll_Data_Analysis[[#This Row],[Annual KPI Bonus Reserve]]+Payroll_Data_Analysis[[#This Row],[Vacation Reserve]]+Payroll_Data_Analysis[[#This Row],[11-Month Salary]] -> 2784366.9 | V527: =Payroll_Data_Analysis[[#This Row],[Payroll Taxes (KPI Bonus)]]+Payroll_Data_Analysis[[#This Row],[Payroll Taxes (Vacation)]]+Payroll_Data_Analysis[[#This Row],[Payroll Taxes (Salary)]] -> 840878.81 | W527: =Payroll_Data_Analysis[[#This Row],[Total Payroll]]+Payroll_Data_Analysis[[#This Row],[Total Payroll Taxes]] -> 3625245.7
... A570: Fleet & Cleaning Operations | B570: Emp_570 | C570: Cleaning Machine Operator | D570: =VLOOKUP(Payroll_Data_Analysis[[#This Row],[Position]],Position_Map!$A$2:$B$58,2,FALSE) -> Operations | E570: 1 | F570: 90800 | G570: 60000 | I570: =dataset!$F570-dataset!$J570-dataset!$G570-dataset!$H570 -> 26000 | J570: =dataset!$G570*0.08 -> 4800 | K570: =dataset!$F570*12 -> 1089600 | L570: =IF(dataset!$G570>=200000,38%,IF(dataset!$G570<=145000,12.3%,)) -> 0.123 | M570: =dataset!$G570*L571*12 -> 88560 | N570: =IF(Payroll_Data_Analysis[[#This Row],[Annual KPI Bonus Reserve]]<=2979000,Payroll_Data_Analysis[[#This Row],[Annual KPI Bonus Reserve]]*0.302,2979000*0.302+(Payroll_Data_Analysis[[#This Row],[Annual KPI Bonus Reserve]]-2979000)*0.151) -> 26745.12 | O570: =dataset!$K570+dataset!$M570 -> 1178160 | P570: =Payroll_Data_Analysis[[#This Row],[Annual Salary + KPI Bonus]]/12/29.3*31 -> 103876.45 | Q570: =IF(Payroll_Data_Analysis[[#This Row],[Vacation Reserve]]<=2979000,Payroll_Data_Analysis[[#This Row],[Vacation Reserve]]*0.302,2979000*0.302+(Payroll_Data_Analysis[[#This Row],[Vacation Reserve]]-2979000)*0.151) -> 31370.688 | R570: =Payroll_Data_Analysis[[#This Row],[Monthly Salary]]*11 -> 998800 | S570: =IF(Payroll_Data_Analysis[[#This Row],[11-Month Salary]]<=2979000,Payroll_Data_Analysis[[#This Row],[11-Month Salary]]*0.302,2979000*0.302+(Payroll_Data_Analysis[[#This Row],[11-Month Salary]]-2979000)*0.151) -> 301637.6 | T570: =IF(Payroll_Data_Analysis[[#This Row],[Base Salary (Monthly)]]>=200000,69507,IF(Payroll_Data_Analysis[[#This Row],[Base Salary (Monthly)]]>=145000,52684,35103)) -> 35103 | U570: =Payroll_Data_Analysis[[#This Row],[Annual KPI Bonus Reserve]]+Payroll_Data_Analysis[[#This Row],[Vacation Reserve]]+Payroll_Data_Analysis[[#This Row],[11-Month Salary]] -> 1191236.5 | V570: =Payroll_Data_Analysis[[#This Row],[Payroll Taxes (KPI Bonus)]]+Payroll_Data_Analysis[[#This Row],[Payroll Taxes (Vacation)]]+Payroll_Data_Analysis[[#This Row],[Payroll Taxes (Salary)]] -> 359753.41 | W570: =Payroll_Data_Analysis[[#This Row],[Total Payroll]]+Payroll_Data_Analysis[[#This Row],[Total Payroll Taxes]] -> 1550989.9
A571: Support Services | B571: Emp_571 | C571: Department Manager | D571: =VLOOKUP(Payroll_Data_Analysis[[#This Row],[Position]],Position_Map!$A$2:$B$58,2,FALSE) -> Management | E571: 1 | F571: 276100 | G571: 145000 | H571: 14500 | I571: =dataset!$F571-dataset!$J571-dataset!$G571-dataset!$H571 -> 105000 | J571: =dataset!$G571*0.08 -> 11600 | K571: =dataset!$F571*12 -> 3313200 | L571: =IF(dataset!$G571>=200000,38%,IF(dataset!$G571<=145000,12.3%,)) -> 0.123 | M571: =dataset!$G571*L572*12 -> 214020 | N571: =IF(Payroll_Data_Analysis[[#This Row],[Annual KPI Bonus Reserve]]<=2979000,Payroll_Data_Analysis[[#This Row],[Annual KPI Bonus Reserve]]*0.302,2979000*0.302+(Payroll_Data_Analysis[[#This Row],[Annual KPI Bonus Reserve]]-2979000)*0.151) -> 64634.04 | O571: =dataset!$K571+dataset!$M571 -> 3527220 | P571: =Payroll_Data_Analysis[[#This Row],[Annual Salary + KPI Bonus]]/12/29.3*31 -> 310989.25 | Q571: =IF(Payroll_Data_Analysis[[#This Row],[Vacation Reserve]]<=2979000,Payroll_Data_Analysis[[#This Row],[Vacation Reserve]]*0.302,2979000*0.302+(Payroll_Data_Analysis[[#This Row],[Vacation Reserve]]-2979000)*0.151) -> 93918.753 | R571: =Payroll_Data_Analysis[[#This Row],[Monthly Salary]]*11 -> 3037100 | S571: =IF(Payroll_Data_Analysis[[#This Row],[11-Month Salary]]<=2979000,Payroll_Data_Analysis[[#This Row],[11-Month Salary]]*0.302,2979000*0.302+(Payroll_Data_Analysis[[#This Row],[11-Month Salary]]-2979000)*0.151) -> 908431.1 | T571: =IF(Payroll_Data_Analysis[[#This Row],[Base Salary (Monthly)]]>=200000,69507,IF(Payroll_Data_Analysis[[#This Row],[Base Salary (Monthly)]]>=145000,52684,35103)) -> 52684 | U571: =Payroll_Data_Analysis[[#This Row],[Annual KPI Bonus Reserve]]+Payroll_Data_Analysis[[#This Row],[Vacation Reserve]]+Payroll_Data_Analysis[[#This Row],[11-Month Salary]] -> 3562109.2 | V571: =Payroll_Data_Analysis[[#This Row],[Payroll Taxes (KPI Bonus)]]+Payroll_Data_Analysis[[#This Row],[Payroll Taxes (Vacation)]]+Payroll_Data_Analysis[[#This Row],[Payroll Taxes (Salary)]] -> 1066983.9 | W571: =Payroll_Data_Analysis[[#This Row],[Total Payroll]]+Payroll_Data_Analysis[[#This Row],[Total Payroll Taxes]] -> 4629093.1
A572: Support Services | B572: Emp_572 | C572: Deputy Department Manager | D572: =VLOOKUP(Payroll_Data_Analysis[[#This Row],[Position]],Position_Map!$A$2:$B$58,2,FALSE) -> Management | E572: 1 | F572: 236600 | G572: 145000 | I572: =dataset!$F572-dataset!$J572-dataset!$G572-dataset!$H572 -> 80000 | J572: =dataset!$G572*0.08 -> 11600 | K572: =dataset!$F572*12 -> 2839200 | L572: =IF(dataset!$G572>=200000,38%,IF(dataset!$G572<=145000,12.3%,)) -> 0.123 | M572: =dataset!$G572*L573*12 -> 214020 | N572: =IF(Payroll_Data_Analysis[[#This Row],[Annual KPI Bonus Reserve]]<=2979000,Payroll_Data_Analysis[[#This Row],[Annual KPI Bonus Reserve]]*0.302,2979000*0.302+(Payroll_Data_Analysis[[#This Row],[Annual KPI Bonus Reserve]]-2979000)*0.151) -> 64634.04 | O572: =dataset!$K572+dataset!$M572 -> 3053220 | P572: =Payroll_Data_Analysis[[#This Row],[Annual Salary + KPI Bonus]]/12/29.3*31 -> 269197.44 | Q572: =IF(Payroll_Data_Analysis[[#This Row],[Vacation Reserve]]<=2979000,Payroll_Data_Analysis[[#This Row],[Vacation Reserve]]*0.302,2979000*0.302+(Payroll_Data_Analysis[[#This Row],[Vacation Reserve]]-2979000)*0.151) -> 81297.627 | R572: =Payroll_Data_Analysis[[#This Row],[Monthly Salary]]*11 -> 2602600 | S572: =IF(Payroll_Data_Analysis[[#This Row],[11-Month Salary]]<=2979000,Payroll_Data_Analysis[[#This Row],[11-Month Salary]]*0.302,2979000*0.302+(Payroll_Data_Analysis[[#This Row],[11-Month Salary]]-2979000)*0.151) -> 785985.2 | T572: =IF(Payroll_Data_Analysis[[#This Row],[Base Salary (Monthly)]]>=200000,69507,IF(Payroll_Data_Analysis[[#This Row],[Base Salary (Monthly)]]>=145000,52684,35103)) -> 52684 | U572: =Payroll_Data_Analysis[[#This Row],[Annual KPI Bonus Reserve]]+Payroll_Data_Analysis[[#This Row],[Vacation Reserve]]+Payroll_Data_Analysis[[#This Row],[11-Month Salary]] -> 3085817.4 | V572: =Payroll_Data_Analysis[[#This Row],[Payroll Taxes (KPI Bonus)]]+Payroll_Data_Analysis[[#This Row],[Payroll Taxes (Vacation)]]+Payroll_Data_Analysis[[#This Row],[Payroll Taxes (Salary)]] -> 931916.87 | W572: =Payroll_Data_Analysis[[#This Row],[Total Payroll]]+Payroll_Data_Analysis[[#This Row],[Total Payroll Taxes]] -> 4017734.3
A573: Support Services | B573: Emp_573 | C573: Lead Specialist | D573: =VLOOKUP(Payroll_Data_Analysis[[#This Row],[Position]],Position_Map!$A$2:$B$58,2,FALSE) -> Professional | E573: 1 | F573: 118400 | G573: 80000 | I573: =dataset!$F573-dataset!$J573-dataset!$G573-dataset!$H573 -> 32000 | J573: =dataset!$G573*0.08 -> 6400 | K573: =dataset!$F573*12 -> 1420800 | L573: =IF(dataset!$G573>=200000,38%,IF(dataset!$G573<=145000,12.3%,)) -> 0.123 | M573: =dataset!$G573*L574*12 -> 118080 | N573: =IF(Payroll_Data_Analysis[[#This Row],[Annual KPI Bonus Reserve]]<=2979000,Payroll_Data_Analysis[[#This Row],[Annual KPI Bonus Reserve]]*0.302,2979000*0.302+(Payroll_Data_Analysis[[#This Row],[Annual KPI Bonus Reserve]]-2979000)*0.151) -> 35660.16 | O573: =dataset!$K573+dataset!$M573 -> 1538880 | P573: =Payroll_Data_Analysis[[#This Row],[Annual Salary + KPI Bonus]]/12/29.3*31 -> 135680.55 | Q573: =IF(Payroll_Data_Analysis[[#This Row],[Vacation Reserve]]<=2979000,Payroll_Data_Analysis[[#This Row],[Vacation Reserve]]*0.302,2979000*0.302+(Payroll_Data_Analysis[[#This Row],[Vacation Reserve]]-2979000)*0.151) -> 40975.525 | R573: =Payroll_Data_Analysis[[#This Row],[Monthly Salary]]*11 -> 1302400 | S573: =IF(Payroll_Data_Analysis[[#This Row],[11-Month Salary]]<=2979000,Payroll_Data_Analysis[[#This Row],[11-Month Salary]]*0.302,2979000*0.302+(Payroll_Data_Analysis[[#This Row],[11-Month Salary]]-2979000)*0.151) -> 393324.8 | T573: =IF(Payroll_Data_Analysis[[#This Row],[Base Salary (Monthly)]]>=200000,69507,IF(Payroll_Data_Analysis[[#This Row],[Base Salary (Monthly)]]>=145000,52684,35103)) -> 35103 | U573: =Payroll_Data_Analysis[[#This Row],[Annual KPI Bonus Reserve]]+Payroll_Data_Analysis[[#This Row],[Vacation Reserve]]+Payroll_Data_Analysis[[#This Row],[11-Month Salary]] -> 1556160.5 | V573: =Payroll_Data_Analysis[[#This Row],[Payroll Taxes (KPI Bonus)]]+Payroll_Data_Analysis[[#This Row],[Payroll Taxes (Vacation)]]+Payroll_Data_Analysis[[#This Row],[Payroll Taxes (Salary)]] -> 469960.48 | W573: =Payroll_Data_Analysis[[#This Row],[Total Payroll]]+Payroll_Data_Analysis[[#This Row],[Total Payroll Taxes]] -> 2026121
A574: Support Services | B574: Emp_574 | C574: Senior Engineer | D574: =VLOOKUP(Payroll_Data_Analysis[[#This Row],[Position]],Position_Map!$A$2:$B$58,2,FALSE) -> Engineering | E574: 1 | F574: 56000 | G574: 35000 | I574: =dataset!$F574-dataset!$J574-dataset!$G574-dataset!$H574 -> 18200 | J574: =dataset!$G574*0.08 -> 2800 | K574: =dataset!$F574*12 -> 672000 | L574: =IF(dataset!$G574>=200000,38%,IF(dataset!$G574<=145000,12.3%,)) -> 0.123 | M574: =dataset!$G574*L575*12 -> 51660 | N574: =IF(Payroll_Data_Analysis[[#This Row],[Annual KPI Bonus Reserve]]<=2979000,Payroll_Data_Analysis[[#This Row],[Annual KPI Bonus Reserve]]*0.302,2979000*0.302+(Payroll_Data_Analysis[[#This Row],[Annual KPI Bonus Reserve]]-2979000)*0.151) -> 15601.32 | O574: =dataset!$K574+dataset!$M574 -> 723660 | P574: =Payroll_Data_Analysis[[#This Row],[Annual Salary + KPI Bonus]]/12/29.3*31 -> 63803.925 | Q574: =IF(Payroll_Data_Analysis[[#This Row],[Vacation Reserve]]<=2979000,Payroll_Data_Analysis[[#This Row],[Vacation Reserve]]*0.302,2979000*0.302+(Payroll_Data_Analysis[[#This Row],[Vacation Reserve]]-2979000)*0.151) -> 19268.785 | R574: =Payroll_Data_Analysis[[#This Row],[Monthly Salary]]*11 -> 616000 | S574: =IF(Payroll_Data_Analysis[[#This Row],[11-Month Salary]]<=2979000,Payroll_Data_Analysis[[#This Row],[11-Month Salary]]*0.302,2979000*0.302+(Payroll_Data_Analysis[[#This Row],[11-Month Salary]]-2979000)*0.151) -> 186032 | T574: =IF(Payroll_Data_Analysis[[#This Row],[Base Salary (Monthly)]]>=200000,69507,IF(Payroll_Data_Analysis[[#This Row],[Base Salary (Monthly)]]>=145000,52684,35103)) -> 35103 | U574: =Payroll_Data_Analysis[[#This Row],[Annual KPI Bonus Reserve]]+Payroll_Data_Analysis[[#This Row],[Vacation Reserve]]+Payroll_Data_Analysis[[#This Row],[11-Month Salary]] -> 731463.92 | V574: =Payroll_Data_Analysis[[#This Row],[Payroll Taxes (KPI Bonus)]]+Payroll_Data_Analysis[[#This Row],[Payroll Taxes (Vacation)]]+Payroll_Data_Analysis[[#This Row],[Payroll Taxes (Salary)]] -> 220902.11 | W574: =Payroll_Data_Analysis[[#This Row],[Total Payroll]]+Payroll_Data_Analysis[[#This Row],[Total Payroll Taxes]] -> 952366.03
A575: Support Services | B575: Emp_575 | C575: Senior Engineer | D575: =VLOOKUP(Payroll_Data_Analysis[[#This Row],[Position]],Position_Map!$A$2:$B$58,2,FALSE) -> Engineering | E575: 1 | F575: 103400 | G575: 80000 | I575: =dataset!$F575-dataset!$J575-dataset!$G575-dataset!$H575 -> 17000 | J575: =dataset!$G575*0.08 -> 6400 | K575: =dataset!$F575*12 -> 1240800 | L575: =IF(dataset!$G575>=200000,38%,IF(dataset!$G575<=145000,12.3%,)) -> 0.123 | M575: =dataset!$G575*L576*12 -> 118080 | N575: =IF(Payroll_Data_Analysis[[#This Row],[Annual KPI Bonus Reserve]]<=2979000,Payroll_Data_Analysis[[#This Row],[Annual KPI Bonus Reserve]]*0.302,2979000*0.302+(Payroll_Data_Analysis[[#This Row],[Annual KPI Bonus Reserve]]-2979000)*0.151) -> 35660.16 | O575: =dataset!$K575+dataset!$M575 -> 1358880 | P575: =Payroll_Data_Analysis[[#This Row],[Annual Salary + KPI Bonus]]/12/29.3*31 -> 119810.24 | Q575: =IF(Payroll_Data_Analysis[[#This Row],[Vacation Reserve]]<=2979000,Payroll_Data_Analysis[[#This Row],[Vacation Reserve]]*0.302,2979000*0.302+(Payroll_Data_Analysis[[#This Row],[Vacation Reserve]]-2979000)*0.151) -> 36182.692 | R575: =Payroll_Data_Analysis[[#This Row],[Monthly Salary]]*11 -> 1137400 | S575: =IF(Payroll_Data_Analysis[[#This Row],[11-Month Salary]]<=2979000,Payroll_Data_Analysis[[#This Row],[11-Month Salary]]*0.302,2979000*0.302+(Payroll_Data_Analysis[[#This Row],[11-Month Salary]]-2979000)*0.151) -> 343494.8 | T575: =IF(Payroll_Data_Analysis[[#This Row],[Base Salary (Monthly)]]>=200000,69507,IF(Payroll_Data_Analysis[[#This Row],[Base Salary (Monthly)]]>=145000,52684,35103)) -> 35103 | U575: =Payroll_Data_Analysis[[#This Row],[Annual KPI Bonus Reserve]]+Payroll_Data_Analysis[[#This Row],[Vacation Reserve]]+Payroll_Data_Analysis[[#This Row],[11-Month Salary]] -> 1375290.2 | V575: =Payroll_Data_Analysis[[#This Row],[Payroll Taxes (KPI Bonus)]]+Payroll_Data_Analysis[[#This Row],[Payroll Taxes (Vacation)]]+Payroll_Data_Analysis[[#This Row],[Payroll Taxes (Salary)]] -> 415337.65 | W575: =Payroll_Data_Analysis[[#This Row],[Total Payroll]]+Payroll_Data_Analysis[[#This Row],[Total Payroll Taxes]] -> 1790627.9
A576: Support Services | B576: Emp_576 | C576: Senior Engineer | D576: =VLOOKUP(Payroll_Data_Analysis[[#This Row],[Position]],Position_Map!$A$2:$B$58,2,FALSE) -> Engineering | E576: 1 | F576: 103400 | G576: 80000 | I576: =dataset!$F576-dataset!$J576-dataset!$G576-dataset!$H576 -> 17000 | J576: =dataset!$G576*0.08 -> 6400 | K576: =dataset!$F576*12 -> 1240800 | L576: =IF(dataset!$G576>=200000,38%,IF(dataset!$G576<=145000,12.3%,)) -> 0.123 | M576: =dataset!$G576*L577*12 -> 118080 | N576: =IF(Payroll_Data_Analysis[[#This Row],[Annual KPI Bonus Reserve]]<=2979000,Payroll_Data_Analysis[[#This Row],[Annual KPI Bonus Reserve]]*0.302,2979000*0.302+(Payroll_Data_Analysis[[#This Row],[Annual KPI Bonus Reserve]]-2979000)*0.151) -> 35660.16 | O576: =dataset!$K576+dataset!$M576 -> 1358880 | P576: =Payroll_Data_Analysis[[#This Row],[Annual Salary + KPI Bonus]]/12/29.3*31 -> 119810.24 | Q576: =IF(Payroll_Data_Analysis[[#This Row],[Vacation Reserve]]<=2979000,Payroll_Data_Analysis[[#This Row],[Vacation Reserve]]*0.302,2979000*0.302+(Payroll_Data_Analysis[[#This Row],[Vacation Reserve]]-2979000)*0.151) -> 36182.692 | R576: =Payroll_Data_Analysis[[#This Row],[Monthly Salary]]*11 -> 1137400 | S576: =IF(Payroll_Data_Analysis[[#This Row],[11-Month Salary]]<=2979000,Payroll_Data_Analysis[[#This Row],[11-Month Salary]]*0.302,2979000*0.302+(Payroll_Data_Analysis[[#This Row],[11-Month Salary]]-2979000)*0.151) -> 343494.8 | T576: =IF(Payroll_Data_Analysis[[#This Row],[Base Salary (Monthly)]]>=200000,69507,IF(Payroll_Data_Analysis[[#This Row],[Base Salary (Monthly)]]>=145000,52684,35103)) -> 35103 | U576: =Payroll_Data_Analysis[[#This Row],[Annual KPI Bonus Reserve]]+Payroll_Data_Analysis[[#This Row],[Vacation Reserve]]+Payroll_Data_Analysis[[#This Row],[11-Month Salary]] -> 1375290.2 | V576: =Payroll_Data_Analysis[[#This Row],[Payroll Taxes (KPI Bonus)]]+Payroll_Data_Analysis[[#This Row],[Payroll Taxes (Vacation)]]+Payroll_Data_Analysis[[#This Row],[Payroll Taxes (Salary)]] -> 415337.65 | W576: =Payroll_Data_Analysis[[#This Row],[Total Payroll]]+Payroll_Data_Analysis[[#This Row],[Total Payroll Taxes]] -> 1790627.9
A577: Support Services | B577: Emp_577 | C577: Senior Engineer | D577: =VLOOKUP(Payroll_Data_Analysis[[#This Row],[Position]],Position_Map!$A$2:$B$58,2,FALSE) -> Engineering | E577: 1 | F577: 103400 | G577: 80000 | I577: =dataset!$F577-dataset!$J577-dataset!$G577-dataset!$H577 -> 17000 | J577: =dataset!$G577*0.08 -> 6400 | K577: =dataset!$F577*12 -> 1240800 | L577: =IF(dataset!$G577>=200000,38%,IF(dataset!$G577<=145000,12.3%,)) -> 0.123 | M577: =dataset!$G577*L578*12 -> 118080 | N577: =IF(Payroll_Data_Analysis[[#This Row],[Annual KPI Bonus Reserve]]<=2979000,Payroll_Data_Analysis[[#This Row],[Annual KPI Bonus Reserve]]*0.302,2979000*0.302+(Payroll_Data_Analysis[[#This Row],[Annual KPI Bonus Reserve]]-2979000)*0.151) -> 35660.16 | O577: =dataset!$K577+dataset!$M577 -> 1358880 | P577: =Payroll_Data_Analysis[[#This Row],[Annual Salary + KPI Bonus]]/12/29.3*31 -> 119810.24 | Q577: =IF(Payroll_Data_Analysis[[#This Row],[Vacation Reserve]]<=2979000,Payroll_Data_Analysis[[#This Row],[Vacation Reserve]]*0.302,2979000*0.302+(Payroll_Data_Analysis[[#This Row],[Vacation Reserve]]-2979000)*0.151) -> 36182.692 | R577: =Payroll_Data_Analysis[[#This Row],[Monthly Salary]]*11 -> 1137400 | S577: =IF(Payroll_Data_Analysis[[#This Row],[11-Month Salary]]<=2979000,Payroll_Data_Analysis[[#This Row],[11-Month Salary]]*0.302,2979000*0.302+(Payroll_Data_Analysis[[#This Row],[11-Month Salary]]-2979000)*0.151) -> 343494.8 | T577: =IF(Payroll_Data_Analysis[[#This Row],[Base Salary (Monthly)]]>=200000,69507,IF(Payroll_Data_Analysis[[#This Row],[Base Salary (Monthly)]]>=145000,52684,35103)) -> 35103 | U577: =Payroll_Data_Analysis[[#This Row],[Annual KPI Bonus Reserve]]+Payroll_Data_Analysis[[#This Row],[Vacation Reserve]]+Payroll_Data_Analysis[[#This Row],[11-Month Salary]] -> 1375290.2 | V577: =Payroll_Data_Analysis[[#This Row],[Payroll Taxes (KPI Bonus)]]+Payroll_Data_Analysis[[#This Row],[Payroll Taxes (Vacation)]]+Payroll_Data_Analysis[[#This Row],[Payroll Taxes (Salary)]] -> 415337.65 | W577: =Payroll_Data_Analysis[[#This Row],[Total Payroll]]+Payroll_Data_Analysis[[#This Row],[Total Payroll Taxes]] -> 1790627.9
A578: Support Services | B578: Emp_578 | C578: Senior Engineer | D578: =VLOOKUP(Payroll_Data_Analysis[[#This Row],[Position]],Position_Map!$A$2:$B$58,2,FALSE) -> Engineering | E578: 1 | F578: 103400 | G578: 80000 | I578: =dataset!$F578-dataset!$J578-dataset!$G578-dataset!$H578 -> 17000 | J578: =dataset!$G578*0.08 -> 6400 | K578: =dataset!$F578*12 -> 1240800 | L578: =IF(dataset!$G578>=200000,38%,IF(dataset!$G578<=145000,12.3%,)) -> 0.123 | M578: =dataset!$G578*L579*12 -> 118080 | N578: =IF(Payroll_Data_Analysis[[#This Row],[Annual KPI Bonus Reserve]]<=2979000,Payroll_Data_Analysis[[#This Row],[Annual KPI Bonus Reserve]]*0.302,2979000*0.302+(Payroll_Data_Analysis[[#This Row],[Annual KPI Bonus Reserve]]-2979000)*0.151) -> 35660.16 | O578: =dataset!$K578+dataset!$M578 -> 1358880 | P578: =Payroll_Data_Analysis[[#This Row],[Annual Salary + KPI Bonus]]/12/29.3*31 -> 119810.24 | Q578: =IF(Payroll_Data_Analysis[[#This Row],[Vacation Reserve]]<=2979000,Payroll_Data_Analysis[[#This Row],[Vacation Reserve]]*0.302,2979000*0.302+(Payroll_Data_Analysis[[#This Row],[Vacation Reserve]]-2979000)*0.151) -> 36182.692 | R578: =Payroll_Data_Analysis[[#This Row],[Monthly Salary]]*11 -> 1137400 | S578: =IF(Payroll_Data_Analysis[[#This Row],[11-Month Salary]]<=2979000,Payroll_Data_Analysis[[#This Row],[11-Month Salary]]*0.302,2979000*0.302+(Payroll_Data_Analysis[[#This Row],[11-Month Salary]]-2979000)*0.151) -> 343494.8 | T578: =IF(Payroll_Data_Analysis[[#This Row],[Base Salary (Monthly)]]>=200000,69507,IF(Payroll_Data_Analysis[[#This Row],[Base Salary (Monthly)]]>=145000,52684,35103)) -> 35103 | U578: =Payroll_Data_Analysis[[#This Row],[Annual KPI Bonus Reserve]]+Payroll_Data_Analysis[[#This Row],[Vacation Reserve]]+Payroll_Data_Analysis[[#This Row],[11-Month Salary]] -> 1375290.2 | V578: =Payroll_Data_Analysis[[#This Row],[Payroll Taxes (KPI Bonus)]]+Payroll_Data_Analysis[[#This Row],[Payroll Taxes (Vacation)]]+Payroll_Data_Analysis[[#This Row],[Payroll Taxes (Salary)]] -> 415337.65 | W578: =Payroll_Data_Analysis[[#This Row],[Total Payroll]]+Payroll_Data_Analysis[[#This Row],[Total Payroll Taxes]] -> 1790627.9
A579: Support Services | B579: Emp_579 | C579: Senior Engineer | D579: =VLOOKUP(Payroll_Data_Analysis[[#This Row],[Position]],Position_Map!$A$2:$B$58,2,FALSE) -> Engineering | E579: 1 | F579: 103400 | G579: 80000 | I579: =dataset!$F579-dataset!$J579-dataset!$G579-dataset!$H579 -> 17000 | J579: =dataset!$G579*0.08 -> 6400 | K579: =dataset!$F579*12 -> 1240800 | L579: =IF(dataset!$G579>=200000,38%,IF(dataset!$G579<=145000,12.3%,)) -> 0.123 | M579: =dataset!$G579*L580*12 -> 118080 | N579: =IF(Payroll_Data_Analysis[[#This Row],[Annual KPI Bonus Reserve]]<=2979000,Payroll_Data_Analysis[[#This Row],[Annual KPI Bonus Reserve]]*0.302,2979000*0.302+(Payroll_Data_Analysis[[#This Row],[Annual KPI Bonus Reserve]]-2979000)*0.151) -> 35660.16 | O579: =dataset!$K579+dataset!$M579 -> 1358880 | P579: =Payroll_Data_Analysis[[#This Row],[Annual Salary + KPI Bonus]]/12/29.3*31 -> 119810.24 | Q579: =IF(Payroll_Data_Analysis[[#This Row],[Vacation Reserve]]<=2979000,Payroll_Data_Analysis[[#This Row],[Vacation Reserve]]*0.302,2979000*0.302+(Payroll_Data_Analysis[[#This Row],[Vacation Reserve]]-2979000)*0.151) -> 36182.692 | R579: =Payroll_Data_Analysis[[#This Row],[Monthly Salary]]*11 -> 1137400 | S579: =IF(Payroll_Data_Analysis[[#This Row],[11-Month Salary]]<=2979000,Payroll_Data_Analysis[[#This Row],[11-Month Salary]]*0.302,2979000*0.302+(Payroll_Data_Analysis[[#This Row],[11-Month Salary]]-2979000)*0.151) -> 343494.8 | T579: =IF(Payroll_Data_Analysis[[#This Row],[Base Salary (Monthly)]]>=200000,69507,IF(Payroll_Data_Analysis[[#This Row],[Base Salary (Monthly)]]>=145000,52684,35103)) -> 35103 | U579: =Payroll_Data_Analysis[[#This Row],[Annual KPI Bonus Reserve]]+Payroll_Data_Analysis[[#This Row],[Vacation Reserve]]+Payroll_Data_Analysis[[#This Row],[11-Month Salary]] -> 1375290.2 | V579: =Payroll_Data_Analysis[[#This Row],[Payroll Taxes (KPI Bonus)]]+Payroll_Data_Analysis[[#This Row],[Payroll Taxes (Vacation)]]+Payroll_Data_Analysis[[#This Row],[Payroll Taxes (Salary)]] -> 415337.65 | W579: =Payroll_Data_Analysis[[#This Row],[Total Payroll]]+Payroll_Data_Analysis[[#This Row],[Total Payroll Taxes]] -> 1790627.9
A580: Support Services | B580: Emp_580 | C580: Senior Engineer | D580: =VLOOKUP(Payroll_Data_Analysis[[#This Row],[Position]],Position_Map!$A$2:$B$58,2,FALSE) -> Engineering | E580: 1 | F580: 103400 | G580: 80000 | I580: =dataset!$F580-dataset!$J580-dataset!$G580-dataset!$H580 -> 17000 | J580: =dataset!$G580*0.08 -> 6400 | K580: =dataset!$F580*12 -> 1240800 | L580: =IF(dataset!$G580>=200000,38%,IF(dataset!$G580<=145000,12.3%,)) -> 0.123 | M580: =dataset!$G580*L581*12 -> 118080 | N580: =IF(Payroll_Data_Analysis[[#This Row],[Annual KPI Bonus Reserve]]<=2979000,Payroll_Data_Analysis[[#This Row],[Annual KPI Bonus Reserve]]*0.302,2979000*0.302+(Payroll_Data_Analysis[[#This Row],[Annual KPI Bonus Reserve]]-2979000)*0.151) -> 35660.16 | O580: =dataset!$K580+dataset!$M580 -> 1358880 | P580: =Payroll_Data_Analysis[[#This Row],[Annual Salary + KPI Bonus]]/12/29.3*31 -> 119810.24 | Q580: =IF(Payroll_Data_Analysis[[#This Row],[Vacation Reserve]]<=2979000,Payroll_Data_Analysis[[#This Row],[Vacation Reserve]]*0.302,2979000*0.302+(Payroll_Data_Analysis[[#This Row],[Vacation Reserve]]-2979000)*0.151) -> 36182.692 | R580: =Payroll_Data_Analysis[[#This Row],[Monthly Salary]]*11 -> 1137400 | S580: =IF(Payroll_Data_Analysis[[#This Row],[11-Month Salary]]<=2979000,Payroll_Data_Analysis[[#This Row],[11-Month Salary]]*0.302,2979000*0.302+(Payroll_Data_Analysis[[#This Row],[11-Month Salary]]-2979000)*0.151) -> 343494.8 | T580: =IF(Payroll_Data_Analysis[[#This Row],[Base Salary (Monthly)]]>=200000,69507,IF(Payroll_Data_Analysis[[#This Row],[Base Salary (Monthly)]]>=145000,52684,35103)) -> 35103 | U580: =Payroll_Data_Analysis[[#This Row],[Annual KPI Bonus Reserve]]+Payroll_Data_Analysis[[#This Row],[Vacation Reserve]]+Payroll_Data_Analysis[[#This Row],[11-Month Salary]] -> 1375290.2 | V580: =Payroll_Data_Analysis[[#This Row],[Payroll Taxes (KPI Bonus)]]+Payroll_Data_Analysis[[#This Row],[Payroll Taxes (Vacation)]]+Payroll_Data_Analysis[[#This Row],[Payroll Taxes (Salary)]] -> 415337.65 | W580: =Payroll_Data_Analysis[[#This Row],[Total Payroll]]+Payroll_Data_Analysis[[#This Row],[Total Payroll Taxes]] -> 1790627.9
A581: Support Services | B581: Emp_581 | C581: Senior Engineer | D581: =VLOOKUP(Payroll_Data_Analysis[[#This Row],[Position]],Position_Map!$A$2:$B$58,2,FALSE) -> Engineering | E581: 1 | F581: 103400 | G581: 80000 | I581: =dataset!$F581-dataset!$J581-dataset!$G581-dataset!$H581 -> 17000 | J581: =dataset!$G581*0.08 -> 6400 | K581: =dataset!$F581*12 -> 1240800 | L581: =IF(dataset!$G581>=200000,38%,IF(dataset!$G581<=145000,12.3%,)) -> 0.123 | M581: =dataset!$G581*L582*12 -> 118080 | N581: =IF(Payroll_Data_Analysis[[#This Row],[Annual KPI Bonus Reserve]]<=2979000,Payroll_Data_Analysis[[#This Row],[Annual KPI Bonus Reserve]]*0.302,2979000*0.302+(Payroll_Data_Analysis[[#This Row],[Annual KPI Bonus Reserve]]-2979000)*0.151) -> 35660.16 | O581: =dataset!$K581+dataset!$M581 -> 1358880 | P581: =Payroll_Data_Analysis[[#This Row],[Annual Salary + KPI Bonus]]/12/29.3*31 -> 119810.24 | Q581: =IF(Payroll_Data_Analysis[[#This Row],[Vacation Reserve]]<=2979000,Payroll_Data_Analysis[[#This Row],[Vacation Reserve]]*0.302,2979000*0.302+(Payroll_Data_Analysis[[#This Row],[Vacation Reserve]]-2979000)*0.151) -> 36182.692 | R581: =Payroll_Data_Analysis[[#This Row],[Monthly Salary]]*11 -> 1137400 | S581: =IF(Payroll_Data_Analysis[[#This Row],[11-Month Salary]]<=2979000,Payroll_Data_Analysis[[#This Row],[11-Month Salary]]*0.302,2979000*0.302+(Payroll_Data_Analysis[[#This Row],[11-Month Salary]]-2979000)*0.151) -> 343494.8 | T581: =IF(Payroll_Data_Analysis[[#This Row],[Base Salary (Monthly)]]>=200000,69507,IF(Payroll_Data_Analysis[[#This Row],[Base Salary (Monthly)]]>=145000,52684,35103)) -> 35103 | U581: =Payroll_Data_Analysis[[#This Row],[Annual KPI Bonus Reserve]]+Payroll_Data_Analysis[[#This Row],[Vacation Reserve]]+Payroll_Data_Analysis[[#This Row],[11-Month Salary]] -> 1375290.2 | V581: =Payroll_Data_Analysis[[#This Row],[Payroll Taxes (KPI Bonus)]]+Payroll_Data_Analysis[[#This Row],[Payroll Taxes (Vacation)]]+Payroll_Data_Analysis[[#This Row],[Payroll Taxes (Salary)]] -> 415337.65 | W581: =Payroll_Data_Analysis[[#This Row],[Total Payroll]]+Payroll_Data_Analysis[[#This Row],[Total Payroll Taxes]] -> 1790627.9
A582: Support Services | B582: Emp_582 | C582: Senior Engineer | D582: =VLOOKUP(Payroll_Data_Analysis[[#This Row],[Position]],Position_Map!$A$2:$B$58,2,FALSE) -> Engineering | E582: 1 | F582: 103400 | G582: 80000 | I582: =dataset!$F582-dataset!$J582-dataset!$G582-dataset!$H582 -> 17000 | J582: =dataset!$G582*0.08 -> 6400 | K582: =dataset!$F582*12 -> 1240800 | L582: =IF(dataset!$G582>=200000,38%,IF(dataset!$G582<=145000,12.3%,)) -> 0.123 | M582: =dataset!$G582*L583*12 -> 118080 | N582: =IF(Payroll_Data_Analysis[[#This Row],[Annual KPI Bonus Reserve]]<=2979000,Payroll_Data_Analysis[[#This Row],[Annual KPI Bonus Reserve]]*0.302,2979000*0.302+(Payroll_Data_Analysis[[#This Row],[Annual KPI Bonus Reserve]]-2979000)*0.151) -> 35660.16 | O582: =dataset!$K582+dataset!$M582 -> 1358880 | P582: =Payroll_Data_Analysis[[#This Row],[Annual Salary + KPI Bonus]]/12/29.3*31 -> 119810.24 | Q582: =IF(Payroll_Data_Analysis[[#This Row],[Vacation Reserve]]<=2979000,Payroll_Data_Analysis[[#This Row],[Vacation Reserve]]*0.302,2979000*0.302+(Payroll_Data_Analysis[[#This Row],[Vacation Reserve]]-2979000)*0.151) -> 36182.692 | R582: =Payroll_Data_Analysis[[#This Row],[Monthly Salary]]*11 -> 1137400 | S582: =IF(Payroll_Data_Analysis[[#This Row],[11-Month Salary]]<=2979000,Payroll_Data_Analysis[[#This Row],[11-Month Salary]]*0.302,2979000*0.302+(Payroll_Data_Analysis[[#This Row],[11-Month Salary]]-2979000)*0.151) -> 343494.8 | T582: =IF(Payroll_Data_Analysis[[#This Row],[Base Salary (Monthly)]]>=200000,69507,IF(Payroll_Data_Analysis[[#This Row],[Base Salary (Monthly)]]>=145000,52684,35103)) -> 35103 | U582: =Payroll_Data_Analysis[[#This Row],[Annual KPI Bonus Reserve]]+Payroll_Data_Analysis[[#This Row],[Vacation Reserve]]+Payroll_Data_Analysis[[#This Row],[11-Month Salary]] -> 1375290.2 | V582: =Payroll_Data_Analysis[[#This Row],[Payroll Taxes (KPI Bonus)]]+Payroll_Data_Analysis[[#This Row],[Payroll Taxes (Vacation)]]+Payroll_Data_Analysis[[#This Row],[Payroll Taxes (Salary)]] -> 415337.65 | W582: =Payroll_Data_Analysis[[#This Row],[Total Payroll]]+Payroll_Data_Analysis[[#This Row],[Total Payroll Taxes]] -> 1790627.9
A583: Support Services | B583: Emp_583 | C583: Senior Engineer | D583: =VLOOKUP(Payroll_Data_Analysis[[#This Row],[Position]],Position_Map!$A$2:$B$58,2,FALSE) -> Engineering | E583: 1 | F583: 103400 | G583: 80000 | I583: =dataset!$F583-dataset!$J583-dataset!$G583-dataset!$H583 -> 17000 | J583: =dataset!$G583*0.08 -> 6400 | K583: =dataset!$F583*12 -> 1240800 | L583: =IF(dataset!$G583>=200000,38%,IF(dataset!$G583<=145000,12.3%,)) -> 0.123 | M583: =dataset!$G583*L584*12 -> 118080 | N583: =IF(Payroll_Data_Analysis[[#This Row],[Annual KPI Bonus Reserve]]<=2979000,Payroll_Data_Analysis[[#This Row],[Annual KPI Bonus Reserve]]*0.302,2979000*0.302+(Payroll_Data_Analysis[[#This Row],[Annual KPI Bonus Reserve]]-2979000)*0.151) -> 35660.16 | O583: =dataset!$K583+dataset!$M583 -> 1358880 | P583: =Payroll_Data_Analysis[[#This Row],[Annual Salary + KPI Bonus]]/12/29.3*31 -> 119810.24 | Q583: =IF(Payroll_Data_Analysis[[#This Row],[Vacation Reserve]]<=2979000,Payroll_Data_Analysis[[#This Row],[Vacation Reserve]]*0.302,2979000*0.302+(Payroll_Data_Analysis[[#This Row],[Vacation Reserve]]-2979000)*0.151) -> 36182.692 | R583: =Payroll_Data_Analysis[[#This Row],[Monthly Salary]]*11 -> 1137400 | S583: =IF(Payroll_Data_Analysis[[#This Row],[11-Month Salary]]<=2979000,Payroll_Data_Analysis[[#This Row],[11-Month Salary]]*0.302,2979000*0.302+(Payroll_Data_Analysis[[#This Row],[11-Month Salary]]-2979000)*0.151) -> 343494.8 | T583: =IF(Payroll_Data_Analysis[[#This Row],[Base Salary (Monthly)]]>=200000,69507,IF(Payroll_Data_Analysis[[#This Row],[Base Salary (Monthly)]]>=145000,52684,35103)) -> 35103 | U583: =Payroll_Data_Analysis[[#This Row],[Annual KPI Bonus Reserve]]+Payroll_Data_Analysis[[#This Row],[Vacation Reserve]]+Payroll_Data_Analysis[[#This Row],[11-Month Salary]] -> 1375290.2 | V583: =Payroll_Data_Analysis[[#This Row],[Payroll Taxes (KPI Bonus)]]+Payroll_Data_Analysis[[#This Row],[Payroll Taxes (Vacation)]]+Payroll_Data_Analysis[[#This Row],[Payroll Taxes (Salary)]] -> 415337.65 | W583: =Payroll_Data_Analysis[[#This Row],[Total Payroll]]+Payroll_Data_Analysis[[#This Row],[Total Payroll Taxes]] -> 1790627.9
... A593: Support Services | B593: Emp_593 | C593: Custodian | D593: =VLOOKUP(Payroll_Data_Analysis[[#This Row],[Position]],Position_Map!$A$2:$B$58,2,FALSE) -> Facilities | E593: 1 | F593: 48800 | G593: 35000 | I593: =dataset!$F593-dataset!$J593-dataset!$G593-dataset!$H593 -> 11000 | J593: =dataset!$G593*0.08 -> 2800 | K593: =dataset!$F593*12 -> 585600 | L593: =IF(dataset!$G593>=200000,38%,IF(dataset!$G593<=145000,12.3%,)) -> 0.123 | M593: =dataset!$G593*L594*12 -> 159600 | N593: =IF(Payroll_Data_Analysis[[#This Row],[Annual KPI Bonus Reserve]]<=2979000,Payroll_Data_Analysis[[#This Row],[Annual KPI Bonus Reserve]]*0.302,2979000*0.302+(Payroll_Data_Analysis[[#This Row],[Annual KPI Bonus Reserve]]-2979000)*0.151) -> 48199.2 | O593: =dataset!$K593+dataset!$M593 -> 745200 | P593: =Payroll_Data_Analysis[[#This Row],[Annual Salary + KPI Bonus]]/12/29.3*31 -> 65703.072 | Q593: =IF(Payroll_Data_Analysis[[#This Row],[Vacation Reserve]]<=2979000,Payroll_Data_Analysis[[#This Row],[Vacation Reserve]]*0.302,2979000*0.302+(Payroll_Data_Analysis[[#This Row],[Vacation Reserve]]-2979000)*0.151) -> 19842.328 | R593: =Payroll_Data_Analysis[[#This Row],[Monthly Salary]]*11 -> 536800 | S593: =IF(Payroll_Data_Analysis[[#This Row],[11-Month Salary]]<=2979000,Payroll_Data_Analysis[[#This Row],[11-Month Salary]]*0.302,2979000*0.302+(Payroll_Data_Analysis[[#This Row],[11-Month Salary]]-2979000)*0.151) -> 162113.6 | T593: =IF(Payroll_Data_Analysis[[#This Row],[Base Salary (Monthly)]]>=200000,69507,IF(Payroll_Data_Analysis[[#This Row],[Base Salary (Monthly)]]>=145000,52684,35103)) -> 35103 | U593: =Payroll_Data_Analysis[[#This Row],[Annual KPI Bonus Reserve]]+Payroll_Data_Analysis[[#This Row],[Vacation Reserve]]+Payroll_Data_Analysis[[#This Row],[11-Month Salary]] -> 762103.07 | V593: =Payroll_Data_Analysis[[#This Row],[Payroll Taxes (KPI Bonus)]]+Payroll_Data_Analysis[[#This Row],[Payroll Taxes (Vacation)]]+Payroll_Data_Analysis[[#This Row],[Payroll Taxes (Salary)]] -> 230155.13 | W593: =Payroll_Data_Analysis[[#This Row],[Total Payroll]]+Payroll_Data_Analysis[[#This Row],[Total Payroll Taxes]] -> 992258.2
A594: Human Resources | B594: Emp_594 | C594: Head of Division | D594: =VLOOKUP(Payroll_Data_Analysis[[#This Row],[Position]],Position_Map!$A$2:$B$58,2,FALSE) -> Management | E594: 1 | F594: 308000 | G594: 200000 | H594: 20000 | I594: =dataset!$F594-dataset!$J594-dataset!$G594-dataset!$H594 -> 72000 | J594: =dataset!$G594*0.08 -> 16000 | K594: =dataset!$F594*12 -> 3696000 | L594: =IF(dataset!$G594>=200000,38%,IF(dataset!$G594<=145000,12.3%,)) -> 0.38 | M594: =dataset!$G594*L595*12 -> 295200 | N594: =IF(Payroll_Data_Analysis[[#This Row],[Annual KPI Bonus Reserve]]<=2979000,Payroll_Data_Analysis[[#This Row],[Annual KPI Bonus Reserve]]*0.302,2979000*0.302+(Payroll_Data_Analysis[[#This Row],[Annual KPI Bonus Reserve]]-2979000)*0.151) -> 89150.4 | O594: =dataset!$K594+dataset!$M594 -> 3991200 | P594: =Payroll_Data_Analysis[[#This Row],[Annual Salary + KPI Bonus]]/12/29.3*31 -> 351897.61 | Q594: =IF(Payroll_Data_Analysis[[#This Row],[Vacation Reserve]]<=2979000,Payroll_Data_Analysis[[#This Row],[Vacation Reserve]]*0.302,2979000*0.302+(Payroll_Data_Analysis[[#This Row],[Vacation Reserve]]-2979000)*0.151) -> 106273.08 | R594: =Payroll_Data_Analysis[[#This Row],[Monthly Salary]]*11 -> 3388000 | S594: =IF(Payroll_Data_Analysis[[#This Row],[11-Month Salary]]<=2979000,Payroll_Data_Analysis[[#This Row],[11-Month Salary]]*0.302,2979000*0.302+(Payroll_Data_Analysis[[#This Row],[11-Month Salary]]-2979000)*0.151) -> 961417 | T594: =IF(Payroll_Data_Analysis[[#This Row],[Base Salary (Monthly)]]>=200000,69507,IF(Payroll_Data_Analysis[[#This Row],[Base Salary (Monthly)]]>=145000,52684,35103)) -> 69507 | U594: =Payroll_Data_Analysis[[#This Row],[Annual KPI Bonus Reserve]]+Payroll_Data_Analysis[[#This Row],[Vacation Reserve]]+Payroll_Data_Analysis[[#This Row],[11-Month Salary]] -> 4035097.6 | V594: =Payroll_Data_Analysis[[#This Row],[Payroll Taxes (KPI Bonus)]]+Payroll_Data_Analysis[[#This Row],[Payroll Taxes (Vacation)]]+Payroll_Data_Analysis[[#This Row],[Payroll Taxes (Salary)]] -> 1156840.5 | W594: =Payroll_Data_Analysis[[#This Row],[Total Payroll]]+Payroll_Data_Analysis[[#This Row],[Total Payroll Taxes]] -> 5191938.1
A595: Human Resources | B595: Emp_595 | C595: Deputy Head of Division – Department Manager | D595: =VLOOKUP(Payroll_Data_Analysis[[#This Row],[Position]],Position_Map!$A$2:$B$58,2,FALSE) -> Management | E595: 1 | F595: 261600 | G595: 145000 | I595: =dataset!$F595-dataset!$J595-dataset!$G595-dataset!$H595 -> 105000 | J595: =dataset!$G595*0.08 -> 11600 | K595: =dataset!$F595*12 -> 3139200 | L595: =IF(dataset!$G595>=200000,38%,IF(dataset!$G595<=145000,12.3%,)) -> 0.123 | M595: =dataset!$G595*L596*12 -> 214020 | N595: =IF(Payroll_Data_Analysis[[#This Row],[Annual KPI Bonus Reserve]]<=2979000,Payroll_Data_Analysis[[#This Row],[Annual KPI Bonus Reserve]]*0.302,2979000*0.302+(Payroll_Data_Analysis[[#This Row],[Annual KPI Bonus Reserve]]-2979000)*0.151) -> 64634.04 | O595: =dataset!$K595+dataset!$M595 -> 3353220 | P595: =Payroll_Data_Analysis[[#This Row],[Annual Salary + KPI Bonus]]/12/29.3*31 -> 295647.95 | Q595: =IF(Payroll_Data_Analysis[[#This Row],[Vacation Reserve]]<=2979000,Payroll_Data_Analysis[[#This Row],[Vacation Reserve]]*0.302,2979000*0.302+(Payroll_Data_Analysis[[#This Row],[Vacation Reserve]]-2979000)*0.151) -> 89285.682 | R595: =Payroll_Data_Analysis[[#This Row],[Monthly Salary]]*11 -> 2877600 | S595: =IF(Payroll_Data_Analysis[[#This Row],[11-Month Salary]]<=2979000,Payroll_Data_Analysis[[#This Row],[11-Month Salary]]*0.302,2979000*0.302+(Payroll_Data_Analysis[[#This Row],[11-Month Salary]]-2979000)*0.151) -> 869035.2 | T595: =IF(Payroll_Data_Analysis[[#This Row],[Base Salary (Monthly)]]>=200000,69507,IF(Payroll_Data_Analysis[[#This Row],[Base Salary (Monthly)]]>=145000,52684,35103)) -> 52684 | U595: =Payroll_Data_Analysis[[#This Row],[Annual KPI Bonus Reserve]]+Payroll_Data_Analysis[[#This Row],[Vacation Reserve]]+Payroll_Data_Analysis[[#This Row],[11-Month Salary]] -> 3387268 | V595: =Payroll_Data_Analysis[[#This Row],[Payroll Taxes (KPI Bonus)]]+Payroll_Data_Analysis[[#This Row],[Payroll Taxes (Vacation)]]+Payroll_Data_Analysis[[#This Row],[Payroll Taxes (Salary)]] -> 1022954.9 | W595: =Payroll_Data_Analysis[[#This Row],[Total Payroll]]+Payroll_Data_Analysis[[#This Row],[Total Payroll Taxes]] -> 4410222.9
A596: Human Resources | B596: Emp_596 | C596: Deputy Head of Division | D596: =VLOOKUP(Payroll_Data_Analysis[[#This Row],[Position]],Position_Map!$A$2:$B$58,2,FALSE) -> Management | E596: 1 | F596: 221600 | G596: 145000 | I596: =dataset!$F596-dataset!$J596-dataset!$G596-dataset!$H596 -> 65000 | J596: =dataset!$G596*0.08 -> 11600 | K596: =dataset!$F596*12 -> 2659200 | L596: =IF(dataset!$G596>=200000,38%,IF(dataset!$G596<=145000,12.3%,)) -> 0.123 | M596: =dataset!$G596*L597*12 -> 214020 | N596: =IF(Payroll_Data_Analysis[[#This Row],[Annual KPI Bonus Reserve]]<=2979000,Payroll_Data_Analysis[[#This Row],[Annual KPI Bonus Reserve]]*0.302,2979000*0.302+(Payroll_Data_Analysis[[#This Row],[Annual KPI Bonus Reserve]]-2979000)*0.151) -> 64634.04 | O596: =dataset!$K596+dataset!$M596 -> 2873220 | P596: =Payroll_Data_Analysis[[#This Row],[Annual Salary + KPI Bonus]]/12/29.3*31 -> 253327.13 | Q596: =IF(Payroll_Data_Analysis[[#This Row],[Vacation Reserve]]<=2979000,Payroll_Data_Analysis[[#This Row],[Vacation Reserve]]*0.302,2979000*0.302+(Payroll_Data_Analysis[[#This Row],[Vacation Reserve]]-2979000)*0.151) -> 76504.794 | R596: =Payroll_Data_Analysis[[#This Row],[Monthly Salary]]*11 -> 2437600 | S596: =IF(Payroll_Data_Analysis[[#This Row],[11-Month Salary]]<=2979000,Payroll_Data_Analysis[[#This Row],[11-Month Salary]]*0.302,2979000*0.302+(Payroll_Data_Analysis[[#This Row],[11-Month Salary]]-2979000)*0.151) -> 736155.2 | T596: =IF(Payroll_Data_Analysis[[#This Row],[Base Salary (Monthly)]]>=200000,69507,IF(Payroll_Data_Analysis[[#This Row],[Base Salary (Monthly)]]>=145000,52684,35103)) -> 52684 | U596: =Payroll_Data_Analysis[[#This Row],[Annual KPI Bonus Reserve]]+Payroll_Data_Analysis[[#This Row],[Vacation Reserve]]+Payroll_Data_Analysis[[#This Row],[11-Month Salary]] -> 2904947.1 | V596: =Payroll_Data_Analysis[[#This Row],[Payroll Taxes (KPI Bonus)]]+Payroll_Data_Analysis[[#This Row],[Payroll Taxes (Vacation)]]+Payroll_Data_Analysis[[#This Row],[Payroll Taxes (Salary)]] -> 877294.03 | W596: =Payroll_Data_Analysis[[#This Row],[Total Payroll]]+Payroll_Data_Analysis[[#This Row],[Total Payroll Taxes]] -> 3782241.2
A597: Human Resources | B597: Emp_597 | C597: Deputy Head of Division | D597: =VLOOKUP(Payroll_Data_Analysis[[#This Row],[Position]],Position_Map!$A$2:$B$58,2,FALSE) -> Management | E597: 1 | F597: 148000 | G597: 100000 | I597: =dataset!$F597-dataset!$J597-dataset!$G597-dataset!$H597 -> 40000 | J597: =dataset!$G597*0.08 -> 8000 | K597: =dataset!$F597*12 -> 1776000 | L597: =IF(dataset!$G597>=200000,38%,IF(dataset!$G597<=145000,12.3%,)) -> 0.123 | M597: =dataset!$G597*L598*12 -> 147600 | N597: =IF(Payroll_Data_Analysis[[#This Row],[Annual KPI Bonus Reserve]]<=2979000,Payroll_Data_Analysis[[#This Row],[Annual KPI Bonus Reserve]]*0.302,2979000*0.302+(Payroll_Data_Analysis[[#This Row],[Annual KPI Bonus Reserve]]-2979000)*0.151) -> 44575.2 | O597: =dataset!$K597+dataset!$M597 -> 1923600 | P597: =Payroll_Data_Analysis[[#This Row],[Annual Salary + KPI Bonus]]/12/29.3*31 -> 169600.68 | Q597: =IF(Payroll_Data_Analysis[[#This Row],[Vacation Reserve]]<=2979000,Payroll_Data_Analysis[[#This Row],[Vacation Reserve]]*0.302,2979000*0.302+(Payroll_Data_Analysis[[#This Row],[Vacation Reserve]]-2979000)*0.151) -> 51219.406 | R597: =Payroll_Data_Analysis[[#This Row],[Monthly Salary]]*11 -> 1628000 | S597: =IF(Payroll_Data_Analysis[[#This Row],[11-Month Salary]]<=2979000,Payroll_Data_Analysis[[#This Row],[11-Month Salary]]*0.302,2979000*0.302+(Payroll_Data_Analysis[[#This Row],[11-Month Salary]]-2979000)*0.151) -> 491656 | T597: =IF(Payroll_Data_Analysis[[#This Row],[Base Salary (Monthly)]]>=200000,69507,IF(Payroll_Data_Analysis[[#This Row],[Base Salary (Monthly)]]>=145000,52684,35103)) -> 35103 | U597: =Payroll_Data_Analysis[[#This Row],[Annual KPI Bonus Reserve]]+Payroll_Data_Analysis[[#This Row],[Vacation Reserve]]+Payroll_Data_Analysis[[#This Row],[11-Month Salary]] -> 1945200.7 | V597: =Payroll_Data_Analysis[[#This Row],[Payroll Taxes (KPI Bonus)]]+Payroll_Data_Analysis[[#This Row],[Payroll Taxes (Vacation)]]+Payroll_Data_Analysis[[#This Row],[Payroll Taxes (Salary)]] -> 587450.61 | W597: =Payroll_Data_Analysis[[#This Row],[Total Payroll]]+Payroll_Data_Analysis[[#This Row],[Total Payroll Taxes]] -> 2532651.3
A598: Human Resources | B598: Emp_598 | C598: Deputy Head of Division – Department Manager | D598: =VLOOKUP(Payroll_Data_Analysis[[#This Row],[Position]],Position_Map!$A$2:$B$58,2,FALSE) -> Management | E598: 1 | F598: 178000 | G598: 100000 | I598: =dataset!$F598-dataset!$J598-dataset!$G598-dataset!$H598 -> 70000 | J598: =dataset!$G598*0.08 -> 8000 | K598: =dataset!$F598*12 -> 2136000 | L598: =IF(dataset!$G598>=200000,38%,IF(dataset!$G598<=145000,12.3%,)) -> 0.123 | M598: =dataset!$G598*L599*12 -> 147600 | N598: =IF(Payroll_Data_Analysis[[#This Row],[Annual KPI Bonus Reserve]]<=2979000,Payroll_Data_Analysis[[#This Row],[Annual KPI Bonus Reserve]]*0.302,2979000*0.302+(Payroll_Data_Analysis[[#This Row],[Annual KPI Bonus Reserve]]-2979000)*0.151) -> 44575.2 | O598: =dataset!$K598+dataset!$M598 -> 2283600 | P598: =Payroll_Data_Analysis[[#This Row],[Annual Salary + KPI Bonus]]/12/29.3*31 -> 201341.3 | Q598: =IF(Payroll_Data_Analysis[[#This Row],[Vacation Reserve]]<=2979000,Payroll_Data_Analysis[[#This Row],[Vacation Reserve]]*0.302,2979000*0.302+(Payroll_Data_Analysis[[#This Row],[Vacation Reserve]]-2979000)*0.151) -> 60805.072 | R598: =Payroll_Data_Analysis[[#This Row],[Monthly Salary]]*11 -> 1958000 | S598: =IF(Payroll_Data_Analysis[[#This Row],[11-Month Salary]]<=2979000,Payroll_Data_Analysis[[#This Row],[11-Month Salary]]*0.302,2979000*0.302+(Payroll_Data_Analysis[[#This Row],[11-Month Salary]]-2979000)*0.151) -> 591316 | T598: =IF(Payroll_Data_Analysis[[#This Row],[Base Salary (Monthly)]]>=200000,69507,IF(Payroll_Data_Analysis[[#This Row],[Base Salary (Monthly)]]>=145000,52684,35103)) -> 35103 | U598: =Payroll_Data_Analysis[[#This Row],[Annual KPI Bonus Reserve]]+Payroll_Data_Analysis[[#This Row],[Vacation Reserve]]+Payroll_Data_Analysis[[#This Row],[11-Month Salary]] -> 2306941.3 | V598: =Payroll_Data_Analysis[[#This Row],[Payroll Taxes (KPI Bonus)]]+Payroll_Data_Analysis[[#This Row],[Payroll Taxes (Vacation)]]+Payroll_Data_Analysis[[#This Row],[Payroll Taxes (Salary)]] -> 696696.27 | W598: =Payroll_Data_Analysis[[#This Row],[Total Payroll]]+Payroll_Data_Analysis[[#This Row],[Total Payroll Taxes]] -> 3003637.6
A599: Human Resources | B599: Emp_599 | C599: Deputy Department Manager | D599: =VLOOKUP(Payroll_Data_Analysis[[#This Row],[Position]],Position_Map!$A$2:$B$58,2,FALSE) -> Management | E599: 1 | F599: 178000 | G599: 100000 | I599: =dataset!$F599-dataset!$J599-dataset!$G599-dataset!$H599 -> 70000 | J599: =dataset!$G599*0.08 -> 8000 | K599: =dataset!$F599*12 -> 2136000 | L599: =IF(dataset!$G599>=200000,38%,IF(dataset!$G599<=145000,12.3%,)) -> 0.123 | M599: =dataset!$G599*L600*12 -> 147600 | N599: =IF(Payroll_Data_Analysis[[#This Row],[Annual KPI Bonus Reserve]]<=2979000,Payroll_Data_Analysis[[#This Row],[Annual KPI Bonus Reserve]]*0.302,2979000*0.302+(Payroll_Data_Analysis[[#This Row],[Annual KPI Bonus Reserve]]-2979000)*0.151) -> 44575.2 | O599: =dataset!$K599+dataset!$M599 -> 2283600 | P599: =Payroll_Data_Analysis[[#This Row],[Annual Salary + KPI Bonus]]/12/29.3*31 -> 201341.3 | Q599: =IF(Payroll_Data_Analysis[[#This Row],[Vacation Reserve]]<=2979000,Payroll_Data_Analysis[[#This Row],[Vacation Reserve]]*0.302,2979000*0.302+(Payroll_Data_Analysis[[#This Row],[Vacation Reserve]]-2979000)*0.151) -> 60805.072 | R599: =Payroll_Data_Analysis[[#This Row],[Monthly Salary]]*11 -> 1958000 | S599: =IF(Payroll_Data_Analysis[[#This Row],[11-Month Salary]]<=2979000,Payroll_Data_Analysis[[#This Row],[11-Month Salary]]*0.302,2979000*0.302+(Payroll_Data_Analysis[[#This Row],[11-Month Salary]]-2979000)*0.151) -> 591316 | T599: =IF(Payroll_Data_Analysis[[#This Row],[Base Salary (Monthly)]]>=200000,69507,IF(Payroll_Data_Analysis[[#This Row],[Base Salary (Monthly)]]>=145000,52684,35103)) -> 35103 | U599: =Payroll_Data_Analysis[[#This Row],[Annual KPI Bonus Reserve]]+Payroll_Data_Analysis[[#This Row],[Vacation Reserve]]+Payroll_Data_Analysis[[#This Row],[11-Month Salary]] -> 2306941.3 | V599: =Payroll_Data_Analysis[[#This Row],[Payroll Taxes (KPI Bonus)]]+Payroll_Data_Analysis[[#This Row],[Payroll Taxes (Vacation)]]+Payroll_Data_Analysis[[#This Row],[Payroll Taxes (Salary)]] -> 696696.27 | W599: =Payroll_Data_Analysis[[#This Row],[Total Payroll]]+Payroll_Data_Analysis[[#This Row],[Total Payroll Taxes]] -> 3003637.6
A600: Human Resources | B600: Emp_600 | C600: Lead Specialist | D600: =VLOOKUP(Payroll_Data_Analysis[[#This Row],[Position]],Position_Map!$A$2:$B$58,2,FALSE) -> Professional | E600: 1 | F600: 104800 | G600: 60000 | I600: =dataset!$F600-dataset!$J600-dataset!$G600-dataset!$H600 -> 40000 | J600: =dataset!$G600*0.08 -> 4800 | K600: =dataset!$F600*12 -> 1257600 | L600: =IF(dataset!$G600>=200000,38%,IF(dataset!$G600<=145000,12.3%,)) -> 0.123 | M600: =dataset!$G600*L601*12 -> 88560 | N600: =IF(Payroll_Data_Analysis[[#This Row],[Annual KPI Bonus Reserve]]<=2979000,Payroll_Data_Analysis[[#This Row],[Annual KPI Bonus Reserve]]*0.302,2979000*0.302+(Payroll_Data_Analysis[[#This Row],[Annual KPI Bonus Reserve]]-2979000)*0.151) -> 26745.12 | O600: =dataset!$K600+dataset!$M600 -> 1346160 | P600: =Payroll_Data_Analysis[[#This Row],[Annual Salary + KPI Bonus]]/12/29.3*31 -> 118688.74 | Q600: =IF(Payroll_Data_Analysis[[#This Row],[Vacation Reserve]]<=2979000,Payroll_Data_Analysis[[#This Row],[Vacation Reserve]]*0.302,2979000*0.302+(Payroll_Data_Analysis[[#This Row],[Vacation Reserve]]-2979000)*0.151) -> 35843.999 | R600: =Payroll_Data_Analysis[[#This Row],[Monthly Salary]]*11 -> 1152800 | S600: =IF(Payroll_Data_Analysis[[#This Row],[11-Month Salary]]<=2979000,Payroll_Data_Analysis[[#This Row],[11-Month Salary]]*0.302,2979000*0.302+(Payroll_Data_Analysis[[#This Row],[11-Month Salary]]-2979000)*0.151) -> 348145.6 | T600: =IF(Payroll_Data_Analysis[[#This Row],[Base Salary (Monthly)]]>=200000,69507,IF(Payroll_Data_Analysis[[#This Row],[Base Salary (Monthly)]]>=145000,52684,35103)) -> 35103 | U600: =Payroll_Data_Analysis[[#This Row],[Annual KPI Bonus Reserve]]+Payroll_Data_Analysis[[#This Row],[Vacation Reserve]]+Payroll_Data_Analysis[[#This Row],[11-Month Salary]] -> 1360048.7 | V600: =Payroll_Data_Analysis[[#This Row],[Payroll Taxes (KPI Bonus)]]+Payroll_Data_Analysis[[#This Row],[Payroll Taxes (Vacation)]]+Payroll_Data_Analysis[[#This Row],[Payroll Taxes (Salary)]] -> 410734.72 | W600: =Payroll_Data_Analysis[[#This Row],[Total Payroll]]+Payroll_Data_Analysis[[#This Row],[Total Payroll Taxes]] -> 1770783.5
A601: Human Resources | B601: Emp_601 | C601: Department Manager | D601: =VLOOKUP(Payroll_Data_Analysis[[#This Row],[Position]],Position_Map!$A$2:$B$58,2,FALSE) -> Management | E601: 1 | F601: 221600 | G601: 145000 | I601: =dataset!$F601-dataset!$J601-dataset!$G601-dataset!$H601 -> 65000 | J601: =dataset!$G601*0.08 -> 11600 | K601: =dataset!$F601*12 -> 2659200 | L601: =IF(dataset!$G601>=200000,38%,IF(dataset!$G601<=145000,12.3%,)) -> 0.123 | M601: =dataset!$G601*L602*12 -> 214020 | N601: =IF(Payroll_Data_Analysis[[#This Row],[Annual KPI Bonus Reserve]]<=2979000,Payroll_Data_Analysis[[#This Row],[Annual KPI Bonus Reserve]]*0.302,2979000*0.302+(Payroll_Data_Analysis[[#This Row],[Annual KPI Bonus Reserve]]-2979000)*0.151) -> 64634.04 | O601: =dataset!$K601+dataset!$M601 -> 2873220 | P601: =Payroll_Data_Analysis[[#This Row],[Annual Salary + KPI Bonus]]/12/29.3*31 -> 253327.13 | Q601: =IF(Payroll_Data_Analysis[[#This Row],[Vacation Reserve]]<=2979000,Payroll_Data_Analysis[[#This Row],[Vacation Reserve]]*0.302,2979000*0.302+(Payroll_Data_Analysis[[#This Row],[Vacation Reserve]]-2979000)*0.151) -> 76504.794 | R601: =Payroll_Data_Analysis[[#This Row],[Monthly Salary]]*11 -> 2437600 | S601: =IF(Payroll_Data_Analysis[[#This Row],[11-Month Salary]]<=2979000,Payroll_Data_Analysis[[#This Row],[11-Month Salary]]*0.302,2979000*0.302+(Payroll_Data_Analysis[[#This Row],[11-Month Salary]]-2979000)*0.151) -> 736155.2 | T601: =IF(Payroll_Data_Analysis[[#This Row],[Base Salary (Monthly)]]>=200000,69507,IF(Payroll_Data_Analysis[[#This Row],[Base Salary (Monthly)]]>=145000,52684,35103)) -> 52684 | U601: =Payroll_Data_Analysis[[#This Row],[Annual KPI Bonus Reserve]]+Payroll_Data_Analysis[[#This Row],[Vacation Reserve]]+Payroll_Data_Analysis[[#This Row],[11-Month Salary]] -> 2904947.1 | V601: =Payroll_Data_Analysis[[#This Row],[Payroll Taxes (KPI Bonus)]]+Payroll_Data_Analysis[[#This Row],[Payroll Taxes (Vacation)]]+Payroll_Data_Analysis[[#This Row],[Payroll Taxes (Salary)]] -> 877294.03 | W601: =Payroll_Data_Analysis[[#This Row],[Total Payroll]]+Payroll_Data_Analysis[[#This Row],[Total Payroll Taxes]] -> 3782241.2
A602: Human Resources | B602: Emp_602 | C602: Deputy Department Manager | D602: =VLOOKUP(Payroll_Data_Analysis[[#This Row],[Position]],Position_Map!$A$2:$B$58,2,FALSE) -> Management | E602: 1 | F602: 221600 | G602: 145000 | I602: =dataset!$F602-dataset!$J602-dataset!$G602-dataset!$H602 -> 65000 | J602: =dataset!$G602*0.08 -> 11600 | K602: =dataset!$F602*12 -> 2659200 | L602: =IF(dataset!$G602>=200000,38%,IF(dataset!$G602<=145000,12.3%,)) -> 0.123 | M602: =dataset!$G602*L603*12 -> 214020 | N602: =IF(Payroll_Data_Analysis[[#This Row],[Annual KPI Bonus Reserve]]<=2979000,Payroll_Data_Analysis[[#This Row],[Annual KPI Bonus Reserve]]*0.302,2979000*0.302+(Payroll_Data_Analysis[[#This Row],[Annual KPI Bonus Reserve]]-2979000)*0.151) -> 64634.04 | O602: =dataset!$K602+dataset!$M602 -> 2873220 | P602: =Payroll_Data_Analysis[[#This Row],[Annual Salary + KPI Bonus]]/12/29.3*31 -> 253327.13 | Q602: =IF(Payroll_Data_Analysis[[#This Row],[Vacation Reserve]]<=2979000,Payroll_Data_Analysis[[#This Row],[Vacation Reserve]]*0.302,2979000*0.302+(Payroll_Data_Analysis[[#This Row],[Vacation Reserve]]-2979000)*0.151) -> 76504.794 | R602: =Payroll_Data_Analysis[[#This Row],[Monthly Salary]]*11 -> 2437600 | S602: =IF(Payroll_Data_Analysis[[#This Row],[11-Month Salary]]<=2979000,Payroll_Data_Analysis[[#This Row],[11-Month Salary]]*0.302,2979000*0.302+(Payroll_Data_Analysis[[#This Row],[11-Month Salary]]-2979000)*0.151) -> 736155.2 | T602: =IF(Payroll_Data_Analysis[[#This Row],[Base Salary (Monthly)]]>=200000,69507,IF(Payroll_Data_Analysis[[#This Row],[Base Salary (Monthly)]]>=145000,52684,35103)) -> 52684 | U602: =Payroll_Data_Analysis[[#This Row],[Annual KPI Bonus Reserve]]+Payroll_Data_Analysis[[#This Row],[Vacation Reserve]]+Payroll_Data_Analysis[[#This Row],[11-Month Salary]] -> 2904947.1 | V602: =Payroll_Data_Analysis[[#This Row],[Payroll Taxes (KPI Bonus)]]+Payroll_Data_Analysis[[#This Row],[Payroll Taxes (Vacation)]]+Payroll_Data_Analysis[[#This Row],[Payroll Taxes (Salary)]] -> 877294.03 | W602: =Payroll_Data_Analysis[[#This Row],[Total Payroll]]+Payroll_Data_Analysis[[#This Row],[Total Payroll Taxes]] -> 3782241.2
A603: Human Resources | B603: Emp_603 | C603: Senior Specialist | D603: =VLOOKUP(Payroll_Data_Analysis[[#This Row],[Position]],Position_Map!$A$2:$B$58,2,FALSE) -> Professional | E603: 1 | F603: 138000 | G603: 100000 | I603: =dataset!$F603-dataset!$J603-dataset!$G603-dataset!$H603 -> 30000 | J603: =dataset!$G603*0.08 -> 8000 | K603: =dataset!$F603*12 -> 1656000 | L603: =IF(dataset!$G603>=200000,38%,IF(dataset!$G603<=145000,12.3%,)) -> 0.123 | M603: =dataset!$G603*L604*12 -> 456000 | N603: =IF(Payroll_Data_Analysis[[#This Row],[Annual KPI Bonus Reserve]]<=2979000,Payroll_Data_Analysis[[#This Row],[Annual KPI Bonus Reserve]]*0.302,2979000*0.302+(Payroll_Data_Analysis[[#This Row],[Annual KPI Bonus Reserve]]-2979000)*0.151) -> 137712 | O603: =dataset!$K603+dataset!$M603 -> 2112000 | P603: =Payroll_Data_Analysis[[#This Row],[Annual Salary + KPI Bonus]]/12/29.3*31 -> 186211.6 | Q603: =IF(Payroll_Data_Analysis[[#This Row],[Vacation Reserve]]<=2979000,Payroll_Data_Analysis[[#This Row],[Vacation Reserve]]*0.302,2979000*0.302+(Payroll_Data_Analysis[[#This Row],[Vacation Reserve]]-2979000)*0.151) -> 56235.904 | R603: =Payroll_Data_Analysis[[#This Row],[Monthly Salary]]*11 -> 1518000 | S603: =IF(Payroll_Data_Analysis[[#This Row],[11-Month Salary]]<=2979000,Payroll_Data_Analysis[[#This Row],[11-Month Salary]]*0.302,2979000*0.302+(Payroll_Data_Analysis[[#This Row],[11-Month Salary]]-2979000)*0.151) -> 458436 | T603: =IF(Payroll_Data_Analysis[[#This Row],[Base Salary (Monthly)]]>=200000,69507,IF(Payroll_Data_Analysis[[#This Row],[Base Salary (Monthly)]]>=145000,52684,35103)) -> 35103 | U603: =Payroll_Data_Analysis[[#This Row],[Annual KPI Bonus Reserve]]+Payroll_Data_Analysis[[#This Row],[Vacation Reserve]]+Payroll_Data_Analysis[[#This Row],[11-Month Salary]] -> 2160211.6 | V603: =Payroll_Data_Analysis[[#This Row],[Payroll Taxes (KPI Bonus)]]+Payroll_Data_Analysis[[#This Row],[Payroll Taxes (Vacation)]]+Payroll_Data_Analysis[[#This Row],[Payroll Taxes (Salary)]] -> 652383.9 | W603: =Payroll_Data_Analysis[[#This Row],[Total Payroll]]+Payroll_Data_Analysis[[#This Row],[Total Payroll Taxes]] -> 2812595.5
